Workbook

Sheet Summary
A1: Property Details | D1: Acquisition Loan Information | G1: Summary Details | J1: Sources (at Close)
A2: Year Built | B2: 2010 | D2: Loan Amount | E2: =E3*B20 -> 26000000 | G2: Purchase Price | H2: =B20 -> 40000000 | J2: Equity | K2: =K11-K3 -> 14710000
A3: Number of Units | B3: 100 | D3: LTV | E3: 0.65 | G3: Going-In Cap Rate | H3: =B24 -> 0.05 | J3: Acquisition Loan Proceeds | K3: =E2 -> 26000000
A4: Number of Buildings | B4: 10 | D4: Going-In DSCR | E4: 1.25 | G4: Purchase Price/Unit | H4: =B21 -> 400000 | J4: Total Sources | K4: =SUM(K2:K3) -> 40710000
A5: Net Rentable SF | B5: 150000 | D5: Going-In Debt Yield | E5: 0.075 | G5: Purchase Price/SF | H5: =H2/B5 -> 266.66667
A6: Average Unit Size | B6: =+B5/B3 -> 1500 | D6: Interest Rate | E6: 0.04 | G6: Total Cost of Project | H6: 42000000 | J6: Uses (at Close)
A7: Net Acres | B7: 5 | D7: Interest-Only Period | E7: 36 | G7: Total Cost/Unit | H7: =H6/B3 -> 420000 | J7: Purchase Price | K7: =B20 -> 40000000
A8: Units Per Acre | B8: =+B3/B7 -> 20 | D8: Loan Fee (%) | E8: 0.01 | J8: Closing Costs | K8: =B22 -> 150000
A9: Street Address | B9: 555 Main Street | D9: Amortization | E9: 360 | G9: Renovation Details | J9: Up-Front Working Capital | K9: =B23 -> 300000
A10: City/State/Zip | B10: San Francisco, CA | D10: Term | E10: 60 | G10: Total Construction Costs | H10: 1000000 | J10: Acquisition Loan Fees | K10: =E8*E2 -> 260000
G11: Total Construction Costs/Unit | H11: =H10/B3 -> 10000 | J11: Total Uses | K11: =SUM(K7:K10) -> 40710000
A12: Parking Information | D12: Refinance Information | G12: Exterior Renovation Costs | H12: 500000
A13: Uncovered Spaces | B13: 100 | D13: Refinance Month | E13: =E10 -> 60 | G13: Exterior Renovation Costs/Unit | H13: =H12/B3 -> 5000 | J13: Additional Equity Requirements (Post-Close)
A14: Carport Spaces | B14: 40 | D14: Loan Amount | E14: 30000000 | G14: Interior Renovation Costs | H14: 500000 | J14: Additional Equity Required | K14: 0
A15: Garage Spaces | B15: 25 | D15: Cap Rate Used For Valuation | E15: 0.06 | G15: Interior Renovation Costs/Unit | H15: =H14/B3 -> 5000
A16: Total Spaces | B16: =SUM(B13:B15) -> 165 | D16: LTV | E16: 0.65 | G16: Return on Cost | H16: 0.15 | J16: Sale Information
A17: Total Spaces/Unit | B17: =B16/B3 -> 1.65 | D17: Going-In DSCR | E17: 1.25 | J17: Closing Costs (%) | K17: 0.03
D18: Going-In Debt Yield | E18: 0.075 | G18: Sale Details | J18: Exit Cap Rate | K18: 0.06
A19: Acquisition Information | D19: Interest Rate | E19: 0.04 | G19: Exit Cap Rate | H19: 0.06 | J19: Hold Period | K19: 120
A20: Purchase Price | B20: 40000000 | D20: Interest-Only Period | E20: 36 | G20: Cap Rate Expansion/Year | H20: 0.001
A21: Purchase Price/Unit | B21: =B20/B3 -> 400000 | D21: Loan Fee (%) | E21: 0.01 | G21: Sale Price | H21: 50000000 | J21: Return Metrics
A22: Closing Costs | B22: 150000 | D22: Amortization | E22: 360 | G22: Sale Price/Unit | H22: =H21/B3 -> 500000 | J22: Internal Rate of Return (IRR) | K22: 0.16
A23: Up-Front Working Capital | B23: 300000 | G23: Costs of Sale | H23: 250000 | J23: Equity Multiple | K23: 2.5
A24: Going-In Cap Rate | B24: 0.05 | G24: Value CAGR | H24: 0.03 | J24: Average Cash-on-Cash | K24: 0.08
A25: Property Closing Date | B25: 44227 | G25: Levered IRR | H25: 0.16
G26: Levered Equity Multiple | H26: 2.5
G27: Levered Average Cash-on-Cash | H27: 0.08

Sheet Revenue
A1: Current In-Place Rents | G1: Stabilized Rents | M1: Renovation Premium | O1: Other Income/Unit/Month | S1: 1 | T1: =S1+1 -> 2 | U1: =T1+1 -> 3 | V1: =U1+1 -> 4 | W1: =V1+1 -> 5 | X1: =W1+1 -> 6 | Y1: =X1+1 -> 7 | Z1: =Y1+1 -> 8 | AA1: =Z1+1 -> 9 | ... AC1: =AB1+1 -> 11 | AF1: 1 | AG1: =AF1+1 -> 2 | AH1: =AG1+1 -> 3 | AI1: =AH1+1 -> 4 | AJ1: =AI1+1 -> 5 | AK1: =AJ1+1 -> 6 | AL1: =AK1+1 -> 7 | AM1: =AL1+1 -> 8 | AN1: =AM1+1 -> 9 | ... FG1: =FF1+1 -> 132
A2: # of Units | B2: Unit Type | C2: SF | D2: Rent/Month | E2: $/SF | G2: # of Units | H2: Unit Type | I2: SF | J2: Rent/Month | K2: $/SF | M2: Premium | O2: Laundry Income | P2: 10 | R2: Physical Vacancy | S2: 0.06 | T2: 0.055 | U2: 0.05 | V2: 0.05 | W2: 0.05 | X2: 0.05 | Y2: 0.05 | Z2: 0.05 | AA2: 0.05 | AB2: 0.05 | AC2: 0.05 | AE2: In-Place Rents | AF2: =A23*D23 -> 245000 | AG2: =AF2*(1+HLOOKUP(ROUNDUP(AF$1/12,0),$S$8:$AC$9,2,0))^(1/12) -> 245998.16 | AH2: =AG2*(1+HLOOKUP(ROUNDUP(AG$1/12,0),$S$8:$AC$9,2,0))^(1/12) -> 247000.39 | AI2: =AH2*(1+HLOOKUP(ROUNDUP(AH$1/12,0),$S$8:$AC$9,2,0))^(1/12) -> 248006.7 | AJ2: =AI2*(1+HLOOKUP(ROUNDUP(AI$1/12,0),$S$8:$AC$9,2,0))^(1/12) -> 249017.11 | AK2: =AJ2*(1+HLOOKUP(ROUNDUP(AJ$1/12,0),$S$8:$AC$9,2,0))^(1/12) -> 250031.63 | AL2: =AK2*(1+HLOOKUP(ROUNDUP(AK$1/12,0),$S$8:$AC$9,2,0))^(1/12) -> 251050.29 | AM2: =AL2*(1+HLOOKUP(ROUNDUP(AL$1/12,0),$S$8:$AC$9,2,0))^(1/12) -> 252073.1 | AN2: =AM2*(1+HLOOKUP(ROUNDUP(AM$1/12,0),$S$8:$AC$9,2,0))^(1/12) -> 253100.08 | ... FG2: =FF2*(1+HLOOKUP(ROUNDUP(FF$1/12,0),$S$8:$AC$9,2,0))^(1/12) -> 348220.21
A3: 50 | B3: 1BR - 1BA | C3: 1000 | D3: 1900 | E3: =IFERROR(D3/C3,0) -> 1.9 | G3: =A3 -> 50 | H3: =B3 -> 1BR - 1BA | I3: =C3 -> 1000 | J3: 2000 | K3: =IFERROR(J3/I3,0) -> 2 | M3: =J3-D3 -> 100 | O3: Late Fees | P3: 10 | R3: Bad Debt | S3: 0.01 | T3: 0.0075 | U3: 0.005 | V3: 0.005 | W3: 0.005 | X3: 0.005 | Y3: 0.005 | Z3: 0.005 | AA3: 0.005 | AB3: 0.005 | AC3: 0.005 | AE3: Stabilized Rents | AF3: =G23*J23 -> 256000 | AG3: =AF3*(1+HLOOKUP(ROUNDUP(AF$1/12,0),$S$8:$AC$9,2,0))^(1/12) -> 257042.98 | AH3: =AG3*(1+HLOOKUP(ROUNDUP(AG$1/12,0),$S$8:$AC$9,2,0))^(1/12) -> 258090.2 | AI3: =AH3*(1+HLOOKUP(ROUNDUP(AH$1/12,0),$S$8:$AC$9,2,0))^(1/12) -> 259141.69 | AJ3: =AI3*(1+HLOOKUP(ROUNDUP(AI$1/12,0),$S$8:$AC$9,2,0))^(1/12) -> 260197.47 | AK3: =AJ3*(1+HLOOKUP(ROUNDUP(AJ$1/12,0),$S$8:$AC$9,2,0))^(1/12) -> 261257.54 | AL3: =AK3*(1+HLOOKUP(ROUNDUP(AK$1/12,0),$S$8:$AC$9,2,0))^(1/12) -> 262321.94 | AM3: =AL3*(1+HLOOKUP(ROUNDUP(AL$1/12,0),$S$8:$AC$9,2,0))^(1/12) -> 263390.67 | AN3: =AM3*(1+HLOOKUP(ROUNDUP(AM$1/12,0),$S$8:$AC$9,2,0))^(1/12) -> 264463.76 | ... FG3: =FF3*(1+HLOOKUP(ROUNDUP(FF$1/12,0),$S$8:$AC$9,2,0))^(1/12) -> 363854.59
A4: 60 | B4: 2BR - 2BA | C4: 1500 | D4: 2500 | E4: =IFERROR(D4/C4,0) -> 1.6666667 | G4: =A4 -> 60 | H4: =B4 -> 2BR - 2BA | I4: =C4 -> 1500 | J4: 2600 | K4: =IFERROR(J4/I4,0) -> 1.7333333 | M4: =J4-D4 -> 100 | O4: Pet Rent | P4: 25 | R4: Concessions | S4: 0.01 | T4: 0.005 | U4: 0 | V4: 0 | W4: 0 | X4: 0 | Y4: 0 | Z4: 0 | AA4: 0 | AB4: 0 | AC4: 0 | AE4: % of Stabilized Units | AF4: =IF(AF1>=$P$16,1,IF(AND(AF1>=$P$15,AF1<$P$16),(AF1-$P$15+1)/$P$17,0)) -> 0 | AG4: =IF(AG1>=$P$16,1,IF(AND(AG1>=$P$15,AG1<$P$16),(AG1-$P$15+1)/$P$17,0)) -> 0 | AH4: =IF(AH1>=$P$16,1,IF(AND(AH1>=$P$15,AH1<$P$16),(AH1-$P$15+1)/$P$17,0)) -> 0 | AI4: =IF(AI1>=$P$16,1,IF(AND(AI1>=$P$15,AI1<$P$16),(AI1-$P$15+1)/$P$17,0)) -> 0 | AJ4: =IF(AJ1>=$P$16,1,IF(AND(AJ1>=$P$15,AJ1<$P$16),(AJ1-$P$15+1)/$P$17,0)) -> 0.090909091 | AK4: =IF(AK1>=$P$16,1,IF(AND(AK1>=$P$15,AK1<$P$16),(AK1-$P$15+1)/$P$17,0)) -> 0.18181818 | AL4: =IF(AL1>=$P$16,1,IF(AND(AL1>=$P$15,AL1<$P$16),(AL1-$P$15+1)/$P$17,0)) -> 0.27272727 | AM4: =IF(AM1>=$P$16,1,IF(AND(AM1>=$P$15,AM1<$P$16),(AM1-$P$15+1)/$P$17,0)) -> 0.36363636 | ... FG4: =IF(FG1>=$P$16,1,IF(AND(FG1>=$P$15,FG1<$P$16),(FG1-$P$15+1)/$P$17,0)) -> 1
A5: 0 | B5: 2BR - 2BA | C5: 0 | D5: 0 | E5: =IFERROR(D5/C5,0) -> 0 | G5: =A5 -> 0 | H5: =B5 -> 2BR - 2BA | I5: =C5 -> 0 | J5: 0 | K5: =IFERROR(J5/I5,0) -> 0 | M5: =J5-D5 -> 0 | O5: Pet Fees | P5: 5 | R5: Other Loss | S5: 0 | T5: 0 | U5: 0 | V5: 0 | W5: 0 | X5: 0 | Y5: 0 | Z5: 0 | AA5: 0 | AB5: 0 | AC5: 0 | AE5: Total Potential Rental Revenue | AF5: =AF3*AF4+AF2*(1-AF4) -> 245000 | AG5: =AG3*AG4+AG2*(1-AG4) -> 245998.16 | AH5: =AH3*AH4+AH2*(1-AH4) -> 247000.39 | AI5: =AI3*AI4+AI2*(1-AI4) -> 248006.7 | AJ5: =AJ3*AJ4+AJ2*(1-AJ4) -> 250033.5 | AK5: =AK3*AK4+AK2*(1-AK4) -> 252072.71 | AL5: =AL3*AL4+AL2*(1-AL4) -> 254124.38 | AM5: =AM3*AM4+AM2*(1-AM4) -> 256188.58 | ... FG5: =FG3*FG4+FG2*(1-FG4) -> 363854.59
A6: 0 | B6: 2BR - 2BA | C6: 0 | D6: 0 | E6: =IFERROR(D6/C6,0) -> 0 | G6: =A6 -> 0 | H6: =B6 -> 2BR - 2BA | I6: =C6 -> 0 | J6: 0 | K6: =IFERROR(J6/I6,0) -> 0 | M6: =J6-D6 -> 0 | O6: Garage Income | P6: 0 | R6: Economic Vacancy | S6: =SUM(S2:S5) -> 0.08 | T6: =SUM(T2:T5) -> 0.0675 | U6: =SUM(U2:U5) -> 0.055 | V6: =SUM(V2:V5) -> 0.055 | W6: =SUM(W2:W5) -> 0.055 | X6: =SUM(X2:X5) -> 0.055 | Y6: =SUM(Y2:Y5) -> 0.055 | Z6: =SUM(Z2:Z5) -> 0.055 | ... AC6: =SUM(AC2:AC5) -> 0.055
A7: 0 | B7: 2BR - 2BA | C7: 0 | D7: 0 | E7: =IFERROR(D7/C7,0) -> 0 | G7: =A7 -> 0 | H7: =B7 -> 2BR - 2BA | I7: =C7 -> 0 | J7: 0 | K7: =IFERROR(J7/I7,0) -> 0 | M7: =J7-D7 -> 0 | O7: Storage Income | P7: 0
A8: 0 | B8: 2BR - 2BA | C8: 0 | D8: 0 | E8: =IFERROR(D8/C8,0) -> 0 | G8: =A8 -> 0 | H8: =B8 -> 2BR - 2BA | I8: =C8 -> 0 | J8: 0 | K8: =IFERROR(J8/I8,0) -> 0 | M8: =J8-D8 -> 0 | O8: Forfeited Deposits | P8: 5 | S8: 1 | T8: =S8+1 -> 2 | U8: =T8+1 -> 3 | V8: =U8+1 -> 4 | W8: =V8+1 -> 5 | X8: =W8+1 -> 6 | Y8: =X8+1 -> 7 | Z8: =Y8+1 -> 8 | AA8: =Z8+1 -> 9 | ... AC8: =AB8+1 -> 11
A9: 0 | B9: 2BR - 2BA | C9: 0 | D9: 0 | E9: =IFERROR(D9/C9,0) -> 0 | G9: =A9 -> 0 | H9: =B9 -> 2BR - 2BA | I9: =C9 -> 0 | J9: 0 | K9: =IFERROR(J9/I9,0) -> 0 | M9: =J9-D9 -> 0 | O9: Other Charges | P9: 0 | R9: Market Rent Growth | S9: 0.05 | T9: 0.04 | U9: 0.03 | V9: 0.03 | W9: 0.03 | X9: 0.03 | Y9: 0.03 | Z9: 0.03 | AA9: 0.03 | AB9: 0.03 | AC9: 0.03
A10: 0 | B10: 2BR - 2BA | C10: 0 | D10: 0 | E10: =IFERROR(D10/C10,0) -> 0 | G10: =A10 -> 0 | H10: =B10 -> 2BR - 2BA | I10: =C10 -> 0 | J10: 0 | K10: =IFERROR(J10/I10,0) -> 0 | M10: =J10-D10 -> 0 | O10: Other Charges | P10: 0 | R10: Other Income Growth | S10: 0.03 | T10: 0.03 | U10: 0.03 | V10: 0.03 | W10: 0.03 | X10: 0.03 | Y10: 0.03 | Z10: 0.03 | AA10: 0.03 | AB10: 0.03 | AC10: 0.03
A11: 0 | B11: 2BR - 2BA | C11: 0 | D11: 0 | E11: =IFERROR(D11/C11,0) -> 0 | G11: =A11 -> 0 | H11: =B11 -> 2BR - 2BA | I11: =C11 -> 0 | J11: 0 | K11: =IFERROR(J11/I11,0) -> 0 | M11: =J11-D11 -> 0 | O11: Other Charges | P11: 0
A12: 0 | B12: 2BR - 2BA | C12: 0 | D12: 0 | E12: =IFERROR(D12/C12,0) -> 0 | G12: =A12 -> 0 | H12: =B12 -> 2BR - 2BA | I12: =C12 -> 0 | J12: 0 | K12: =IFERROR(J12/I12,0) -> 0 | M12: =J12-D12 -> 0 | O12: Total | P12: =SUM(P2:P11) -> 55
A13: 0 | B13: 2BR - 2BA | C13: 0 | D13: 0 | E13: =IFERROR(D13/C13,0) -> 0 | G13: =A13 -> 0 | H13: =B13 -> 2BR - 2BA | I13: =C13 -> 0 | J13: 0 | K13: =IFERROR(J13/I13,0) -> 0 | M13: =J13-D13 -> 0
A14: 0 | B14: 2BR - 2BA | C14: 0 | D14: 0 | E14: =IFERROR(D14/C14,0) -> 0 | G14: =A14 -> 0 | H14: =B14 -> 2BR - 2BA | I14: =C14 -> 0 | J14: 0 | K14: =IFERROR(J14/I14,0) -> 0 | M14: =J14-D14 -> 0 | O14: Rent Increase Timing
A15: 0 | B15: 2BR - 2BA | C15: 0 | D15: 0 | E15: =IFERROR(D15/C15,0) -> 0 | G15: =A15 -> 0 | H15: =B15 -> 2BR - 2BA | I15: =C15 -> 0 | J15: 0 | K15: =IFERROR(J15/I15,0) -> 0 | M15: =J15-D15 -> 0 | O15: Month Start | P15: 5
A16: 0 | B16: 2BR - 2BA | C16: 0 | D16: 0 | E16: =IFERROR(D16/C16,0) -> 0 | G16: =A16 -> 0 | H16: =B16 -> 2BR - 2BA | I16: =C16 -> 0 | J16: 0 | K16: =IFERROR(J16/I16,0) -> 0 | M16: =J16-D16 -> 0 | O16: Month End | P16: 15
A17: 0 | B17: 2BR - 2BA | C17: 0 | D17: 0 | E17: =IFERROR(D17/C17,0) -> 0 | G17: =A17 -> 0 | H17: =B17 -> 2BR - 2BA | I17: =C17 -> 0 | J17: 0 | K17: =IFERROR(J17/I17,0) -> 0 | M17: =J17-D17 -> 0 | O17: Rent Increase Period | P17: =P16-P15+1 -> 11
A18: 0 | B18: 2BR - 2BA | C18: 0 | D18: 0 | E18: =IFERROR(D18/C18,0) -> 0 | G18: =A18 -> 0 | H18: =B18 -> 2BR - 2BA | I18: =C18 -> 0 | J18: 0 | K18: =IFERROR(J18/I18,0) -> 0 | M18: =J18-D18 -> 0
A19: 0 | B19: 2BR - 2BA | C19: 0 | D19: 0 | E19: =IFERROR(D19/C19,0) -> 0 | G19: =A19 -> 0 | H19: =B19 -> 2BR - 2BA | I19: =C19 -> 0 | J19: 0 | K19: =IFERROR(J19/I19,0) -> 0 | M19: =J19-D19 -> 0
A20: 0 | B20: 2BR - 2BA | C20: 0 | D20: 0 | E20: =IFERROR(D20/C20,0) -> 0 | G20: =A20 -> 0 | H20: =B20 -> 2BR - 2BA | I20: =C20 -> 0 | J20: 0 | K20: =IFERROR(J20/I20,0) -> 0 | M20: =J20-D20 -> 0
A21: 0 | B21: 2BR - 2BA | C21: 0 | D21: 0 | E21: =IFERROR(D21/C21,0) -> 0 | G21: =A21 -> 0 | H21: =B21 -> 2BR - 2BA | I21: =C21 -> 0 | J21: 0 | K21: =IFERROR(J21/I21,0) -> 0 | M21: =J21-D21 -> 0
A22: 0 | B22: 2BR - 2BA | C22: 0 | D22: 0 | E22: =IFERROR(D22/C22,0) -> 0 | G22: =A22 -> 0 | H22: =B22 -> 2BR - 2BA | I22: =C22 -> 0 | J22: 0 | K22: =IFERROR(J22/I22,0) -> 0 | M22: =J22-D22 -> 0
A23: =SUM(A3:A22) -> 110 | C23: =SUMPRODUCT(C3:C22,$A$3:$A$22)/$A$23 -> 1272.7273 | D23: =SUMPRODUCT(D3:D22,$A$3:$A$22)/$A$23 -> 2227.2727 | E23: =IFERROR(D23/C23,0) -> 1.75 | G23: =SUM(G3:G22) -> 110 | I23: =SUMPRODUCT(I3:I22,$G$3:$G$22)/$G$23 -> 1272.7273 | J23: =SUMPRODUCT(J3:J22,$G$3:$G$22)/$G$23 -> 2327.2727 | K23: =IFERROR(J23/I23,0) -> 1.8285714 | M23: =SUMPRODUCT(M3:M22,$G$3:$G$22)/$G$23 -> 100

Sheet Expenses
A1: T-12 Operating Expenses | E1: Hold Period Operating Expenses | J1: Property Tax Growth Rates
A2: Item | B2: Total | C2: $/Unit/Year | E2: Item | F2: Total | G2: $/Unit/Year | J2: 1 | K2: =J2+1 -> 2 | L2: =K2+1 -> 3 | M2: =L2+1 -> 4 | N2: =M2+1 -> 5 | O2: =N2+1 -> 6 | P2: =O2+1 -> 7 | Q2: =P2+1 -> 8 | R2: =Q2+1 -> 9 | ... T2: =S2+1 -> 11
A3: Payroll | B3: 190000 | C3: =B3/Revenue!$A$23 -> 1727.2727 | E3: Payroll | F3: =G3*Revenue!$A$23 -> 198000 | G3: 1800 | J3: 0.1 | K3: 0.05 | L3: 0.03 | M3: 0.03 | N3: 0.03 | O3: 0.03 | P3: 0.03 | Q3: 0.03 | R3: 0.03 | S3: 0.03 | T3: 0.03
A4: General & Administrative | B4: 30000 | C4: =B4/Revenue!$A$23 -> 272.72727 | E4: General & Administrative | F4: =G4*Revenue!$A$23 -> 30250 | G4: 275
A5: Marketing | B5: 25000 | C5: =B5/Revenue!$A$23 -> 227.27273 | E5: Marketing | F5: =G5*Revenue!$A$23 -> 24750 | G5: 225 | J5: Hold Period Property Taxes
A6: Repairs & Maintenance | B6: 60000 | C6: =B6/Revenue!$A$23 -> 545.45455 | E6: Repairs & Maintenance | F6: =G6*Revenue!$A$23 -> 60500 | G6: 550 | J6: 1 | K6: =J6+1 -> 2 | L6: =K6+1 -> 3 | M6: =L6+1 -> 4 | N6: =M6+1 -> 5 | O6: =N6+1 -> 6 | P6: =O6+1 -> 7 | Q6: =P6+1 -> 8 | R6: =Q6+1 -> 9 | ... T6: =S6+1 -> 11
A7: Turnover Costs | B7: 40000 | C7: =B7/Revenue!$A$23 -> 363.63636 | E7: Turnover Costs | F7: =G7*Revenue!$A$23 -> 41250 | G7: 375 | I7: Assessed Property Value | J7: =IF(B18="Yes",Summary!B20*Expenses!B19,Expenses!B20*(1+Expenses!J3)) -> 38500000 | K7: =J7*(1+K3) -> 40425000 | L7: =K7*(1+L3) -> 41637750 | M7: =L7*(1+M3) -> 42886882 | N7: =M7*(1+N3) -> 44173489 | O7: =N7*(1+O3) -> 45498694 | P7: =O7*(1+P3) -> 46863654 | Q7: =P7*(1+Q3) -> 48269564 | R7: =Q7*(1+R3) -> 49717651 | ... T7: =S7*(1+T3) -> 52745456
A8: Contract Services | B8: 25000 | C8: =B8/Revenue!$A$23 -> 227.27273 | E8: Contract Services | F8: =G8*Revenue!$A$23 -> 24750 | G8: 225 | I8: Property Taxes | J8: =J7*$B$17 -> 385000 | K8: =K7*$B$17 -> 404250 | L8: =L7*$B$17 -> 416377.5 | M8: =M7*$B$17 -> 428868.83 | N8: =N7*$B$17 -> 441734.89 | O8: =O7*$B$17 -> 454986.94 | P8: =P7*$B$17 -> 468636.54 | Q8: =Q7*$B$17 -> 482695.64 | ... T8: =T7*$B$17 -> 527454.56
A9: Utilities | B9: 60000 | C9: =B9/Revenue!$A$23 -> 545.45455 | E9: Utilities | F9: =G9*Revenue!$A$23 -> 60500 | G9: 550 | I9: Fixed Charge Assessments | J9: =B21*(1+J3) -> 27500 | K9: =J9*(1+K3) -> 28875 | L9: =K9*(1+L3) -> 29741.25 | M9: =L9*(1+M3) -> 30633.488 | N9: =M9*(1+N3) -> 31552.492 | O9: =N9*(1+O3) -> 32499.067 | P9: =O9*(1+P3) -> 33474.039 | Q9: =P9*(1+Q3) -> 34478.26 | R9: =Q9*(1+R3) -> 35512.608 | ... T9: =S9*(1+T3) -> 37675.326
A10: Utility Bill-Back | B10: -50000 | C10: =B10/Revenue!$A$23 -> -454.54545 | E10: Utility Bill-Back | F10: =G10*Revenue!$A$23 -> -52250 | G10: -475 | I10: Total Property Taxes | J10: =SUM(J8:J9) -> 412500 | K10: =SUM(K8:K9) -> 433125 | L10: =SUM(L8:L9) -> 446118.75 | M10: =SUM(M8:M9) -> 459502.31 | N10: =SUM(N8:N9) -> 473287.38 | O10: =SUM(O8:O9) -> 487486 | P10: =SUM(P8:P9) -> 502110.58 | Q10: =SUM(Q8:Q9) -> 517173.9 | ... T10: =SUM(T8:T9) -> 565129.89
A11: Property Management Fee | B11: 120000 | C11: =B11/Revenue!$A$23 -> 1090.9091 | E11: Property Management Fee | F11: =G11*Revenue!$A$23 -> 0 | G11: 0
A12: Property Taxes | B12: 275000 | C12: =B12/Revenue!$A$23 -> 2500 | E12: Property Taxes | F12: =J10 -> 412500 | G12: =F12/Revenue!A23 -> 3750
A13: Insurance | B13: 50000 | C13: =B13/Revenue!$A$23 -> 454.54545 | E13: Insurance | F13: =G13*Revenue!$A$23 -> 49500 | G13: 450
A14: Total | B14: =SUM(B3:B13) -> 825000 | C14: =B14/Revenue!$A$23 -> 7500 | E14: Total | F14: =SUM(F3:F13) -> 849750 | G14: =F14/Revenue!$A$23 -> 7725
A16: Property Tax Information | E16: Other Expense Assumptions
A17: Millage Rate | B17: 0.01 | E17: Annual Expense Growth | F17: 0.03
A18: Reassessed Upon Sale | B18: No | E18: Capital Expense Reserves/Unit | F18: 300
A19: % of Value Assessed | B19: 1 | E19: Property Management Fee | F19: 0.04
A20: Current Assessed Value | B20: 35000000
A21: Fixed Charge Assessments | B21: 25000

Sheet Construction Budget
H1: 1 | I1: =H1+1 -> 2 | J1: =I1+1 -> 3 | K1: =J1+1 -> 4 | L1: =K1+1 -> 5 | M1: =L1+1 -> 6 | N1: =M1+1 -> 7 | O1: =N1+1 -> 8 | P1: =O1+1 -> 9 | ... EI1: =EH1+1 -> 132
H2: =ROUNDUP(H1/12,0) -> 1 | I2: =ROUNDUP(I1/12,0) -> 1 | J2: =ROUNDUP(J1/12,0) -> 1 | K2: =ROUNDUP(K1/12,0) -> 1 | L2: =ROUNDUP(L1/12,0) -> 1 | M2: =ROUNDUP(M1/12,0) -> 1 | N2: =ROUNDUP(N1/12,0) -> 1 | O2: =ROUNDUP(O1/12,0) -> 1 | ... EI2: =ROUNDUP(EI1/12,0) -> 11
B3: Exterior Renovation Budget | EI3: 0
A4: Check | B4: Item | C4: Total | D4: Per Unit | E4: Month Start | F4: Month End | G4: Total Months
A5: =IF(ABS(SUM(H5:EI5)-C5)<0.0001,"OK","ERROR") -> OK | B5: Exterior Painting | C5: 500000 | D5: =C5/Revenue!$A$23 -> 4545.4545 | E5: 2 | F5: 5 | G5: =F5-E5+1 -> 4 | H5: =IF(AND(H$1>=$E5,H$1<=$F5),$C5/$G5,0) -> 0 | I5: =IF(AND(I$1>=$E5,I$1<=$F5),$C5/$G5,0) -> 125000 | J5: =IF(AND(J$1>=$E5,J$1<=$F5),$C5/$G5,0) -> 125000 | K5: =IF(AND(K$1>=$E5,K$1<=$F5),$C5/$G5,0) -> 125000 | L5: =IF(AND(L$1>=$E5,L$1<=$F5),$C5/$G5,0) -> 125000 | M5: =IF(AND(M$1>=$E5,M$1<=$F5),$C5/$G5,0) -> 0 | N5: =IF(AND(N$1>=$E5,N$1<=$F5),$C5/$G5,0) -> 0 | O5: =IF(AND(O$1>=$E5,O$1<=$F5),$C5/$G5,0) -> 0 | ... EI5: =IF(AND(EI$1>=$E5,EI$1<=$F5),$C5/$G5,0) -> 0
A6: =IF(ABS(SUM(H6:EI6)-C6)<0.0001,"OK","ERROR") -> OK | B6: Fitness Center Renovation | C6: 250000 | D6: =C6/Revenue!$A$23 -> 2272.7273 | E6: 3 | F6: 7 | G6: =F6-E6+1 -> 5 | H6: =IF(AND(H$1>=$E6,H$1<=$F6),$C6/$G6,0) -> 0 | I6: =IF(AND(I$1>=$E6,I$1<=$F6),$C6/$G6,0) -> 0 | J6: =IF(AND(J$1>=$E6,J$1<=$F6),$C6/$G6,0) -> 50000 | K6: =IF(AND(K$1>=$E6,K$1<=$F6),$C6/$G6,0) -> 50000 | L6: =IF(AND(L$1>=$E6,L$1<=$F6),$C6/$G6,0) -> 50000 | M6: =IF(AND(M$1>=$E6,M$1<=$F6),$C6/$G6,0) -> 50000 | N6: =IF(AND(N$1>=$E6,N$1<=$F6),$C6/$G6,0) -> 50000 | O6: =IF(AND(O$1>=$E6,O$1<=$F6),$C6/$G6,0) -> 0 | ... EI6: =IF(AND(EI$1>=$E6,EI$1<=$F6),$C6/$G6,0) -> 0
A7: =IF(ABS(SUM(H7:EI7)-C7)<0.0001,"OK","ERROR") -> OK | B7: Leasing Center Renovation | C7: 400000 | D7: =C7/Revenue!$A$23 -> 3636.3636 | E7: 6 | F7: 9 | G7: =F7-E7+1 -> 4 | H7: =IF(AND(H$1>=$E7,H$1<=$F7),$C7/$G7,0) -> 0 | I7: =IF(AND(I$1>=$E7,I$1<=$F7),$C7/$G7,0) -> 0 | J7: =IF(AND(J$1>=$E7,J$1<=$F7),$C7/$G7,0) -> 0 | K7: =IF(AND(K$1>=$E7,K$1<=$F7),$C7/$G7,0) -> 0 | L7: =IF(AND(L$1>=$E7,L$1<=$F7),$C7/$G7,0) -> 0 | M7: =IF(AND(M$1>=$E7,M$1<=$F7),$C7/$G7,0) -> 100000 | N7: =IF(AND(N$1>=$E7,N$1<=$F7),$C7/$G7,0) -> 100000 | O7: =IF(AND(O$1>=$E7,O$1<=$F7),$C7/$G7,0) -> 100000 | ... EI7: =IF(AND(EI$1>=$E7,EI$1<=$F7),$C7/$G7,0) -> 0
A8: =IF(ABS(SUM(H8:EI8)-C8)<0.0001,"OK","ERROR") -> OK | B8: Dog Park | C8: 30000 | D8: =C8/Revenue!$A$23 -> 272.72727 | E8: 10 | F8: 12 | G8: =F8-E8+1 -> 3 | H8: =IF(AND(H$1>=$E8,H$1<=$F8),$C8/$G8,0) -> 0 | I8: =IF(AND(I$1>=$E8,I$1<=$F8),$C8/$G8,0) -> 0 | J8: =IF(AND(J$1>=$E8,J$1<=$F8),$C8/$G8,0) -> 0 | K8: =IF(AND(K$1>=$E8,K$1<=$F8),$C8/$G8,0) -> 0 | L8: =IF(AND(L$1>=$E8,L$1<=$F8),$C8/$G8,0) -> 0 | M8: =IF(AND(M$1>=$E8,M$1<=$F8),$C8/$G8,0) -> 0 | N8: =IF(AND(N$1>=$E8,N$1<=$F8),$C8/$G8,0) -> 0 | O8: =IF(AND(O$1>=$E8,O$1<=$F8),$C8/$G8,0) -> 0 | ... EI8: =IF(AND(EI$1>=$E8,EI$1<=$F8),$C8/$G8,0) -> 0
A9: =IF(ABS(SUM(H9:EI9)-C9)<0.0001,"OK","ERROR") -> OK | B9: Other | C9: 0 | D9: =C9/Revenue!$A$23 -> 0 | E9: 1 | F9: 1 | G9: =F9-E9+1 -> 1 | H9: =IF(AND(H$1>=$E9,H$1<=$F9),$C9/$G9,0) -> 0 | I9: =IF(AND(I$1>=$E9,I$1<=$F9),$C9/$G9,0) -> 0 | J9: =IF(AND(J$1>=$E9,J$1<=$F9),$C9/$G9,0) -> 0 | K9: =IF(AND(K$1>=$E9,K$1<=$F9),$C9/$G9,0) -> 0 | L9: =IF(AND(L$1>=$E9,L$1<=$F9),$C9/$G9,0) -> 0 | M9: =IF(AND(M$1>=$E9,M$1<=$F9),$C9/$G9,0) -> 0 | N9: =IF(AND(N$1>=$E9,N$1<=$F9),$C9/$G9,0) -> 0 | O9: =IF(AND(O$1>=$E9,O$1<=$F9),$C9/$G9,0) -> 0 | ... EI9: =IF(AND(EI$1>=$E9,EI$1<=$F9),$C9/$G9,0) -> 0
A10: =IF(ABS(SUM(H10:EI10)-C10)<0.0001,"OK","ERROR") -> OK | B10: Other | C10: 0 | D10: =C10/Revenue!$A$23 -> 0 | E10: 1 | F10: 1 | G10: =F10-E10+1 -> 1 | H10: =IF(AND(H$1>=$E10,H$1<=$F10),$C10/$G10,0) -> 0 | I10: =IF(AND(I$1>=$E10,I$1<=$F10),$C10/$G10,0) -> 0 | J10: =IF(AND(J$1>=$E10,J$1<=$F10),$C10/$G10,0) -> 0 | K10: =IF(AND(K$1>=$E10,K$1<=$F10),$C10/$G10,0) -> 0 | L10: =IF(AND(L$1>=$E10,L$1<=$F10),$C10/$G10,0) -> 0 | M10: =IF(AND(M$1>=$E10,M$1<=$F10),$C10/$G10,0) -> 0 | N10: =IF(AND(N$1>=$E10,N$1<=$F10),$C10/$G10,0) -> 0 | O10: =IF(AND(O$1>=$E10,O$1<=$F10),$C10/$G10,0) -> 0 | ... EI10: =IF(AND(EI$1>=$E10,EI$1<=$F10),$C10/$G10,0) -> 0
A11: =IF(ABS(SUM(H11:EI11)-C11)<0.0001,"OK","ERROR") -> OK | B11: Other | C11: 0 | D11: =C11/Revenue!$A$23 -> 0 | E11: 1 | F11: 1 | G11: =F11-E11+1 -> 1 | H11: =IF(AND(H$1>=$E11,H$1<=$F11),$C11/$G11,0) -> 0 | I11: =IF(AND(I$1>=$E11,I$1<=$F11),$C11/$G11,0) -> 0 | J11: =IF(AND(J$1>=$E11,J$1<=$F11),$C11/$G11,0) -> 0 | K11: =IF(AND(K$1>=$E11,K$1<=$F11),$C11/$G11,0) -> 0 | L11: =IF(AND(L$1>=$E11,L$1<=$F11),$C11/$G11,0) -> 0 | M11: =IF(AND(M$1>=$E11,M$1<=$F11),$C11/$G11,0) -> 0 | N11: =IF(AND(N$1>=$E11,N$1<=$F11),$C11/$G11,0) -> 0 | O11: =IF(AND(O$1>=$E11,O$1<=$F11),$C11/$G11,0) -> 0 | ... EI11: =IF(AND(EI$1>=$E11,EI$1<=$F11),$C11/$G11,0) -> 0
A12: =IF(ABS(SUM(H12:EI12)-C12)<0.0001,"OK","ERROR") -> OK | B12: Other | C12: 0 | D12: =C12/Revenue!$A$23 -> 0 | E12: 1 | F12: 1 | G12: =F12-E12+1 -> 1 | H12: =IF(AND(H$1>=$E12,H$1<=$F12),$C12/$G12,0) -> 0 | I12: =IF(AND(I$1>=$E12,I$1<=$F12),$C12/$G12,0) -> 0 | J12: =IF(AND(J$1>=$E12,J$1<=$F12),$C12/$G12,0) -> 0 | K12: =IF(AND(K$1>=$E12,K$1<=$F12),$C12/$G12,0) -> 0 | L12: =IF(AND(L$1>=$E12,L$1<=$F12),$C12/$G12,0) -> 0 | M12: =IF(AND(M$1>=$E12,M$1<=$F12),$C12/$G12,0) -> 0 | N12: =IF(AND(N$1>=$E12,N$1<=$F12),$C12/$G12,0) -> 0 | O12: =IF(AND(O$1>=$E12,O$1<=$F12),$C12/$G12,0) -> 0 | ... EI12: =IF(AND(EI$1>=$E12,EI$1<=$F12),$C12/$G12,0) -> 0
A13: =IF(ABS(SUM(H13:EI13)-C13)<0.0001,"OK","ERROR") -> OK | B13: Other | C13: 0 | D13: =C13/Revenue!$A$23 -> 0 | E13: 1 | F13: 1 | G13: =F13-E13+1 -> 1 | H13: =IF(AND(H$1>=$E13,H$1<=$F13),$C13/$G13,0) -> 0 | I13: =IF(AND(I$1>=$E13,I$1<=$F13),$C13/$G13,0) -> 0 | J13: =IF(AND(J$1>=$E13,J$1<=$F13),$C13/$G13,0) -> 0 | K13: =IF(AND(K$1>=$E13,K$1<=$F13),$C13/$G13,0) -> 0 | L13: =IF(AND(L$1>=$E13,L$1<=$F13),$C13/$G13,0) -> 0 | M13: =IF(AND(M$1>=$E13,M$1<=$F13),$C13/$G13,0) -> 0 | N13: =IF(AND(N$1>=$E13,N$1<=$F13),$C13/$G13,0) -> 0 | O13: =IF(AND(O$1>=$E13,O$1<=$F13),$C13/$G13,0) -> 0 | ... EI13: =IF(AND(EI$1>=$E13,EI$1<=$F13),$C13/$G13,0) -> 0
A14: =IF(ABS(SUM(H14:EI14)-C14)<0.0001,"OK","ERROR") -> OK | B14: Other | C14: 0 | D14: =C14/Revenue!$A$23 -> 0 | E14: 1 | F14: 1 | G14: =F14-E14+1 -> 1 | H14: =IF(AND(H$1>=$E14,H$1<=$F14),$C14/$G14,0) -> 0 | I14: =IF(AND(I$1>=$E14,I$1<=$F14),$C14/$G14,0) -> 0 | J14: =IF(AND(J$1>=$E14,J$1<=$F14),$C14/$G14,0) -> 0 | K14: =IF(AND(K$1>=$E14,K$1<=$F14),$C14/$G14,0) -> 0 | L14: =IF(AND(L$1>=$E14,L$1<=$F14),$C14/$G14,0) -> 0 | M14: =IF(AND(M$1>=$E14,M$1<=$F14),$C14/$G14,0) -> 0 | N14: =IF(AND(N$1>=$E14,N$1<=$F14),$C14/$G14,0) -> 0 | O14: =IF(AND(O$1>=$E14,O$1<=$F14),$C14/$G14,0) -> 0 | ... EI14: =IF(AND(EI$1>=$E14,EI$1<=$F14),$C14/$G14,0) -> 0
A15: =IF(ABS(SUM(H15:EI15)-C15)<0.0001,"OK","ERROR") -> OK | B15: Other | C15: 0 | D15: =C15/Revenue!$A$23 -> 0 | E15: 1 | F15: 1 | G15: =F15-E15+1 -> 1 | H15: =IF(AND(H$1>=$E15,H$1<=$F15),$C15/$G15,0) -> 0 | I15: =IF(AND(I$1>=$E15,I$1<=$F15),$C15/$G15,0) -> 0 | J15: =IF(AND(J$1>=$E15,J$1<=$F15),$C15/$G15,0) -> 0 | K15: =IF(AND(K$1>=$E15,K$1<=$F15),$C15/$G15,0) -> 0 | L15: =IF(AND(L$1>=$E15,L$1<=$F15),$C15/$G15,0) -> 0 | M15: =IF(AND(M$1>=$E15,M$1<=$F15),$C15/$G15,0) -> 0 | N15: =IF(AND(N$1>=$E15,N$1<=$F15),$C15/$G15,0) -> 0 | O15: =IF(AND(O$1>=$E15,O$1<=$F15),$C15/$G15,0) -> 0 | ... EI15: =IF(AND(EI$1>=$E15,EI$1<=$F15),$C15/$G15,0) -> 0
A16: =IF(ABS(SUM(H16:EI16)-C16)<0.0001,"OK","ERROR") -> OK | B16: Other | C16: 0 | D16: =C16/Revenue!$A$23 -> 0 | E16: 1 | F16: 1 | G16: =F16-E16+1 -> 1 | H16: =IF(AND(H$1>=$E16,H$1<=$F16),$C16/$G16,0) -> 0 | I16: =IF(AND(I$1>=$E16,I$1<=$F16),$C16/$G16,0) -> 0 | J16: =IF(AND(J$1>=$E16,J$1<=$F16),$C16/$G16,0) -> 0 | K16: =IF(AND(K$1>=$E16,K$1<=$F16),$C16/$G16,0) -> 0 | L16: =IF(AND(L$1>=$E16,L$1<=$F16),$C16/$G16,0) -> 0 | M16: =IF(AND(M$1>=$E16,M$1<=$F16),$C16/$G16,0) -> 0 | N16: =IF(AND(N$1>=$E16,N$1<=$F16),$C16/$G16,0) -> 0 | O16: =IF(AND(O$1>=$E16,O$1<=$F16),$C16/$G16,0) -> 0 | ... EI16: =IF(AND(EI$1>=$E16,EI$1<=$F16),$C16/$G16,0) -> 0
... A20: =IF(ABS(SUM(H20:EI20)-C20)<0.0001,"OK","ERROR") -> OK | B20: Other | C20: 0 | D20: =C20/Revenue!$A$23 -> 0 | E20: 1 | F20: 1 | G20: =F20-E20+1 -> 1 | H20: =IF(AND(H$1>=$E20,H$1<=$F20),$C20/$G20,0) -> 0 | I20: =IF(AND(I$1>=$E20,I$1<=$F20),$C20/$G20,0) -> 0 | J20: =IF(AND(J$1>=$E20,J$1<=$F20),$C20/$G20,0) -> 0 | K20: =IF(AND(K$1>=$E20,K$1<=$F20),$C20/$G20,0) -> 0 | L20: =IF(AND(L$1>=$E20,L$1<=$F20),$C20/$G20,0) -> 0 | M20: =IF(AND(M$1>=$E20,M$1<=$F20),$C20/$G20,0) -> 0 | N20: =IF(AND(N$1>=$E20,N$1<=$F20),$C20/$G20,0) -> 0 | O20: =IF(AND(O$1>=$E20,O$1<=$F20),$C20/$G20,0) -> 0 | ... EI20: =IF(AND(EI$1>=$E20,EI$1<=$F20),$C20/$G20,0) -> 0
A21: =IF(ABS(SUM(H21:EI21)-C21)<0.0001,"OK","ERROR") -> OK | B21: Subtotal | C21: =SUM(C5:C20) -> 1180000 | D21: =SUM(D5:D20) -> 10727.273 | E21: {=MIN(IF($C$5:$C$20>0,E5:E20))} -> 2 | F21: {=MAX(IF($C$5:$C$20>0,F5:F20))} -> 12 | G21: =F21-E21+1 -> 11 | H21: =SUM(H5:H20) -> 0 | I21: =SUM(I5:I20) -> 125000 | J21: =SUM(J5:J20) -> 175000 | K21: =SUM(K5:K20) -> 175000 | L21: =SUM(L5:L20) -> 175000 | M21: =SUM(M5:M20) -> 150000 | N21: =SUM(N5:N20) -> 150000 | O21: =SUM(O5:O20) -> 100000 | ... EI21: =SUM(EI5:EI20) -> 0
B23: Interior Renovation Budget | EI23: 0
A24: Check | B24: Item | C24: Total | D24: Per Unit | E24: Month Start | F24: Month End | G24: Total Months
A25: =IF(ABS(SUM(H25:EI25)-C25)<0.0001,"OK","ERROR") -> OK | B25: Countertops | C25: =D25*Revenue!$A$23 -> 220000 | D25: 2000 | E25: 2 | F25: 25 | G25: =F25-E25+1 -> 24 | H25: =IF(AND(H$1>=$E25,H$1<=$F25),$C25/$G25,0) -> 0 | I25: =IF(AND(I$1>=$E25,I$1<=$F25),$C25/$G25,0) -> 9166.6667 | J25: =IF(AND(J$1>=$E25,J$1<=$F25),$C25/$G25,0) -> 9166.6667 | K25: =IF(AND(K$1>=$E25,K$1<=$F25),$C25/$G25,0) -> 9166.6667 | L25: =IF(AND(L$1>=$E25,L$1<=$F25),$C25/$G25,0) -> 9166.6667 | M25: =IF(AND(M$1>=$E25,M$1<=$F25),$C25/$G25,0) -> 9166.6667 | N25: =IF(AND(N$1>=$E25,N$1<=$F25),$C25/$G25,0) -> 9166.6667 | O25: =IF(AND(O$1>=$E25,O$1<=$F25),$C25/$G25,0) -> 9166.6667 | ... EI25: =IF(AND(EI$1>=$E25,EI$1<=$F25),$C25/$G25,0) -> 0
A26: =IF(ABS(SUM(H26:EI26)-C26)<0.0001,"OK","ERROR") -> OK | B26: Flooring | C26: =D26*Revenue!$A$23 -> 165000 | D26: 1500 | E26: 2 | F26: 25 | G26: =F26-E26+1 -> 24 | H26: =IF(AND(H$1>=$E26,H$1<=$F26),$C26/$G26,0) -> 0 | I26: =IF(AND(I$1>=$E26,I$1<=$F26),$C26/$G26,0) -> 6875 | J26: =IF(AND(J$1>=$E26,J$1<=$F26),$C26/$G26,0) -> 6875 | K26: =IF(AND(K$1>=$E26,K$1<=$F26),$C26/$G26,0) -> 6875 | L26: =IF(AND(L$1>=$E26,L$1<=$F26),$C26/$G26,0) -> 6875 | M26: =IF(AND(M$1>=$E26,M$1<=$F26),$C26/$G26,0) -> 6875 | N26: =IF(AND(N$1>=$E26,N$1<=$F26),$C26/$G26,0) -> 6875 | O26: =IF(AND(O$1>=$E26,O$1<=$F26),$C26/$G26,0) -> 6875 | ... EI26: =IF(AND(EI$1>=$E26,EI$1<=$F26),$C26/$G26,0) -> 0
A27: =IF(ABS(SUM(H27:EI27)-C27)<0.0001,"OK","ERROR") -> OK | B27: Cabinets | C27: =D27*Revenue!$A$23 -> 165000 | D27: 1500 | E27: 2 | F27: 25 | G27: =F27-E27+1 -> 24 | H27: =IF(AND(H$1>=$E27,H$1<=$F27),$C27/$G27,0) -> 0 | I27: =IF(AND(I$1>=$E27,I$1<=$F27),$C27/$G27,0) -> 6875 | J27: =IF(AND(J$1>=$E27,J$1<=$F27),$C27/$G27,0) -> 6875 | K27: =IF(AND(K$1>=$E27,K$1<=$F27),$C27/$G27,0) -> 6875 | L27: =IF(AND(L$1>=$E27,L$1<=$F27),$C27/$G27,0) -> 6875 | M27: =IF(AND(M$1>=$E27,M$1<=$F27),$C27/$G27,0) -> 6875 | N27: =IF(AND(N$1>=$E27,N$1<=$F27),$C27/$G27,0) -> 6875 | O27: =IF(AND(O$1>=$E27,O$1<=$F27),$C27/$G27,0) -> 6875 | ... EI27: =IF(AND(EI$1>=$E27,EI$1<=$F27),$C27/$G27,0) -> 0
A28: =IF(ABS(SUM(H28:EI28)-C28)<0.0001,"OK","ERROR") -> OK | B28: Fixtures | C28: =D28*Revenue!$A$23 -> 55000 | D28: 500 | E28: 2 | F28: 25 | G28: =F28-E28+1 -> 24 | H28: =IF(AND(H$1>=$E28,H$1<=$F28),$C28/$G28,0) -> 0 | I28: =IF(AND(I$1>=$E28,I$1<=$F28),$C28/$G28,0) -> 2291.6667 | J28: =IF(AND(J$1>=$E28,J$1<=$F28),$C28/$G28,0) -> 2291.6667 | K28: =IF(AND(K$1>=$E28,K$1<=$F28),$C28/$G28,0) -> 2291.6667 | L28: =IF(AND(L$1>=$E28,L$1<=$F28),$C28/$G28,0) -> 2291.6667 | M28: =IF(AND(M$1>=$E28,M$1<=$F28),$C28/$G28,0) -> 2291.6667 | N28: =IF(AND(N$1>=$E28,N$1<=$F28),$C28/$G28,0) -> 2291.6667 | O28: =IF(AND(O$1>=$E28,O$1<=$F28),$C28/$G28,0) -> 2291.6667 | ... EI28: =IF(AND(EI$1>=$E28,EI$1<=$F28),$C28/$G28,0) -> 0
A29: =IF(ABS(SUM(H29:EI29)-C29)<0.0001,"OK","ERROR") -> OK | B29: Other | C29: =D29*Revenue!$A$23 -> 0 | D29: 0 | E29: 1 | F29: 1 | G29: =F29-E29+1 -> 1 | H29: =IF(AND(H$1>=$E29,H$1<=$F29),$C29/$G29,0) -> 0 | I29: =IF(AND(I$1>=$E29,I$1<=$F29),$C29/$G29,0) -> 0 | J29: =IF(AND(J$1>=$E29,J$1<=$F29),$C29/$G29,0) -> 0 | K29: =IF(AND(K$1>=$E29,K$1<=$F29),$C29/$G29,0) -> 0 | L29: =IF(AND(L$1>=$E29,L$1<=$F29),$C29/$G29,0) -> 0 | M29: =IF(AND(M$1>=$E29,M$1<=$F29),$C29/$G29,0) -> 0 | N29: =IF(AND(N$1>=$E29,N$1<=$F29),$C29/$G29,0) -> 0 | O29: =IF(AND(O$1>=$E29,O$1<=$F29),$C29/$G29,0) -> 0 | ... EI29: =IF(AND(EI$1>=$E29,EI$1<=$F29),$C29/$G29,0) -> 0
A30: =IF(ABS(SUM(H30:EI30)-C30)<0.0001,"OK","ERROR") -> OK | B30: Other | C30: =D30*Revenue!$A$23 -> 0 | D30: 0 | E30: 1 | F30: 1 | G30: =F30-E30+1 -> 1 | H30: =IF(AND(H$1>=$E30,H$1<=$F30),$C30/$G30,0) -> 0 | I30: =IF(AND(I$1>=$E30,I$1<=$F30),$C30/$G30,0) -> 0 | J30: =IF(AND(J$1>=$E30,J$1<=$F30),$C30/$G30,0) -> 0 | K30: =IF(AND(K$1>=$E30,K$1<=$F30),$C30/$G30,0) -> 0 | L30: =IF(AND(L$1>=$E30,L$1<=$F30),$C30/$G30,0) -> 0 | M30: =IF(AND(M$1>=$E30,M$1<=$F30),$C30/$G30,0) -> 0 | N30: =IF(AND(N$1>=$E30,N$1<=$F30),$C30/$G30,0) -> 0 | O30: =IF(AND(O$1>=$E30,O$1<=$F30),$C30/$G30,0) -> 0 | ... EI30: =IF(AND(EI$1>=$E30,EI$1<=$F30),$C30/$G30,0) -> 0
A31: =IF(ABS(SUM(H31:EI31)-C31)<0.0001,"OK","ERROR") -> OK | B31: Other | C31: =D31*Revenue!$A$23 -> 0 | D31: 0 | E31: 1 | F31: 1 | G31: =F31-E31+1 -> 1 | H31: =IF(AND(H$1>=$E31,H$1<=$F31),$C31/$G31,0) -> 0 | I31: =IF(AND(I$1>=$E31,I$1<=$F31),$C31/$G31,0) -> 0 | J31: =IF(AND(J$1>=$E31,J$1<=$F31),$C31/$G31,0) -> 0 | K31: =IF(AND(K$1>=$E31,K$1<=$F31),$C31/$G31,0) -> 0 | L31: =IF(AND(L$1>=$E31,L$1<=$F31),$C31/$G31,0) -> 0 | M31: =IF(AND(M$1>=$E31,M$1<=$F31),$C31/$G31,0) -> 0 | N31: =IF(AND(N$1>=$E31,N$1<=$F31),$C31/$G31,0) -> 0 | O31: =IF(AND(O$1>=$E31,O$1<=$F31),$C31/$G31,0) -> 0 | ... EI31: =IF(AND(EI$1>=$E31,EI$1<=$F31),$C31/$G31,0) -> 0
A32: =IF(ABS(SUM(H32:EI32)-C32)<0.0001,"OK","ERROR") -> OK | B32: Other | C32: =D32*Revenue!$A$23 -> 0 | D32: 0 | E32: 1 | F32: 1 | G32: =F32-E32+1 -> 1 | H32: =IF(AND(H$1>=$E32,H$1<=$F32),$C32/$G32,0) -> 0 | I32: =IF(AND(I$1>=$E32,I$1<=$F32),$C32/$G32,0) -> 0 | J32: =IF(AND(J$1>=$E32,J$1<=$F32),$C32/$G32,0) -> 0 | K32: =IF(AND(K$1>=$E32,K$1<=$F32),$C32/$G32,0) -> 0 | L32: =IF(AND(L$1>=$E32,L$1<=$F32),$C32/$G32,0) -> 0 | M32: =IF(AND(M$1>=$E32,M$1<=$F32),$C32/$G32,0) -> 0 | N32: =IF(AND(N$1>=$E32,N$1<=$F32),$C32/$G32,0) -> 0 | O32: =IF(AND(O$1>=$E32,O$1<=$F32),$C32/$G32,0) -> 0 | ... EI32: =IF(AND(EI$1>=$E32,EI$1<=$F32),$C32/$G32,0) -> 0
A33: =IF(ABS(SUM(H33:EI33)-C33)<0.0001,"OK","ERROR") -> OK | B33: Other | C33: =D33*Revenue!$A$23 -> 0 | D33: 0 | E33: 1 | F33: 1 | G33: =F33-E33+1 -> 1 | H33: =IF(AND(H$1>=$E33,H$1<=$F33),$C33/$G33,0) -> 0 | I33: =IF(AND(I$1>=$E33,I$1<=$F33),$C33/$G33,0) -> 0 | J33: =IF(AND(J$1>=$E33,J$1<=$F33),$C33/$G33,0) -> 0 | K33: =IF(AND(K$1>=$E33,K$1<=$F33),$C33/$G33,0) -> 0 | L33: =IF(AND(L$1>=$E33,L$1<=$F33),$C33/$G33,0) -> 0 | M33: =IF(AND(M$1>=$E33,M$1<=$F33),$C33/$G33,0) -> 0 | N33: =IF(AND(N$1>=$E33,N$1<=$F33),$C33/$G33,0) -> 0 | O33: =IF(AND(O$1>=$E33,O$1<=$F33),$C33/$G33,0) -> 0 | ... EI33: =IF(AND(EI$1>=$E33,EI$1<=$F33),$C33/$G33,0) -> 0
A34: =IF(ABS(SUM(H34:EI34)-C34)<0.0001,"OK","ERROR") -> OK | B34: Other | C34: =D34*Revenue!$A$23 -> 0 | D34: 0 | E34: 1 | F34: 1 | G34: =F34-E34+1 -> 1 | H34: =IF(AND(H$1>=$E34,H$1<=$F34),$C34/$G34,0) -> 0 | I34: =IF(AND(I$1>=$E34,I$1<=$F34),$C34/$G34,0) -> 0 | J34: =IF(AND(J$1>=$E34,J$1<=$F34),$C34/$G34,0) -> 0 | K34: =IF(AND(K$1>=$E34,K$1<=$F34),$C34/$G34,0) -> 0 | L34: =IF(AND(L$1>=$E34,L$1<=$F34),$C34/$G34,0) -> 0 | M34: =IF(AND(M$1>=$E34,M$1<=$F34),$C34/$G34,0) -> 0 | N34: =IF(AND(N$1>=$E34,N$1<=$F34),$C34/$G34,0) -> 0 | O34: =IF(AND(O$1>=$E34,O$1<=$F34),$C34/$G34,0) -> 0 | ... EI34: =IF(AND(EI$1>=$E34,EI$1<=$F34),$C34/$G34,0) -> 0
A35: =IF(ABS(SUM(H35:EI35)-C35)<0.0001,"OK","ERROR") -> OK | B35: Other | C35: =D35*Revenue!$A$23 -> 0 | D35: 0 | E35: 1 | F35: 1 | G35: =F35-E35+1 -> 1 | H35: =IF(AND(H$1>=$E35,H$1<=$F35),$C35/$G35,0) -> 0 | I35: =IF(AND(I$1>=$E35,I$1<=$F35),$C35/$G35,0) -> 0 | J35: =IF(AND(J$1>=$E35,J$1<=$F35),$C35/$G35,0) -> 0 | K35: =IF(AND(K$1>=$E35,K$1<=$F35),$C35/$G35,0) -> 0 | L35: =IF(AND(L$1>=$E35,L$1<=$F35),$C35/$G35,0) -> 0 | M35: =IF(AND(M$1>=$E35,M$1<=$F35),$C35/$G35,0) -> 0 | N35: =IF(AND(N$1>=$E35,N$1<=$F35),$C35/$G35,0) -> 0 | O35: =IF(AND(O$1>=$E35,O$1<=$F35),$C35/$G35,0) -> 0 | ... EI35: =IF(AND(EI$1>=$E35,EI$1<=$F35),$C35/$G35,0) -> 0
A36: =IF(ABS(SUM(H36:EI36)-C36)<0.0001,"OK","ERROR") -> OK | B36: Other | C36: =D36*Revenue!$A$23 -> 0 | D36: 0 | E36: 1 | F36: 1 | G36: =F36-E36+1 -> 1 | H36: =IF(AND(H$1>=$E36,H$1<=$F36),$C36/$G36,0) -> 0 | I36: =IF(AND(I$1>=$E36,I$1<=$F36),$C36/$G36,0) -> 0 | J36: =IF(AND(J$1>=$E36,J$1<=$F36),$C36/$G36,0) -> 0 | K36: =IF(AND(K$1>=$E36,K$1<=$F36),$C36/$G36,0) -> 0 | L36: =IF(AND(L$1>=$E36,L$1<=$F36),$C36/$G36,0) -> 0 | M36: =IF(AND(M$1>=$E36,M$1<=$F36),$C36/$G36,0) -> 0 | N36: =IF(AND(N$1>=$E36,N$1<=$F36),$C36/$G36,0) -> 0 | O36: =IF(AND(O$1>=$E36,O$1<=$F36),$C36/$G36,0) -> 0 | ... EI36: =IF(AND(EI$1>=$E36,EI$1<=$F36),$C36/$G36,0) -> 0
... A40: =IF(ABS(SUM(H40:EI40)-C40)<0.0001,"OK","ERROR") -> OK | B40: Other | C40: =D40*Revenue!$A$23 -> 0 | D40: 0 | E40: 1 | F40: 1 | G40: =F40-E40+1 -> 1 | H40: =IF(AND(H$1>=$E40,H$1<=$F40),$C40/$G40,0) -> 0 | I40: =IF(AND(I$1>=$E40,I$1<=$F40),$C40/$G40,0) -> 0 | J40: =IF(AND(J$1>=$E40,J$1<=$F40),$C40/$G40,0) -> 0 | K40: =IF(AND(K$1>=$E40,K$1<=$F40),$C40/$G40,0) -> 0 | L40: =IF(AND(L$1>=$E40,L$1<=$F40),$C40/$G40,0) -> 0 | M40: =IF(AND(M$1>=$E40,M$1<=$F40),$C40/$G40,0) -> 0 | N40: =IF(AND(N$1>=$E40,N$1<=$F40),$C40/$G40,0) -> 0 | O40: =IF(AND(O$1>=$E40,O$1<=$F40),$C40/$G40,0) -> 0 | ... EI40: =IF(AND(EI$1>=$E40,EI$1<=$F40),$C40/$G40,0) -> 0
A41: =IF(ABS(SUM(H41:EI41)-C41)<0.0001,"OK","ERROR") -> OK | B41: Subtotal | C41: =SUM(C25:C40) -> 605000 | D41: =SUM(D25:D40) -> 5500 | E41: {=MIN(IF($C$25:$C$40>0,E25:E40))} -> 2 | F41: {=MAX(IF($C$25:$C$40>0,F25:F40))} -> 25 | G41: =F41-E41+1 -> 24 | H41: =SUM(H25:H40) -> 0 | I41: =SUM(I25:I40) -> 25208.333 | J41: =SUM(J25:J40) -> 25208.333 | K41: =SUM(K25:K40) -> 25208.333 | L41: =SUM(L25:L40) -> 25208.333 | M41: =SUM(M25:M40) -> 25208.333 | N41: =SUM(N25:N40) -> 25208.333 | O41: =SUM(O25:O40) -> 25208.333 | ... EI41: =SUM(EI25:EI40) -> 0
B43: Contingency | EI43: 0
A44: Check | B44: Percentage | C44: Total | D44: Per Unit | E44: Month Start | F44: Month End | G44: Total Months
A45: =IF(ABS(SUM(H45:EI45)-C45)<0.0001,"OK","ERROR") -> OK | B45: 0.1 | C45: =B45*SUM(C21,C41) -> 178500 | D45: =C45/Revenue!A23 -> 1622.7273 | E45: =MIN(E21,E41) -> 2 | F45: =MAX(F21,F41) -> 25 | G45: =F45-E45+1 -> 24 | H45: =$B$45*SUM(H21,H41) -> 0 | I45: =$B$45*SUM(I21,I41) -> 15020.833 | J45: =$B$45*SUM(J21,J41) -> 20020.833 | K45: =$B$45*SUM(K21,K41) -> 20020.833 | L45: =$B$45*SUM(L21,L41) -> 20020.833 | M45: =$B$45*SUM(M21,M41) -> 17520.833 | N45: =$B$45*SUM(N21,N41) -> 17520.833 | O45: =$B$45*SUM(O21,O41) -> 12520.833 | ... EI45: =$B$45*SUM(EI21,EI41) -> 0
B47: Overall Construction Budget | EI47: 0
A48: Check | B48: Item | C48: Total | D48: Per Unit | E48: Month Start | F48: Month End | G48: Total Months
A49: =IF(ABS(SUM(H49:EI49)-C49)<0.0001,"OK","ERROR") -> OK | B49: Total Construction Budget | C49: =SUM(C21,C41,C45) -> 1963500 | D49: =SUM(D21,D41,D45) -> 17850 | E49: =E45 -> 2 | F49: =F45 -> 25 | G49: =F49-E49+1 -> 24 | H49: =SUM(H21,H41,H45) -> 0 | I49: =SUM(I21,I41,I45) -> 165229.17 | J49: =SUM(J21,J41,J45) -> 220229.17 | K49: =SUM(K21,K41,K45) -> 220229.17 | L49: =SUM(L21,L41,L45) -> 220229.17 | M49: =SUM(M21,M41,M45) -> 192729.17 | N49: =SUM(N21,N41,N45) -> 192729.17 | O49: =SUM(O21,O41,O45) -> 137729.17 | ... EI49: =SUM(EI21,EI41,EI45) -> 0

Sheet Financing
A1: Check | B1: Acquisition Financing | ED1: 0
A2: =IF(ABS(A6-A8-A4)<0.0001,"OK","ERROR") -> OK | B2: Month | C2: 1 | D2: =C2+1 -> 2 | E2: =D2+1 -> 3 | F2: =E2+1 -> 4 | G2: =F2+1 -> 5 | H2: =G2+1 -> 6 | I2: =H2+1 -> 7 | J2: =I2+1 -> 8 | K2: =J2+1 -> 9 | ... ED2: =EC2+1 -> 132
B3: Date | C3: =EOMONTH(Summary!B25,1) -> 44255 | D3: =EOMONTH(C3,1) -> 44286 | E3: =EOMONTH(D3,1) -> 44316 | F3: =EOMONTH(E3,1) -> 44347 | G3: =EOMONTH(F3,1) -> 44377 | H3: =EOMONTH(G3,1) -> 44408 | I3: =EOMONTH(H3,1) -> 44439 | J3: =EOMONTH(I3,1) -> 44469 | K3: =EOMONTH(J3,1) -> 44500 | ... ED3: =EOMONTH(EC3,1) -> 48244
A4: =MAX(C4:ED4) -> 26000000 | B4: Starting Balance | C4: =Summary!E2 -> 26000000 | D4: =C9 -> 26000000 | E4: =D9 -> 26000000 | F4: =E9 -> 26000000 | G4: =F9 -> 26000000 | H4: =G9 -> 26000000 | I4: =H9 -> 26000000 | J4: =I9 -> 26000000 | K4: =J9 -> 26000000 | ... ED4: =EC9 -> 0
A5: =SUM(C5:ED5) -> 6099071.4 | B5: Total Loan Payment | C5: =IF(C2>MIN(Summary!$E$10,Summary!$K$19),0,IF(C2<=Summary!$E$7,Summary!$E$6/12*Financing!C4,PMT(Summary!$E$6/12,Summary!$E$9,-Summary!$E$2,0,0))) -> 86666.667 | D5: =IF(D2>MIN(Summary!$E$10,Summary!$K$19),0,IF(D2<=Summary!$E$7,Summary!$E$6/12*Financing!D4,PMT(Summary!$E$6/12,Summary!$E$9,-Summary!$E$2,0,0))) -> 86666.667 | E5: =IF(E2>MIN(Summary!$E$10,Summary!$K$19),0,IF(E2<=Summary!$E$7,Summary!$E$6/12*Financing!E4,PMT(Summary!$E$6/12,Summary!$E$9,-Summary!$E$2,0,0))) -> 86666.667 | F5: =IF(F2>MIN(Summary!$E$10,Summary!$K$19),0,IF(F2<=Summary!$E$7,Summary!$E$6/12*Financing!F4,PMT(Summary!$E$6/12,Summary!$E$9,-Summary!$E$2,0,0))) -> 86666.667 | G5: =IF(G2>MIN(Summary!$E$10,Summary!$K$19),0,IF(G2<=Summary!$E$7,Summary!$E$6/12*Financing!G4,PMT(Summary!$E$6/12,Summary!$E$9,-Summary!$E$2,0,0))) -> 86666.667 | H5: =IF(H2>MIN(Summary!$E$10,Summary!$K$19),0,IF(H2<=Summary!$E$7,Summary!$E$6/12*Financing!H4,PMT(Summary!$E$6/12,Summary!$E$9,-Summary!$E$2,0,0))) -> 86666.667 | I5: =IF(I2>MIN(Summary!$E$10,Summary!$K$19),0,IF(I2<=Summary!$E$7,Summary!$E$6/12*Financing!I4,PMT(Summary!$E$6/12,Summary!$E$9,-Summary!$E$2,0,0))) -> 86666.667 | J5: =IF(J2>MIN(Summary!$E$10,Summary!$K$19),0,IF(J2<=Summary!$E$7,Summary!$E$6/12*Financing!J4,PMT(Summary!$E$6/12,Summary!$E$9,-Summary!$E$2,0,0))) -> 86666.667 | ... ED5: =IF(ED2>MIN(Summary!$E$10,Summary!$K$19),0,IF(ED2<=Summary!$E$7,Summary!$E$6/12*Financing!ED4,PMT(Summary!$E$6/12,Summary!$E$9,-Summary!$E$2,0,0))) -> 0
A6: =SUM(C6:ED6) -> 934393.25 | B6: Principal Payment | C6: =C5-C7 -> 0 | D6: =D5-D7 -> 0 | E6: =E5-E7 -> 0 | F6: =F5-F7 -> 0 | G6: =G5-G7 -> 0 | H6: =H5-H7 -> 0 | I6: =I5-I7 -> 0 | J6: =J5-J7 -> 0 | ... ED6: =ED5-ED7 -> 0
A7: =SUM(C7:ED7) -> 5164678.2 | B7: Interest Payment | C7: =C4*Summary!$E$6/12 -> 86666.667 | D7: =D4*Summary!$E$6/12 -> 86666.667 | E7: =E4*Summary!$E$6/12 -> 86666.667 | F7: =F4*Summary!$E$6/12 -> 86666.667 | G7: =G4*Summary!$E$6/12 -> 86666.667 | H7: =H4*Summary!$E$6/12 -> 86666.667 | I7: =I4*Summary!$E$6/12 -> 86666.667 | J7: =J4*Summary!$E$6/12 -> 86666.667 | ... ED7: =ED4*Summary!$E$6/12 -> 0
A8: =SUM(C8:ED8) -> -25065607 | B8: Loan Payoff | C8: =IF(C2=MIN(Summary!$E$10,Summary!$K$19),-Financing!C4+Financing!C6,0) -> 0 | D8: =IF(D2=MIN(Summary!$E$10,Summary!$K$19),-Financing!D4+Financing!D6,0) -> 0 | E8: =IF(E2=MIN(Summary!$E$10,Summary!$K$19),-Financing!E4+Financing!E6,0) -> 0 | F8: =IF(F2=MIN(Summary!$E$10,Summary!$K$19),-Financing!F4+Financing!F6,0) -> 0 | G8: =IF(G2=MIN(Summary!$E$10,Summary!$K$19),-Financing!G4+Financing!G6,0) -> 0 | H8: =IF(H2=MIN(Summary!$E$10,Summary!$K$19),-Financing!H4+Financing!H6,0) -> 0 | I8: =IF(I2=MIN(Summary!$E$10,Summary!$K$19),-Financing!I4+Financing!I6,0) -> 0 | J8: =IF(J2=MIN(Summary!$E$10,Summary!$K$19),-Financing!J4+Financing!J6,0) -> 0 | ... ED8: =IF(ED2=MIN(Summary!$E$10,Summary!$K$19),-Financing!ED4+Financing!ED6,0) -> 0
B9: Ending Balance | C9: =C4-C6+C8 -> 26000000 | D9: =D4-D6+D8 -> 26000000 | E9: =E4-E6+E8 -> 26000000 | F9: =F4-F6+F8 -> 26000000 | G9: =G4-G6+G8 -> 26000000 | H9: =H4-H6+H8 -> 26000000 | I9: =I4-I6+I8 -> 26000000 | J9: =J4-J6+J8 -> 26000000 | ... ED9: =ED4-ED6+ED8 -> 0
A11: Check | B11: Refinancing | ED11: 0
A12: =IF(ABS(A16-A18-A14)<0.0001,"OK","ERROR") -> OK | B12: Month | C12: 1 | D12: =C12+1 -> 2 | E12: =D12+1 -> 3 | F12: =E12+1 -> 4 | G12: =F12+1 -> 5 | H12: =G12+1 -> 6 | I12: =H12+1 -> 7 | J12: =I12+1 -> 8 | K12: =J12+1 -> 9 | ... ED12: =EC12+1 -> 132
B13: Date | C13: =C3 -> 44255 | D13: =EOMONTH(C13,1) -> 44286 | E13: =EOMONTH(D13,1) -> 44316 | F13: =EOMONTH(E13,1) -> 44347 | G13: =EOMONTH(F13,1) -> 44377 | H13: =EOMONTH(G13,1) -> 44408 | I13: =EOMONTH(H13,1) -> 44439 | J13: =EOMONTH(I13,1) -> 44469 | K13: =EOMONTH(J13,1) -> 44500 | ... ED13: =EOMONTH(EC13,1) -> 48244
A14: =MAX(C14:ED14) -> 30000000 | B14: Starting Balance | C14: =IF(OR(C12>Summary!$K$19,Summary!$K$19=Summary!$E$10,C12<Summary!$E$10),0,IF(C12=Summary!$E$13,Summary!$E$14,Financing!B19)) -> 0 | D14: =IF(OR(D12>Summary!$K$19,Summary!$K$19=Summary!$E$10,D12<Summary!$E$10),0,IF(D12=Summary!$E$13,Summary!$E$14,Financing!C19)) -> 0 | E14: =IF(OR(E12>Summary!$K$19,Summary!$K$19=Summary!$E$10,E12<Summary!$E$10),0,IF(E12=Summary!$E$13,Summary!$E$14,Financing!D19)) -> 0 | F14: =IF(OR(F12>Summary!$K$19,Summary!$K$19=Summary!$E$10,F12<Summary!$E$10),0,IF(F12=Summary!$E$13,Summary!$E$14,Financing!E19)) -> 0 | G14: =IF(OR(G12>Summary!$K$19,Summary!$K$19=Summary!$E$10,G12<Summary!$E$10),0,IF(G12=Summary!$E$13,Summary!$E$14,Financing!F19)) -> 0 | H14: =IF(OR(H12>Summary!$K$19,Summary!$K$19=Summary!$E$10,H12<Summary!$E$10),0,IF(H12=Summary!$E$13,Summary!$E$14,Financing!G19)) -> 0 | I14: =IF(OR(I12>Summary!$K$19,Summary!$K$19=Summary!$E$10,I12<Summary!$E$10),0,IF(I12=Summary!$E$13,Summary!$E$14,Financing!H19)) -> 0 | J14: =IF(OR(J12>Summary!$K$19,Summary!$K$19=Summary!$E$10,J12<Summary!$E$10),0,IF(J12=Summary!$E$13,Summary!$E$14,Financing!I19)) -> 0 | ... ED14: =IF(OR(ED12>Summary!$K$19,Summary!$K$19=Summary!$E$10,ED12<Summary!$E$10),0,IF(ED12=Summary!$E$13,Summary!$E$14,Financing!EC19)) -> 0
A15: =SUM(C15:ED15) -> 7037390.1 | B15: Total Loan Payment | C15: =IF(OR(C12>Summary!$K$19,C12<=Summary!$E$13),0,IF(C12<=Summary!$E$13+Summary!$E$20,Summary!$E$19/12*Financing!C14,PMT(Summary!$E$19/12,Summary!$E$22,-Summary!$E$14,0,0))) -> 0 | D15: =IF(OR(D12>Summary!$K$19,D12<=Summary!$E$13),0,IF(D12<=Summary!$E$13+Summary!$E$20,Summary!$E$19/12*Financing!D14,PMT(Summary!$E$19/12,Summary!$E$22,-Summary!$E$14,0,0))) -> 0 | E15: =IF(OR(E12>Summary!$K$19,E12<=Summary!$E$13),0,IF(E12<=Summary!$E$13+Summary!$E$20,Summary!$E$19/12*Financing!E14,PMT(Summary!$E$19/12,Summary!$E$22,-Summary!$E$14,0,0))) -> 0 | F15: =IF(OR(F12>Summary!$K$19,F12<=Summary!$E$13),0,IF(F12<=Summary!$E$13+Summary!$E$20,Summary!$E$19/12*Financing!F14,PMT(Summary!$E$19/12,Summary!$E$22,-Summary!$E$14,0,0))) -> 0 | G15: =IF(OR(G12>Summary!$K$19,G12<=Summary!$E$13),0,IF(G12<=Summary!$E$13+Summary!$E$20,Summary!$E$19/12*Financing!G14,PMT(Summary!$E$19/12,Summary!$E$22,-Summary!$E$14,0,0))) -> 0 | H15: =IF(OR(H12>Summary!$K$19,H12<=Summary!$E$13),0,IF(H12<=Summary!$E$13+Summary!$E$20,Summary!$E$19/12*Financing!H14,PMT(Summary!$E$19/12,Summary!$E$22,-Summary!$E$14,0,0))) -> 0 | I15: =IF(OR(I12>Summary!$K$19,I12<=Summary!$E$13),0,IF(I12<=Summary!$E$13+Summary!$E$20,Summary!$E$19/12*Financing!I14,PMT(Summary!$E$19/12,Summary!$E$22,-Summary!$E$14,0,0))) -> 0 | J15: =IF(OR(J12>Summary!$K$19,J12<=Summary!$E$13),0,IF(J12<=Summary!$E$13+Summary!$E$20,Summary!$E$19/12*Financing!J14,PMT(Summary!$E$19/12,Summary!$E$22,-Summary!$E$14,0,0))) -> 0 | ... ED15: =IF(OR(ED12>Summary!$K$19,ED12<=Summary!$E$13),0,IF(ED12<=Summary!$E$13+Summary!$E$20,Summary!$E$19/12*Financing!ED14,PMT(Summary!$E$19/12,Summary!$E$22,-Summary!$E$14,0,0))) -> 0
A16: =SUM(C16:ED16) -> 1078146.1 | B16: Principal Payment | C16: =C15-C17 -> 0 | D16: =D15-D17 -> 0 | E16: =E15-E17 -> 0 | F16: =F15-F17 -> 0 | G16: =G15-G17 -> 0 | H16: =H15-H17 -> 0 | I16: =I15-I17 -> 0 | J16: =J15-J17 -> 0 | ... ED16: =ED15-ED17 -> 0
A17: =SUM(C17:ED17) -> 5959244.1 | B17: Interest Payment | C17: =IF(C12=Summary!$E$13,0,Summary!$E$19/12*Financing!C14) -> 0 | D17: =IF(D12=Summary!$E$13,0,Summary!$E$19/12*Financing!D14) -> 0 | E17: =IF(E12=Summary!$E$13,0,Summary!$E$19/12*Financing!E14) -> 0 | F17: =IF(F12=Summary!$E$13,0,Summary!$E$19/12*Financing!F14) -> 0 | G17: =IF(G12=Summary!$E$13,0,Summary!$E$19/12*Financing!G14) -> 0 | H17: =IF(H12=Summary!$E$13,0,Summary!$E$19/12*Financing!H14) -> 0 | I17: =IF(I12=Summary!$E$13,0,Summary!$E$19/12*Financing!I14) -> 0 | J17: =IF(J12=Summary!$E$13,0,Summary!$E$19/12*Financing!J14) -> 0 | ... ED17: =IF(ED12=Summary!$E$13,0,Summary!$E$19/12*Financing!ED14) -> 0
A18: =SUM(C18:ED18) -> -28921854 | B18: Loan Payoff | C18: =IF(C12=Summary!$K$19,-Financing!C14+Financing!C16,0) -> 0 | D18: =IF(D12=Summary!$K$19,-Financing!D14+Financing!D16,0) -> 0 | E18: =IF(E12=Summary!$K$19,-Financing!E14+Financing!E16,0) -> 0 | F18: =IF(F12=Summary!$K$19,-Financing!F14+Financing!F16,0) -> 0 | G18: =IF(G12=Summary!$K$19,-Financing!G14+Financing!G16,0) -> 0 | H18: =IF(H12=Summary!$K$19,-Financing!H14+Financing!H16,0) -> 0 | I18: =IF(I12=Summary!$K$19,-Financing!I14+Financing!I16,0) -> 0 | J18: =IF(J12=Summary!$K$19,-Financing!J14+Financing!J16,0) -> 0 | ... ED18: =IF(ED12=Summary!$K$19,-Financing!ED14+Financing!ED16,0) -> 0
B19: Ending Balance | C19: =C14-C16+C18 -> 0 | D19: =D14-D16+D18 -> 0 | E19: =E14-E16+E18 -> 0 | F19: =F14-F16+F18 -> 0 | G19: =G14-G16+G18 -> 0 | H19: =H14-H16+H18 -> 0 | I19: =I14-I16+I18 -> 0 | J19: =J14-J16+J18 -> 0 | ... ED19: =ED14-ED16+ED18 -> 0

Sheet Monthly CF
B1: Month | C1: 0 | D1: 1 | E1: =D1+1 -> 2 | F1: =E1+1 -> 3 | G1: =F1+1 -> 4 | H1: =G1+1 -> 5 | I1: =H1+1 -> 6 | J1: =I1+1 -> 7 | K1: =J1+1 -> 8 | L1: =K1+1 -> 9 | ... EE1: =ED1+1 -> 132
B2: Year | C2: 0 | D2: =ROUNDUP(D1/12,0) -> 1 | E2: =ROUNDUP(E1/12,0) -> 1 | F2: =ROUNDUP(F1/12,0) -> 1 | G2: =ROUNDUP(G1/12,0) -> 1 | H2: =ROUNDUP(H1/12,0) -> 1 | I2: =ROUNDUP(I1/12,0) -> 1 | J2: =ROUNDUP(J1/12,0) -> 1 | K2: =ROUNDUP(K1/12,0) -> 1 | ... EE2: =ROUNDUP(EE1/12,0) -> 11
B3: Month Ending | C3: =Summary!B25 -> 44227 | D3: =EOMONTH(C3,1) -> 44255 | E3: =EOMONTH(D3,1) -> 44286 | F3: =EOMONTH(E3,1) -> 44316 | G3: =EOMONTH(F3,1) -> 44347 | H3: =EOMONTH(G3,1) -> 44377 | I3: =EOMONTH(H3,1) -> 44408 | J3: =EOMONTH(I3,1) -> 44439 | K3: =EOMONTH(J3,1) -> 44469 | ... EE3: =EOMONTH(ED3,1) -> 48244
B5: Revenue
A6: =SUMIF($C$1:$EE$1,"<="&Summary!$K$19,'Monthly CF'!C6:EE6) -> 36563661 | B6: Gross Potential Rental Revenue | D6: =Revenue!AF5 -> 245000 | E6: =Revenue!AG5 -> 245998.16 | F6: =Revenue!AH5 -> 247000.39 | G6: =Revenue!AI5 -> 248006.7 | H6: =Revenue!AJ5 -> 250033.5 | I6: =Revenue!AK5 -> 252072.71 | J6: =Revenue!AL5 -> 254124.38 | K6: =Revenue!AM5 -> 256188.58 | ... EE6: =Revenue!FG5 -> 363854.59
A7: =SUMIF($C$1:$EE$1,"<="&Summary!$K$19,'Monthly CF'!C7:EE7) -> -1875029.6 | B7: Physical Vacancy | D7: =D$6*-HLOOKUP(D$2,Revenue!$S$1:$AC$5,MATCH('Monthly CF'!$B7,Revenue!$R$1:$R$5,0),0) -> -14700 | E7: =E$6*-HLOOKUP(E$2,Revenue!$S$1:$AC$5,MATCH('Monthly CF'!$B7,Revenue!$R$1:$R$5,0),0) -> -14759.89 | F7: =F$6*-HLOOKUP(F$2,Revenue!$S$1:$AC$5,MATCH('Monthly CF'!$B7,Revenue!$R$1:$R$5,0),0) -> -14820.023 | G7: =G$6*-HLOOKUP(G$2,Revenue!$S$1:$AC$5,MATCH('Monthly CF'!$B7,Revenue!$R$1:$R$5,0),0) -> -14880.402 | H7: =H$6*-HLOOKUP(H$2,Revenue!$S$1:$AC$5,MATCH('Monthly CF'!$B7,Revenue!$R$1:$R$5,0),0) -> -15002.01 | I7: =I$6*-HLOOKUP(I$2,Revenue!$S$1:$AC$5,MATCH('Monthly CF'!$B7,Revenue!$R$1:$R$5,0),0) -> -15124.363 | J7: =J$6*-HLOOKUP(J$2,Revenue!$S$1:$AC$5,MATCH('Monthly CF'!$B7,Revenue!$R$1:$R$5,0),0) -> -15247.463 | K7: =K$6*-HLOOKUP(K$2,Revenue!$S$1:$AC$5,MATCH('Monthly CF'!$B7,Revenue!$R$1:$R$5,0),0) -> -15371.315 | ... EE7: =EE$6*-HLOOKUP(EE$2,Revenue!$S$1:$AC$5,MATCH('Monthly CF'!$B7,Revenue!$R$1:$R$5,0),0) -> -18192.729
A8: =SUMIF($C$1:$EE$1,"<="&Summary!$K$19,'Monthly CF'!C8:EE8) -> -206241.58 | B8: Bad Debt | D8: =D$6*-HLOOKUP(D$2,Revenue!$S$1:$AC$5,MATCH('Monthly CF'!$B8,Revenue!$R$1:$R$5,0),0) -> -2450 | E8: =E$6*-HLOOKUP(E$2,Revenue!$S$1:$AC$5,MATCH('Monthly CF'!$B8,Revenue!$R$1:$R$5,0),0) -> -2459.9816 | F8: =F$6*-HLOOKUP(F$2,Revenue!$S$1:$AC$5,MATCH('Monthly CF'!$B8,Revenue!$R$1:$R$5,0),0) -> -2470.0039 | G8: =G$6*-HLOOKUP(G$2,Revenue!$S$1:$AC$5,MATCH('Monthly CF'!$B8,Revenue!$R$1:$R$5,0),0) -> -2480.067 | H8: =H$6*-HLOOKUP(H$2,Revenue!$S$1:$AC$5,MATCH('Monthly CF'!$B8,Revenue!$R$1:$R$5,0),0) -> -2500.335 | I8: =I$6*-HLOOKUP(I$2,Revenue!$S$1:$AC$5,MATCH('Monthly CF'!$B8,Revenue!$R$1:$R$5,0),0) -> -2520.7271 | J8: =J$6*-HLOOKUP(J$2,Revenue!$S$1:$AC$5,MATCH('Monthly CF'!$B8,Revenue!$R$1:$R$5,0),0) -> -2541.2438 | K8: =K$6*-HLOOKUP(K$2,Revenue!$S$1:$AC$5,MATCH('Monthly CF'!$B8,Revenue!$R$1:$R$5,0),0) -> -2561.8858 | ... EE8: =EE$6*-HLOOKUP(EE$2,Revenue!$S$1:$AC$5,MATCH('Monthly CF'!$B8,Revenue!$R$1:$R$5,0),0) -> -1819.2729
A9: =SUMIF($C$1:$EE$1,"<="&Summary!$K$19,'Monthly CF'!C9:EE9) -> -46846.558 | B9: Concessions | D9: =D$6*-HLOOKUP(D$2,Revenue!$S$1:$AC$5,MATCH('Monthly CF'!$B9,Revenue!$R$1:$R$5,0),0) -> -2450 | E9: =E$6*-HLOOKUP(E$2,Revenue!$S$1:$AC$5,MATCH('Monthly CF'!$B9,Revenue!$R$1:$R$5,0),0) -> -2459.9816 | F9: =F$6*-HLOOKUP(F$2,Revenue!$S$1:$AC$5,MATCH('Monthly CF'!$B9,Revenue!$R$1:$R$5,0),0) -> -2470.0039 | G9: =G$6*-HLOOKUP(G$2,Revenue!$S$1:$AC$5,MATCH('Monthly CF'!$B9,Revenue!$R$1:$R$5,0),0) -> -2480.067 | H9: =H$6*-HLOOKUP(H$2,Revenue!$S$1:$AC$5,MATCH('Monthly CF'!$B9,Revenue!$R$1:$R$5,0),0) -> -2500.335 | I9: =I$6*-HLOOKUP(I$2,Revenue!$S$1:$AC$5,MATCH('Monthly CF'!$B9,Revenue!$R$1:$R$5,0),0) -> -2520.7271 | J9: =J$6*-HLOOKUP(J$2,Revenue!$S$1:$AC$5,MATCH('Monthly CF'!$B9,Revenue!$R$1:$R$5,0),0) -> -2541.2438 | K9: =K$6*-HLOOKUP(K$2,Revenue!$S$1:$AC$5,MATCH('Monthly CF'!$B9,Revenue!$R$1:$R$5,0),0) -> -2561.8858 | ... EE9: =EE$6*-HLOOKUP(EE$2,Revenue!$S$1:$AC$5,MATCH('Monthly CF'!$B9,Revenue!$R$1:$R$5,0),0) -> 0
A10: =SUMIF($C$1:$EE$1,"<="&Summary!$K$19,'Monthly CF'!C10:EE10) -> 0 | B10: Other Loss | D10: =D$6*-HLOOKUP(D$2,Revenue!$S$1:$AC$5,MATCH('Monthly CF'!$B10,Revenue!$R$1:$R$5,0),0) -> 0 | E10: =E$6*-HLOOKUP(E$2,Revenue!$S$1:$AC$5,MATCH('Monthly CF'!$B10,Revenue!$R$1:$R$5,0),0) -> 0 | F10: =F$6*-HLOOKUP(F$2,Revenue!$S$1:$AC$5,MATCH('Monthly CF'!$B10,Revenue!$R$1:$R$5,0),0) -> 0 | G10: =G$6*-HLOOKUP(G$2,Revenue!$S$1:$AC$5,MATCH('Monthly CF'!$B10,Revenue!$R$1:$R$5,0),0) -> 0 | H10: =H$6*-HLOOKUP(H$2,Revenue!$S$1:$AC$5,MATCH('Monthly CF'!$B10,Revenue!$R$1:$R$5,0),0) -> 0 | I10: =I$6*-HLOOKUP(I$2,Revenue!$S$1:$AC$5,MATCH('Monthly CF'!$B10,Revenue!$R$1:$R$5,0),0) -> 0 | J10: =J$6*-HLOOKUP(J$2,Revenue!$S$1:$AC$5,MATCH('Monthly CF'!$B10,Revenue!$R$1:$R$5,0),0) -> 0 | K10: =K$6*-HLOOKUP(K$2,Revenue!$S$1:$AC$5,MATCH('Monthly CF'!$B10,Revenue!$R$1:$R$5,0),0) -> 0 | ... EE10: =EE$6*-HLOOKUP(EE$2,Revenue!$S$1:$AC$5,MATCH('Monthly CF'!$B10,Revenue!$R$1:$R$5,0),0) -> 0
A11: =SUMIF($C$1:$EE$1,"<="&Summary!$K$19,'Monthly CF'!C11:EE11) -> 34435543 | B11: Net Rental Income | D11: =SUM(D6:D10) -> 225400 | E11: =SUM(E6:E10) -> 226318.31 | F11: =SUM(F6:F10) -> 227240.36 | G11: =SUM(G6:G10) -> 228166.16 | H11: =SUM(H6:H10) -> 230030.82 | I11: =SUM(I6:I10) -> 231906.89 | J11: =SUM(J6:J10) -> 233794.43 | K11: =SUM(K6:K10) -> 235693.5 | ... EE11: =SUM(EE6:EE10) -> 343842.59
B13: Other Income
A14: =SUMIF($C$1:$EE$1,"<="&Summary!$K$19,'Monthly CF'!C14:EE14) -> 153392.8 | B14: =Revenue!O2 -> Laundry Income | D14: =IF(D$1=1,Revenue!$P2*Revenue!$A$23,'Monthly CF'!C14*((1+HLOOKUP('Monthly CF'!C$2,Revenue!$S$8:$AC$10,3,0))^(1/12))) -> 1100 | E14: =IF(E$1=1,Revenue!$P2*Revenue!$A$23,'Monthly CF'!D14*((1+HLOOKUP('Monthly CF'!D$2,Revenue!$S$8:$AC$10,3,0))^(1/12))) -> 1102.7129 | F14: =IF(F$1=1,Revenue!$P2*Revenue!$A$23,'Monthly CF'!E14*((1+HLOOKUP('Monthly CF'!E$2,Revenue!$S$8:$AC$10,3,0))^(1/12))) -> 1105.4325 | G14: =IF(G$1=1,Revenue!$P2*Revenue!$A$23,'Monthly CF'!F14*((1+HLOOKUP('Monthly CF'!F$2,Revenue!$S$8:$AC$10,3,0))^(1/12))) -> 1108.1588 | H14: =IF(H$1=1,Revenue!$P2*Revenue!$A$23,'Monthly CF'!G14*((1+HLOOKUP('Monthly CF'!G$2,Revenue!$S$8:$AC$10,3,0))^(1/12))) -> 1110.8918 | I14: =IF(I$1=1,Revenue!$P2*Revenue!$A$23,'Monthly CF'!H14*((1+HLOOKUP('Monthly CF'!H$2,Revenue!$S$8:$AC$10,3,0))^(1/12))) -> 1113.6316 | J14: =IF(J$1=1,Revenue!$P2*Revenue!$A$23,'Monthly CF'!I14*((1+HLOOKUP('Monthly CF'!I$2,Revenue!$S$8:$AC$10,3,0))^(1/12))) -> 1116.3781 | K14: =IF(K$1=1,Revenue!$P2*Revenue!$A$23,'Monthly CF'!J14*((1+HLOOKUP('Monthly CF'!J$2,Revenue!$S$8:$AC$10,3,0))^(1/12))) -> 1119.1314 | ... EE14: =IF(EE$1=1,Revenue!$P2*Revenue!$A$23,'Monthly CF'!ED14*((1+HLOOKUP('Monthly CF'!ED$2,Revenue!$S$8:$AC$10,3,0))^(1/12))) -> 1518.9112
A15: =SUMIF($C$1:$EE$1,"<="&Summary!$K$19,'Monthly CF'!C15:EE15) -> 153392.8 | B15: =Revenue!O3 -> Late Fees | D15: =IF(D$1=1,Revenue!$P3*Revenue!$A$23,'Monthly CF'!C15*((1+HLOOKUP('Monthly CF'!C$2,Revenue!$S$8:$AC$10,3,0))^(1/12))) -> 1100 | E15: =IF(E$1=1,Revenue!$P3*Revenue!$A$23,'Monthly CF'!D15*((1+HLOOKUP('Monthly CF'!D$2,Revenue!$S$8:$AC$10,3,0))^(1/12))) -> 1102.7129 | F15: =IF(F$1=1,Revenue!$P3*Revenue!$A$23,'Monthly CF'!E15*((1+HLOOKUP('Monthly CF'!E$2,Revenue!$S$8:$AC$10,3,0))^(1/12))) -> 1105.4325 | G15: =IF(G$1=1,Revenue!$P3*Revenue!$A$23,'Monthly CF'!F15*((1+HLOOKUP('Monthly CF'!F$2,Revenue!$S$8:$AC$10,3,0))^(1/12))) -> 1108.1588 | H15: =IF(H$1=1,Revenue!$P3*Revenue!$A$23,'Monthly CF'!G15*((1+HLOOKUP('Monthly CF'!G$2,Revenue!$S$8:$AC$10,3,0))^(1/12))) -> 1110.8918 | I15: =IF(I$1=1,Revenue!$P3*Revenue!$A$23,'Monthly CF'!H15*((1+HLOOKUP('Monthly CF'!H$2,Revenue!$S$8:$AC$10,3,0))^(1/12))) -> 1113.6316 | J15: =IF(J$1=1,Revenue!$P3*Revenue!$A$23,'Monthly CF'!I15*((1+HLOOKUP('Monthly CF'!I$2,Revenue!$S$8:$AC$10,3,0))^(1/12))) -> 1116.3781 | K15: =IF(K$1=1,Revenue!$P3*Revenue!$A$23,'Monthly CF'!J15*((1+HLOOKUP('Monthly CF'!J$2,Revenue!$S$8:$AC$10,3,0))^(1/12))) -> 1119.1314 | ... EE15: =IF(EE$1=1,Revenue!$P3*Revenue!$A$23,'Monthly CF'!ED15*((1+HLOOKUP('Monthly CF'!ED$2,Revenue!$S$8:$AC$10,3,0))^(1/12))) -> 1518.9112
A16: =SUMIF($C$1:$EE$1,"<="&Summary!$K$19,'Monthly CF'!C16:EE16) -> 383481.99 | B16: =Revenue!O4 -> Pet Rent | D16: =IF(D$1=1,Revenue!$P4*Revenue!$A$23,'Monthly CF'!C16*((1+HLOOKUP('Monthly CF'!C$2,Revenue!$S$8:$AC$10,3,0))^(1/12))) -> 2750 | E16: =IF(E$1=1,Revenue!$P4*Revenue!$A$23,'Monthly CF'!D16*((1+HLOOKUP('Monthly CF'!D$2,Revenue!$S$8:$AC$10,3,0))^(1/12))) -> 2756.7822 | F16: =IF(F$1=1,Revenue!$P4*Revenue!$A$23,'Monthly CF'!E16*((1+HLOOKUP('Monthly CF'!E$2,Revenue!$S$8:$AC$10,3,0))^(1/12))) -> 2763.5812 | G16: =IF(G$1=1,Revenue!$P4*Revenue!$A$23,'Monthly CF'!F16*((1+HLOOKUP('Monthly CF'!F$2,Revenue!$S$8:$AC$10,3,0))^(1/12))) -> 2770.3969 | H16: =IF(H$1=1,Revenue!$P4*Revenue!$A$23,'Monthly CF'!G16*((1+HLOOKUP('Monthly CF'!G$2,Revenue!$S$8:$AC$10,3,0))^(1/12))) -> 2777.2295 | I16: =IF(I$1=1,Revenue!$P4*Revenue!$A$23,'Monthly CF'!H16*((1+HLOOKUP('Monthly CF'!H$2,Revenue!$S$8:$AC$10,3,0))^(1/12))) -> 2784.0789 | J16: =IF(J$1=1,Revenue!$P4*Revenue!$A$23,'Monthly CF'!I16*((1+HLOOKUP('Monthly CF'!I$2,Revenue!$S$8:$AC$10,3,0))^(1/12))) -> 2790.9452 | K16: =IF(K$1=1,Revenue!$P4*Revenue!$A$23,'Monthly CF'!J16*((1+HLOOKUP('Monthly CF'!J$2,Revenue!$S$8:$AC$10,3,0))^(1/12))) -> 2797.8284 | ... EE16: =IF(EE$1=1,Revenue!$P4*Revenue!$A$23,'Monthly CF'!ED16*((1+HLOOKUP('Monthly CF'!ED$2,Revenue!$S$8:$AC$10,3,0))^(1/12))) -> 3797.278
A17: =SUMIF($C$1:$EE$1,"<="&Summary!$K$19,'Monthly CF'!C17:EE17) -> 76696.398 | B17: =Revenue!O5 -> Pet Fees | D17: =IF(D$1=1,Revenue!$P5*Revenue!$A$23,'Monthly CF'!C17*((1+HLOOKUP('Monthly CF'!C$2,Revenue!$S$8:$AC$10,3,0))^(1/12))) -> 550 | E17: =IF(E$1=1,Revenue!$P5*Revenue!$A$23,'Monthly CF'!D17*((1+HLOOKUP('Monthly CF'!D$2,Revenue!$S$8:$AC$10,3,0))^(1/12))) -> 551.35645 | F17: =IF(F$1=1,Revenue!$P5*Revenue!$A$23,'Monthly CF'!E17*((1+HLOOKUP('Monthly CF'!E$2,Revenue!$S$8:$AC$10,3,0))^(1/12))) -> 552.71624 | G17: =IF(G$1=1,Revenue!$P5*Revenue!$A$23,'Monthly CF'!F17*((1+HLOOKUP('Monthly CF'!F$2,Revenue!$S$8:$AC$10,3,0))^(1/12))) -> 554.07939 | H17: =IF(H$1=1,Revenue!$P5*Revenue!$A$23,'Monthly CF'!G17*((1+HLOOKUP('Monthly CF'!G$2,Revenue!$S$8:$AC$10,3,0))^(1/12))) -> 555.4459 | I17: =IF(I$1=1,Revenue!$P5*Revenue!$A$23,'Monthly CF'!H17*((1+HLOOKUP('Monthly CF'!H$2,Revenue!$S$8:$AC$10,3,0))^(1/12))) -> 556.81578 | J17: =IF(J$1=1,Revenue!$P5*Revenue!$A$23,'Monthly CF'!I17*((1+HLOOKUP('Monthly CF'!I$2,Revenue!$S$8:$AC$10,3,0))^(1/12))) -> 558.18904 | K17: =IF(K$1=1,Revenue!$P5*Revenue!$A$23,'Monthly CF'!J17*((1+HLOOKUP('Monthly CF'!J$2,Revenue!$S$8:$AC$10,3,0))^(1/12))) -> 559.56568 | ... EE17: =IF(EE$1=1,Revenue!$P5*Revenue!$A$23,'Monthly CF'!ED17*((1+HLOOKUP('Monthly CF'!ED$2,Revenue!$S$8:$AC$10,3,0))^(1/12))) -> 759.45561
A18: =SUMIF($C$1:$EE$1,"<="&Summary!$K$19,'Monthly CF'!C18:EE18) -> 0 | B18: =Revenue!O6 -> Garage Income | D18: =IF(D$1=1,Revenue!$P6*Revenue!$A$23,'Monthly CF'!C18*((1+HLOOKUP('Monthly CF'!C$2,Revenue!$S$8:$AC$10,3,0))^(1/12))) -> 0 | E18: =IF(E$1=1,Revenue!$P6*Revenue!$A$23,'Monthly CF'!D18*((1+HLOOKUP('Monthly CF'!D$2,Revenue!$S$8:$AC$10,3,0))^(1/12))) -> 0 | F18: =IF(F$1=1,Revenue!$P6*Revenue!$A$23,'Monthly CF'!E18*((1+HLOOKUP('Monthly CF'!E$2,Revenue!$S$8:$AC$10,3,0))^(1/12))) -> 0 | G18: =IF(G$1=1,Revenue!$P6*Revenue!$A$23,'Monthly CF'!F18*((1+HLOOKUP('Monthly CF'!F$2,Revenue!$S$8:$AC$10,3,0))^(1/12))) -> 0 | H18: =IF(H$1=1,Revenue!$P6*Revenue!$A$23,'Monthly CF'!G18*((1+HLOOKUP('Monthly CF'!G$2,Revenue!$S$8:$AC$10,3,0))^(1/12))) -> 0 | I18: =IF(I$1=1,Revenue!$P6*Revenue!$A$23,'Monthly CF'!H18*((1+HLOOKUP('Monthly CF'!H$2,Revenue!$S$8:$AC$10,3,0))^(1/12))) -> 0 | J18: =IF(J$1=1,Revenue!$P6*Revenue!$A$23,'Monthly CF'!I18*((1+HLOOKUP('Monthly CF'!I$2,Revenue!$S$8:$AC$10,3,0))^(1/12))) -> 0 | K18: =IF(K$1=1,Revenue!$P6*Revenue!$A$23,'Monthly CF'!J18*((1+HLOOKUP('Monthly CF'!J$2,Revenue!$S$8:$AC$10,3,0))^(1/12))) -> 0 | ... EE18: =IF(EE$1=1,Revenue!$P6*Revenue!$A$23,'Monthly CF'!ED18*((1+HLOOKUP('Monthly CF'!ED$2,Revenue!$S$8:$AC$10,3,0))^(1/12))) -> 0
A19: =SUMIF($C$1:$EE$1,"<="&Summary!$K$19,'Monthly CF'!C19:EE19) -> 0 | B19: =Revenue!O7 -> Storage Income | D19: =IF(D$1=1,Revenue!$P7*Revenue!$A$23,'Monthly CF'!C19*((1+HLOOKUP('Monthly CF'!C$2,Revenue!$S$8:$AC$10,3,0))^(1/12))) -> 0 | E19: =IF(E$1=1,Revenue!$P7*Revenue!$A$23,'Monthly CF'!D19*((1+HLOOKUP('Monthly CF'!D$2,Revenue!$S$8:$AC$10,3,0))^(1/12))) -> 0 | F19: =IF(F$1=1,Revenue!$P7*Revenue!$A$23,'Monthly CF'!E19*((1+HLOOKUP('Monthly CF'!E$2,Revenue!$S$8:$AC$10,3,0))^(1/12))) -> 0 | G19: =IF(G$1=1,Revenue!$P7*Revenue!$A$23,'Monthly CF'!F19*((1+HLOOKUP('Monthly CF'!F$2,Revenue!$S$8:$AC$10,3,0))^(1/12))) -> 0 | H19: =IF(H$1=1,Revenue!$P7*Revenue!$A$23,'Monthly CF'!G19*((1+HLOOKUP('Monthly CF'!G$2,Revenue!$S$8:$AC$10,3,0))^(1/12))) -> 0 | I19: =IF(I$1=1,Revenue!$P7*Revenue!$A$23,'Monthly CF'!H19*((1+HLOOKUP('Monthly CF'!H$2,Revenue!$S$8:$AC$10,3,0))^(1/12))) -> 0 | J19: =IF(J$1=1,Revenue!$P7*Revenue!$A$23,'Monthly CF'!I19*((1+HLOOKUP('Monthly CF'!I$2,Revenue!$S$8:$AC$10,3,0))^(1/12))) -> 0 | K19: =IF(K$1=1,Revenue!$P7*Revenue!$A$23,'Monthly CF'!J19*((1+HLOOKUP('Monthly CF'!J$2,Revenue!$S$8:$AC$10,3,0))^(1/12))) -> 0 | ... EE19: =IF(EE$1=1,Revenue!$P7*Revenue!$A$23,'Monthly CF'!ED19*((1+HLOOKUP('Monthly CF'!ED$2,Revenue!$S$8:$AC$10,3,0))^(1/12))) -> 0
A20: =SUMIF($C$1:$EE$1,"<="&Summary!$K$19,'Monthly CF'!C20:EE20) -> 76696.398 | B20: =Revenue!O8 -> Forfeited Deposits | D20: =IF(D$1=1,Revenue!$P8*Revenue!$A$23,'Monthly CF'!C20*((1+HLOOKUP('Monthly CF'!C$2,Revenue!$S$8:$AC$10,3,0))^(1/12))) -> 550 | E20: =IF(E$1=1,Revenue!$P8*Revenue!$A$23,'Monthly CF'!D20*((1+HLOOKUP('Monthly CF'!D$2,Revenue!$S$8:$AC$10,3,0))^(1/12))) -> 551.35645 | F20: =IF(F$1=1,Revenue!$P8*Revenue!$A$23,'Monthly CF'!E20*((1+HLOOKUP('Monthly CF'!E$2,Revenue!$S$8:$AC$10,3,0))^(1/12))) -> 552.71624 | G20: =IF(G$1=1,Revenue!$P8*Revenue!$A$23,'Monthly CF'!F20*((1+HLOOKUP('Monthly CF'!F$2,Revenue!$S$8:$AC$10,3,0))^(1/12))) -> 554.07939 | H20: =IF(H$1=1,Revenue!$P8*Revenue!$A$23,'Monthly CF'!G20*((1+HLOOKUP('Monthly CF'!G$2,Revenue!$S$8:$AC$10,3,0))^(1/12))) -> 555.4459 | I20: =IF(I$1=1,Revenue!$P8*Revenue!$A$23,'Monthly CF'!H20*((1+HLOOKUP('Monthly CF'!H$2,Revenue!$S$8:$AC$10,3,0))^(1/12))) -> 556.81578 | J20: =IF(J$1=1,Revenue!$P8*Revenue!$A$23,'Monthly CF'!I20*((1+HLOOKUP('Monthly CF'!I$2,Revenue!$S$8:$AC$10,3,0))^(1/12))) -> 558.18904 | K20: =IF(K$1=1,Revenue!$P8*Revenue!$A$23,'Monthly CF'!J20*((1+HLOOKUP('Monthly CF'!J$2,Revenue!$S$8:$AC$10,3,0))^(1/12))) -> 559.56568 | ... EE20: =IF(EE$1=1,Revenue!$P8*Revenue!$A$23,'Monthly CF'!ED20*((1+HLOOKUP('Monthly CF'!ED$2,Revenue!$S$8:$AC$10,3,0))^(1/12))) -> 759.45561
A21: =SUMIF($C$1:$EE$1,"<="&Summary!$K$19,'Monthly CF'!C21:EE21) -> 0 | B21: =Revenue!O9 -> Other Charges | D21: =IF(D$1=1,Revenue!$P9*Revenue!$A$23,'Monthly CF'!C21*((1+HLOOKUP('Monthly CF'!C$2,Revenue!$S$8:$AC$10,3,0))^(1/12))) -> 0 | E21: =IF(E$1=1,Revenue!$P9*Revenue!$A$23,'Monthly CF'!D21*((1+HLOOKUP('Monthly CF'!D$2,Revenue!$S$8:$AC$10,3,0))^(1/12))) -> 0 | F21: =IF(F$1=1,Revenue!$P9*Revenue!$A$23,'Monthly CF'!E21*((1+HLOOKUP('Monthly CF'!E$2,Revenue!$S$8:$AC$10,3,0))^(1/12))) -> 0 | G21: =IF(G$1=1,Revenue!$P9*Revenue!$A$23,'Monthly CF'!F21*((1+HLOOKUP('Monthly CF'!F$2,Revenue!$S$8:$AC$10,3,0))^(1/12))) -> 0 | H21: =IF(H$1=1,Revenue!$P9*Revenue!$A$23,'Monthly CF'!G21*((1+HLOOKUP('Monthly CF'!G$2,Revenue!$S$8:$AC$10,3,0))^(1/12))) -> 0 | I21: =IF(I$1=1,Revenue!$P9*Revenue!$A$23,'Monthly CF'!H21*((1+HLOOKUP('Monthly CF'!H$2,Revenue!$S$8:$AC$10,3,0))^(1/12))) -> 0 | J21: =IF(J$1=1,Revenue!$P9*Revenue!$A$23,'Monthly CF'!I21*((1+HLOOKUP('Monthly CF'!I$2,Revenue!$S$8:$AC$10,3,0))^(1/12))) -> 0 | K21: =IF(K$1=1,Revenue!$P9*Revenue!$A$23,'Monthly CF'!J21*((1+HLOOKUP('Monthly CF'!J$2,Revenue!$S$8:$AC$10,3,0))^(1/12))) -> 0 | ... EE21: =IF(EE$1=1,Revenue!$P9*Revenue!$A$23,'Monthly CF'!ED21*((1+HLOOKUP('Monthly CF'!ED$2,Revenue!$S$8:$AC$10,3,0))^(1/12))) -> 0
A22: =SUMIF($C$1:$EE$1,"<="&Summary!$K$19,'Monthly CF'!C22:EE22) -> 0 | B22: =Revenue!O10 -> Other Charges | D22: =IF(D$1=1,Revenue!$P10*Revenue!$A$23,'Monthly CF'!C22*((1+HLOOKUP('Monthly CF'!C$2,Revenue!$S$8:$AC$10,3,0))^(1/12))) -> 0 | E22: =IF(E$1=1,Revenue!$P10*Revenue!$A$23,'Monthly CF'!D22*((1+HLOOKUP('Monthly CF'!D$2,Revenue!$S$8:$AC$10,3,0))^(1/12))) -> 0 | F22: =IF(F$1=1,Revenue!$P10*Revenue!$A$23,'Monthly CF'!E22*((1+HLOOKUP('Monthly CF'!E$2,Revenue!$S$8:$AC$10,3,0))^(1/12))) -> 0 | G22: =IF(G$1=1,Revenue!$P10*Revenue!$A$23,'Monthly CF'!F22*((1+HLOOKUP('Monthly CF'!F$2,Revenue!$S$8:$AC$10,3,0))^(1/12))) -> 0 | H22: =IF(H$1=1,Revenue!$P10*Revenue!$A$23,'Monthly CF'!G22*((1+HLOOKUP('Monthly CF'!G$2,Revenue!$S$8:$AC$10,3,0))^(1/12))) -> 0 | I22: =IF(I$1=1,Revenue!$P10*Revenue!$A$23,'Monthly CF'!H22*((1+HLOOKUP('Monthly CF'!H$2,Revenue!$S$8:$AC$10,3,0))^(1/12))) -> 0 | J22: =IF(J$1=1,Revenue!$P10*Revenue!$A$23,'Monthly CF'!I22*((1+HLOOKUP('Monthly CF'!I$2,Revenue!$S$8:$AC$10,3,0))^(1/12))) -> 0 | K22: =IF(K$1=1,Revenue!$P10*Revenue!$A$23,'Monthly CF'!J22*((1+HLOOKUP('Monthly CF'!J$2,Revenue!$S$8:$AC$10,3,0))^(1/12))) -> 0 | ... EE22: =IF(EE$1=1,Revenue!$P10*Revenue!$A$23,'Monthly CF'!ED22*((1+HLOOKUP('Monthly CF'!ED$2,Revenue!$S$8:$AC$10,3,0))^(1/12))) -> 0
A23: =SUMIF($C$1:$EE$1,"<="&Summary!$K$19,'Monthly CF'!C23:EE23) -> 0 | B23: =Revenue!O11 -> Other Charges | D23: =IF(D$1=1,Revenue!$P11*Revenue!$A$23,'Monthly CF'!C23*((1+HLOOKUP('Monthly CF'!C$2,Revenue!$S$8:$AC$10,3,0))^(1/12))) -> 0 | E23: =IF(E$1=1,Revenue!$P11*Revenue!$A$23,'Monthly CF'!D23*((1+HLOOKUP('Monthly CF'!D$2,Revenue!$S$8:$AC$10,3,0))^(1/12))) -> 0 | F23: =IF(F$1=1,Revenue!$P11*Revenue!$A$23,'Monthly CF'!E23*((1+HLOOKUP('Monthly CF'!E$2,Revenue!$S$8:$AC$10,3,0))^(1/12))) -> 0 | G23: =IF(G$1=1,Revenue!$P11*Revenue!$A$23,'Monthly CF'!F23*((1+HLOOKUP('Monthly CF'!F$2,Revenue!$S$8:$AC$10,3,0))^(1/12))) -> 0 | H23: =IF(H$1=1,Revenue!$P11*Revenue!$A$23,'Monthly CF'!G23*((1+HLOOKUP('Monthly CF'!G$2,Revenue!$S$8:$AC$10,3,0))^(1/12))) -> 0 | I23: =IF(I$1=1,Revenue!$P11*Revenue!$A$23,'Monthly CF'!H23*((1+HLOOKUP('Monthly CF'!H$2,Revenue!$S$8:$AC$10,3,0))^(1/12))) -> 0 | J23: =IF(J$1=1,Revenue!$P11*Revenue!$A$23,'Monthly CF'!I23*((1+HLOOKUP('Monthly CF'!I$2,Revenue!$S$8:$AC$10,3,0))^(1/12))) -> 0 | K23: =IF(K$1=1,Revenue!$P11*Revenue!$A$23,'Monthly CF'!J23*((1+HLOOKUP('Monthly CF'!J$2,Revenue!$S$8:$AC$10,3,0))^(1/12))) -> 0 | ... EE23: =IF(EE$1=1,Revenue!$P11*Revenue!$A$23,'Monthly CF'!ED23*((1+HLOOKUP('Monthly CF'!ED$2,Revenue!$S$8:$AC$10,3,0))^(1/12))) -> 0
A24: =SUMIF($C$1:$EE$1,"<="&Summary!$K$19,'Monthly CF'!C24:EE24) -> 843660.38 | B24: Total Other Income | D24: =SUM(D14:D23) -> 6050 | E24: =SUM(E14:E23) -> 6064.9209 | F24: =SUM(F14:F23) -> 6079.8787 | G24: =SUM(G14:G23) -> 6094.8733 | H24: =SUM(H14:H23) -> 6109.9049 | I24: =SUM(I14:I23) -> 6124.9736 | J24: =SUM(J14:J23) -> 6140.0794 | K24: =SUM(K14:K23) -> 6155.2225 | ... EE24: =SUM(EE14:EE23) -> 8354.0117
A26: =SUMIF($C$1:$EE$1,"<="&Summary!$K$19,'Monthly CF'!C26:EE26) -> 35279204 | B26: Effective Gross Revenue | D26: =SUM(D11,D24) -> 231450 | E26: =SUM(E11,E24) -> 232383.23 | F26: =SUM(F11,F24) -> 233320.23 | G26: =SUM(G11,G24) -> 234261.03 | H26: =SUM(H11,H24) -> 236140.73 | I26: =SUM(I11,I24) -> 238031.87 | J26: =SUM(J11,J24) -> 239934.51 | K26: =SUM(K11,K24) -> 241848.72 | ... EE26: =SUM(EE11,EE24) -> 352196.6
B28: Expenses
A29: =SUMIF($C$1:$EE$1,"<="&Summary!$K$19,'Monthly CF'!C29:EE29) -> -2300891.9 | B29: =Expenses!E3 -> Payroll | D29: =-Expenses!$F3/12*(1+Expenses!$F$17)^((D$1-1)/12) -> -16500 | E29: =-Expenses!$F3/12*(1+Expenses!$F$17)^((E$1-1)/12) -> -16540.693 | F29: =-Expenses!$F3/12*(1+Expenses!$F$17)^((F$1-1)/12) -> -16581.487 | G29: =-Expenses!$F3/12*(1+Expenses!$F$17)^((G$1-1)/12) -> -16622.382 | H29: =-Expenses!$F3/12*(1+Expenses!$F$17)^((H$1-1)/12) -> -16663.377 | I29: =-Expenses!$F3/12*(1+Expenses!$F$17)^((I$1-1)/12) -> -16704.473 | J29: =-Expenses!$F3/12*(1+Expenses!$F$17)^((J$1-1)/12) -> -16745.671 | K29: =-Expenses!$F3/12*(1+Expenses!$F$17)^((K$1-1)/12) -> -16786.97 | ... EE29: =-Expenses!$F3/12*(1+Expenses!$F$17)^((EE$1-1)/12) -> -22783.668
A30: =SUMIF($C$1:$EE$1,"<="&Summary!$K$19,'Monthly CF'!C30:EE30) -> -351525.16 | B30: =Expenses!E4 -> General & Administrative | D30: =-Expenses!$F4/12*(1+Expenses!$F$17)^((D$1-1)/12) -> -2520.8333 | E30: =-Expenses!$F4/12*(1+Expenses!$F$17)^((E$1-1)/12) -> -2527.0504 | F30: =-Expenses!$F4/12*(1+Expenses!$F$17)^((F$1-1)/12) -> -2533.2828 | G30: =-Expenses!$F4/12*(1+Expenses!$F$17)^((G$1-1)/12) -> -2539.5305 | H30: =-Expenses!$F4/12*(1+Expenses!$F$17)^((H$1-1)/12) -> -2545.7937 | I30: =-Expenses!$F4/12*(1+Expenses!$F$17)^((I$1-1)/12) -> -2552.0723 | J30: =-Expenses!$F4/12*(1+Expenses!$F$17)^((J$1-1)/12) -> -2558.3664 | K30: =-Expenses!$F4/12*(1+Expenses!$F$17)^((K$1-1)/12) -> -2564.676 | ... EE30: =-Expenses!$F4/12*(1+Expenses!$F$17)^((EE$1-1)/12) -> -3480.8382
A31: =SUMIF($C$1:$EE$1,"<="&Summary!$K$19,'Monthly CF'!C31:EE31) -> -287611.49 | B31: =Expenses!E5 -> Marketing | D31: =-Expenses!$F5/12*(1+Expenses!$F$17)^((D$1-1)/12) -> -2062.5 | E31: =-Expenses!$F5/12*(1+Expenses!$F$17)^((E$1-1)/12) -> -2067.5867 | F31: =-Expenses!$F5/12*(1+Expenses!$F$17)^((F$1-1)/12) -> -2072.6859 | G31: =-Expenses!$F5/12*(1+Expenses!$F$17)^((G$1-1)/12) -> -2077.7977 | H31: =-Expenses!$F5/12*(1+Expenses!$F$17)^((H$1-1)/12) -> -2082.9221 | I31: =-Expenses!$F5/12*(1+Expenses!$F$17)^((I$1-1)/12) -> -2088.0592 | J31: =-Expenses!$F5/12*(1+Expenses!$F$17)^((J$1-1)/12) -> -2093.2089 | K31: =-Expenses!$F5/12*(1+Expenses!$F$17)^((K$1-1)/12) -> -2098.3713 | ... EE31: =-Expenses!$F5/12*(1+Expenses!$F$17)^((EE$1-1)/12) -> -2847.9585
A32: =SUMIF($C$1:$EE$1,"<="&Summary!$K$19,'Monthly CF'!C32:EE32) -> -703050.32 | B32: =Expenses!E6 -> Repairs & Maintenance | D32: =-Expenses!$F6/12*(1+Expenses!$F$17)^((D$1-1)/12) -> -5041.6667 | E32: =-Expenses!$F6/12*(1+Expenses!$F$17)^((E$1-1)/12) -> -5054.1008 | F32: =-Expenses!$F6/12*(1+Expenses!$F$17)^((F$1-1)/12) -> -5066.5656 | G32: =-Expenses!$F6/12*(1+Expenses!$F$17)^((G$1-1)/12) -> -5079.0611 | H32: =-Expenses!$F6/12*(1+Expenses!$F$17)^((H$1-1)/12) -> -5091.5874 | I32: =-Expenses!$F6/12*(1+Expenses!$F$17)^((I$1-1)/12) -> -5104.1446 | J32: =-Expenses!$F6/12*(1+Expenses!$F$17)^((J$1-1)/12) -> -5116.7328 | K32: =-Expenses!$F6/12*(1+Expenses!$F$17)^((K$1-1)/12) -> -5129.3521 | ... EE32: =-Expenses!$F6/12*(1+Expenses!$F$17)^((EE$1-1)/12) -> -6961.6764
A33: =SUMIF($C$1:$EE$1,"<="&Summary!$K$19,'Monthly CF'!C33:EE33) -> -479352.49 | B33: =Expenses!E7 -> Turnover Costs | D33: =-Expenses!$F7/12*(1+Expenses!$F$17)^((D$1-1)/12) -> -3437.5 | E33: =-Expenses!$F7/12*(1+Expenses!$F$17)^((E$1-1)/12) -> -3445.9778 | F33: =-Expenses!$F7/12*(1+Expenses!$F$17)^((F$1-1)/12) -> -3454.4765 | G33: =-Expenses!$F7/12*(1+Expenses!$F$17)^((G$1-1)/12) -> -3462.9962 | H33: =-Expenses!$F7/12*(1+Expenses!$F$17)^((H$1-1)/12) -> -3471.5369 | I33: =-Expenses!$F7/12*(1+Expenses!$F$17)^((I$1-1)/12) -> -3480.0986 | J33: =-Expenses!$F7/12*(1+Expenses!$F$17)^((J$1-1)/12) -> -3488.6815 | K33: =-Expenses!$F7/12*(1+Expenses!$F$17)^((K$1-1)/12) -> -3497.2855 | ... EE33: =-Expenses!$F7/12*(1+Expenses!$F$17)^((EE$1-1)/12) -> -4746.5975
A34: =SUMIF($C$1:$EE$1,"<="&Summary!$K$19,'Monthly CF'!C34:EE34) -> -287611.49 | B34: =Expenses!E8 -> Contract Services | D34: =-Expenses!$F8/12*(1+Expenses!$F$17)^((D$1-1)/12) -> -2062.5 | E34: =-Expenses!$F8/12*(1+Expenses!$F$17)^((E$1-1)/12) -> -2067.5867 | F34: =-Expenses!$F8/12*(1+Expenses!$F$17)^((F$1-1)/12) -> -2072.6859 | G34: =-Expenses!$F8/12*(1+Expenses!$F$17)^((G$1-1)/12) -> -2077.7977 | H34: =-Expenses!$F8/12*(1+Expenses!$F$17)^((H$1-1)/12) -> -2082.9221 | I34: =-Expenses!$F8/12*(1+Expenses!$F$17)^((I$1-1)/12) -> -2088.0592 | J34: =-Expenses!$F8/12*(1+Expenses!$F$17)^((J$1-1)/12) -> -2093.2089 | K34: =-Expenses!$F8/12*(1+Expenses!$F$17)^((K$1-1)/12) -> -2098.3713 | ... EE34: =-Expenses!$F8/12*(1+Expenses!$F$17)^((EE$1-1)/12) -> -2847.9585
A35: =SUMIF($C$1:$EE$1,"<="&Summary!$K$19,'Monthly CF'!C35:EE35) -> -703050.32 | B35: =Expenses!E9 -> Utilities | D35: =-Expenses!$F9/12*(1+Expenses!$F$17)^((D$1-1)/12) -> -5041.6667 | E35: =-Expenses!$F9/12*(1+Expenses!$F$17)^((E$1-1)/12) -> -5054.1008 | F35: =-Expenses!$F9/12*(1+Expenses!$F$17)^((F$1-1)/12) -> -5066.5656 | G35: =-Expenses!$F9/12*(1+Expenses!$F$17)^((G$1-1)/12) -> -5079.0611 | H35: =-Expenses!$F9/12*(1+Expenses!$F$17)^((H$1-1)/12) -> -5091.5874 | I35: =-Expenses!$F9/12*(1+Expenses!$F$17)^((I$1-1)/12) -> -5104.1446 | J35: =-Expenses!$F9/12*(1+Expenses!$F$17)^((J$1-1)/12) -> -5116.7328 | K35: =-Expenses!$F9/12*(1+Expenses!$F$17)^((K$1-1)/12) -> -5129.3521 | ... EE35: =-Expenses!$F9/12*(1+Expenses!$F$17)^((EE$1-1)/12) -> -6961.6764
A36: =SUMIF($C$1:$EE$1,"<="&Summary!$K$19,'Monthly CF'!C36:EE36) -> 607179.82 | B36: =Expenses!E10 -> Utility Bill-Back | D36: =-Expenses!$F10/12*(1+Expenses!$F$17)^((D$1-1)/12) -> 4354.1667 | E36: =-Expenses!$F10/12*(1+Expenses!$F$17)^((E$1-1)/12) -> 4364.9052 | F36: =-Expenses!$F10/12*(1+Expenses!$F$17)^((F$1-1)/12) -> 4375.6703 | G36: =-Expenses!$F10/12*(1+Expenses!$F$17)^((G$1-1)/12) -> 4386.4618 | H36: =-Expenses!$F10/12*(1+Expenses!$F$17)^((H$1-1)/12) -> 4397.28 | I36: =-Expenses!$F10/12*(1+Expenses!$F$17)^((I$1-1)/12) -> 4408.1249 | J36: =-Expenses!$F10/12*(1+Expenses!$F$17)^((J$1-1)/12) -> 4418.9965 | K36: =-Expenses!$F10/12*(1+Expenses!$F$17)^((K$1-1)/12) -> 4429.895 | ... EE36: =-Expenses!$F10/12*(1+Expenses!$F$17)^((EE$1-1)/12) -> 6012.3569
A37: =SUMIF($C$1:$EE$1,"<="&Summary!$K$19,'Monthly CF'!C37:EE37) -> -1411168.2 | B37: =Expenses!E11 -> Property Management Fee | D37: =D26*-Expenses!$F$19 -> -9258 | E37: =E26*-Expenses!$F$19 -> -9295.3291 | F37: =F26*-Expenses!$F$19 -> -9332.8094 | G37: =G26*-Expenses!$F$19 -> -9370.4414 | H37: =H26*-Expenses!$F$19 -> -9445.6291 | I37: =I26*-Expenses!$F$19 -> -9521.2746 | J37: =J26*-Expenses!$F$19 -> -9597.3803 | K37: =K26*-Expenses!$F$19 -> -9673.9488 | ... EE37: =EE26*-Expenses!$F$19 -> -14087.864
A38: =SUMIF($C$1:$EE$1,"<="&Summary!$K$19,'Monthly CF'!C38:EE38) -> -4812662.8 | B38: =Expenses!E12 -> Property Taxes | D38: =IF(AND(D1>Summary!$K$19,Expenses!$B$18="Yes"),('Monthly CF'!$A$64*Expenses!$B$19*Expenses!$B$17+HLOOKUP('Monthly CF'!D2,Expenses!$J$6:$T$10,4,0))/-12,HLOOKUP('Monthly CF'!D2,Expenses!$J$6:$T$10,5,0)/-12) -> -34375 | E38: =IF(AND(E1>Summary!$K$19,Expenses!$B$18="Yes"),('Monthly CF'!$A$64*Expenses!$B$19*Expenses!$B$17+HLOOKUP('Monthly CF'!E2,Expenses!$J$6:$T$10,4,0))/-12,HLOOKUP('Monthly CF'!E2,Expenses!$J$6:$T$10,5,0)/-12) -> -34375 | F38: =IF(AND(F1>Summary!$K$19,Expenses!$B$18="Yes"),('Monthly CF'!$A$64*Expenses!$B$19*Expenses!$B$17+HLOOKUP('Monthly CF'!F2,Expenses!$J$6:$T$10,4,0))/-12,HLOOKUP('Monthly CF'!F2,Expenses!$J$6:$T$10,5,0)/-12) -> -34375 | G38: =IF(AND(G1>Summary!$K$19,Expenses!$B$18="Yes"),('Monthly CF'!$A$64*Expenses!$B$19*Expenses!$B$17+HLOOKUP('Monthly CF'!G2,Expenses!$J$6:$T$10,4,0))/-12,HLOOKUP('Monthly CF'!G2,Expenses!$J$6:$T$10,5,0)/-12) -> -34375 | H38: =IF(AND(H1>Summary!$K$19,Expenses!$B$18="Yes"),('Monthly CF'!$A$64*Expenses!$B$19*Expenses!$B$17+HLOOKUP('Monthly CF'!H2,Expenses!$J$6:$T$10,4,0))/-12,HLOOKUP('Monthly CF'!H2,Expenses!$J$6:$T$10,5,0)/-12) -> -34375 | I38: =IF(AND(I1>Summary!$K$19,Expenses!$B$18="Yes"),('Monthly CF'!$A$64*Expenses!$B$19*Expenses!$B$17+HLOOKUP('Monthly CF'!I2,Expenses!$J$6:$T$10,4,0))/-12,HLOOKUP('Monthly CF'!I2,Expenses!$J$6:$T$10,5,0)/-12) -> -34375 | J38: =IF(AND(J1>Summary!$K$19,Expenses!$B$18="Yes"),('Monthly CF'!$A$64*Expenses!$B$19*Expenses!$B$17+HLOOKUP('Monthly CF'!J2,Expenses!$J$6:$T$10,4,0))/-12,HLOOKUP('Monthly CF'!J2,Expenses!$J$6:$T$10,5,0)/-12) -> -34375 | K38: =IF(AND(K1>Summary!$K$19,Expenses!$B$18="Yes"),('Monthly CF'!$A$64*Expenses!$B$19*Expenses!$B$17+HLOOKUP('Monthly CF'!K2,Expenses!$J$6:$T$10,4,0))/-12,HLOOKUP('Monthly CF'!K2,Expenses!$J$6:$T$10,5,0)/-12) -> -34375 | ... EE38: =IF(AND(EE1>Summary!$K$19,Expenses!$B$18="Yes"),('Monthly CF'!$A$64*Expenses!$B$19*Expenses!$B$17+HLOOKUP('Monthly CF'!EE2,Expenses!$J$6:$T$10,4,0))/-12,HLOOKUP('Monthly CF'!EE2,Expenses!$J$6:$T$10,5,0)/-12) -> -47094.157
A39: =SUMIF($C$1:$EE$1,"<="&Summary!$K$19,'Monthly CF'!C39:EE39) -> -567462.03 | B39: =Expenses!E13 -> Insurance | D39: =-Expenses!$F$13/12*(1+Expenses!$F$17)^('Monthly CF'!D2-1) -> -4125 | E39: =-Expenses!$F$13/12*(1+Expenses!$F$17)^('Monthly CF'!E2-1) -> -4125 | F39: =-Expenses!$F$13/12*(1+Expenses!$F$17)^('Monthly CF'!F2-1) -> -4125 | G39: =-Expenses!$F$13/12*(1+Expenses!$F$17)^('Monthly CF'!G2-1) -> -4125 | H39: =-Expenses!$F$13/12*(1+Expenses!$F$17)^('Monthly CF'!H2-1) -> -4125 | I39: =-Expenses!$F$13/12*(1+Expenses!$F$17)^('Monthly CF'!I2-1) -> -4125 | J39: =-Expenses!$F$13/12*(1+Expenses!$F$17)^('Monthly CF'!J2-1) -> -4125 | K39: =-Expenses!$F$13/12*(1+Expenses!$F$17)^('Monthly CF'!K2-1) -> -4125 | ... EE39: =-Expenses!$F$13/12*(1+Expenses!$F$17)^('Monthly CF'!EE2-1) -> -5543.6551
A40: =SUMIF($C$1:$EE$1,"<="&Summary!$K$19,'Monthly CF'!C40:EE40) -> -378308.02 | B40: Capital Expense Reserves | D40: =-Expenses!$F$18/12*Revenue!$A$23*(1+Expenses!$F$17)^('Monthly CF'!D2-1) -> -2750 | E40: =-Expenses!$F$18/12*Revenue!$A$23*(1+Expenses!$F$17)^('Monthly CF'!E2-1) -> -2750 | F40: =-Expenses!$F$18/12*Revenue!$A$23*(1+Expenses!$F$17)^('Monthly CF'!F2-1) -> -2750 | G40: =-Expenses!$F$18/12*Revenue!$A$23*(1+Expenses!$F$17)^('Monthly CF'!G2-1) -> -2750 | H40: =-Expenses!$F$18/12*Revenue!$A$23*(1+Expenses!$F$17)^('Monthly CF'!H2-1) -> -2750 | I40: =-Expenses!$F$18/12*Revenue!$A$23*(1+Expenses!$F$17)^('Monthly CF'!I2-1) -> -2750 | J40: =-Expenses!$F$18/12*Revenue!$A$23*(1+Expenses!$F$17)^('Monthly CF'!J2-1) -> -2750 | K40: =-Expenses!$F$18/12*Revenue!$A$23*(1+Expenses!$F$17)^('Monthly CF'!K2-1) -> -2750 | ... EE40: =-Expenses!$F$18/12*Revenue!$A$23*(1+Expenses!$F$17)^('Monthly CF'!EE2-1) -> -3695.77
A41: =SUMIF($C$1:$EE$1,"<="&Summary!$K$19,'Monthly CF'!C41:EE41) -> -11675514 | B41: Total Operating Expenses | D41: =SUM(D29:D40) -> -82820.5 | E41: =SUM(E29:E40) -> -82937.52 | F41: =SUM(F29:F40) -> -83054.889 | G41: =SUM(G29:G40) -> -83172.606 | H41: =SUM(H29:H40) -> -83328.076 | I41: =SUM(I29:I40) -> -83484.202 | J41: =SUM(J29:J40) -> -83640.986 | K41: =SUM(K29:K40) -> -83798.433 | ... EE41: =SUM(EE29:EE40) -> -115039.46
A43: =SUMIF($C$1:$EE$1,"<="&Summary!$K$19,'Monthly CF'!C43:EE43) -> 23603689 | B43: Net Operating Income | D43: =SUM(D26,D41) -> 148629.5 | E43: =SUM(E26,E41) -> 149445.71 | F43: =SUM(F26,F41) -> 150265.35 | G43: =SUM(G26,G41) -> 151088.43 | H43: =SUM(H26,H41) -> 152812.65 | I43: =SUM(I26,I41) -> 154547.66 | J43: =SUM(J26,J41) -> 156293.52 | K43: =SUM(K26,K41) -> 158050.29 | ... EE43: =SUM(EE26,EE41) -> 237157.14
A45: =SUMIF($C$1:$EE$1,"<="&Summary!$K$19,'Monthly CF'!C45:EE45) -> -1963500 | B45: Construction Expenses | D45: =-'Construction Budget'!H49 -> 0 | E45: =-'Construction Budget'!I49 -> -165229.17 | F45: =-'Construction Budget'!J49 -> -220229.17 | G45: =-'Construction Budget'!K49 -> -220229.17 | H45: =-'Construction Budget'!L49 -> -220229.17 | I45: =-'Construction Budget'!M49 -> -192729.17 | J45: =-'Construction Budget'!N49 -> -192729.17 | K45: =-'Construction Budget'!O49 -> -137729.17 | ... EE45: =-'Construction Budget'!EI49 -> 0
A47: =SUMIF($C$1:$EE$1,"<="&Summary!$K$19,'Monthly CF'!C47:EE47) -> 21640189 | B47: Cash Flow Before Debt Service | D47: =IF(D1>Summary!$K$19,0,SUM(D43,D45)) -> 148629.5 | E47: =IF(E1>Summary!$K$19,0,SUM(E43,E45)) -> -15783.459 | F47: =IF(F1>Summary!$K$19,0,SUM(F43,F45)) -> -69963.82 | G47: =IF(G1>Summary!$K$19,0,SUM(G43,G45)) -> -69140.737 | H47: =IF(H1>Summary!$K$19,0,SUM(H43,H45)) -> -67416.514 | I47: =IF(I1>Summary!$K$19,0,SUM(I43,I45)) -> -38181.503 | J47: =IF(J1>Summary!$K$19,0,SUM(J43,J45)) -> -36435.645 | K47: =IF(K1>Summary!$K$19,0,SUM(K43,K45)) -> 20321.12 | ... EE47: =IF(EE1>Summary!$K$19,0,SUM(EE43,EE45)) -> 0
B49: Loan Information
A50: =SUMIF($C$1:$EE$1,"<="&Summary!$K$19,'Monthly CF'!C50:EE50) -> 56000000 | B50: Loan Funding | C50: =Summary!E2 -> 26000000 | D50: =IF(D1>=Summary!$K$19,0,IF('Monthly CF'!D1=Summary!$E$13,Summary!$E$14,0)) -> 0 | E50: =IF(E1>=Summary!$K$19,0,IF('Monthly CF'!E1=Summary!$E$13,Summary!$E$14,0)) -> 0 | F50: =IF(F1>=Summary!$K$19,0,IF('Monthly CF'!F1=Summary!$E$13,Summary!$E$14,0)) -> 0 | G50: =IF(G1>=Summary!$K$19,0,IF('Monthly CF'!G1=Summary!$E$13,Summary!$E$14,0)) -> 0 | H50: =IF(H1>=Summary!$K$19,0,IF('Monthly CF'!H1=Summary!$E$13,Summary!$E$14,0)) -> 0 | I50: =IF(I1>=Summary!$K$19,0,IF('Monthly CF'!I1=Summary!$E$13,Summary!$E$14,0)) -> 0 | J50: =IF(J1>=Summary!$K$19,0,IF('Monthly CF'!J1=Summary!$E$13,Summary!$E$14,0)) -> 0 | K50: =IF(K1>=Summary!$K$19,0,IF('Monthly CF'!K1=Summary!$E$13,Summary!$E$14,0)) -> 0 | ... EE50: =IF(EE1>=Summary!$K$19,0,IF('Monthly CF'!EE1=Summary!$E$13,Summary!$E$14,0)) -> 0
A51: =SUMIF($C$1:$EE$1,"<="&Summary!$K$19,'Monthly CF'!C51:EE51) -> -13136462 | B51: Total Payment | D51: =-SUM(Financing!C5,Financing!C15) -> -86666.667 | E51: =-SUM(Financing!D5,Financing!D15) -> -86666.667 | F51: =-SUM(Financing!E5,Financing!E15) -> -86666.667 | G51: =-SUM(Financing!F5,Financing!F15) -> -86666.667 | H51: =-SUM(Financing!G5,Financing!G15) -> -86666.667 | I51: =-SUM(Financing!H5,Financing!H15) -> -86666.667 | J51: =-SUM(Financing!I5,Financing!I15) -> -86666.667 | K51: =-SUM(Financing!J5,Financing!J15) -> -86666.667 | ... EE51: =-SUM(Financing!ED5,Financing!ED15) -> 0
A52: =SUMIF($C$1:$EE$1,"<="&Summary!$K$19,'Monthly CF'!C52:EE52) -> -53987461 | B52: Loan Payoff | D52: =SUM(Financing!C8,Financing!C18) -> 0 | E52: =SUM(Financing!D8,Financing!D18) -> 0 | F52: =SUM(Financing!E8,Financing!E18) -> 0 | G52: =SUM(Financing!F8,Financing!F18) -> 0 | H52: =SUM(Financing!G8,Financing!G18) -> 0 | I52: =SUM(Financing!H8,Financing!H18) -> 0 | J52: =SUM(Financing!I8,Financing!I18) -> 0 | K52: =SUM(Financing!J8,Financing!J18) -> 0 | ... EE52: =SUM(Financing!ED8,Financing!ED18) -> 0
A53: =SUMIF($C$1:$EE$1,"<="&Summary!$K$19,'Monthly CF'!C53:EE53) -> -560000 | B53: Loan Fees | C53: =C50*-Summary!E8 -> -260000 | D53: =D50*-Summary!$E$21 -> 0 | E53: =E50*-Summary!$E$21 -> 0 | F53: =F50*-Summary!$E$21 -> 0 | G53: =G50*-Summary!$E$21 -> 0 | H53: =H50*-Summary!$E$21 -> 0 | I53: =I50*-Summary!$E$21 -> 0 | J53: =J50*-Summary!$E$21 -> 0 | K53: =K50*-Summary!$E$21 -> 0 | ... EE53: =EE50*-Summary!$E$21 -> 0
A55: =SUMIF($C$1:$EE$1,"<="&Summary!$K$19,'Monthly CF'!C55:EE55) -> 8503727.8 | B55: Cash Flow After Debt Service | D55: =SUM(D47,D51) -> 61962.833 | E55: =SUM(E47,E51) -> -102450.13 | F55: =SUM(F47,F51) -> -156630.49 | G55: =SUM(G47,G51) -> -155807.4 | H55: =SUM(H47,H51) -> -154083.18 | I55: =SUM(I47,I51) -> -124848.17 | J55: =SUM(J47,J51) -> -123102.31 | K55: =SUM(K47,K51) -> -66345.547 | ... EE55: =SUM(EE47,EE51) -> 0
B57: Working Capital Funding
A58: =SUMIF($C$1:$EE$1,"<="&Summary!$K$19,'Monthly CF'!C58:EE58) -> -300000 | B58: Working Capital Contributed | C58: =-Summary!B23 -> -300000 | EE58: 0
A59: =SUMIF($C$1:$EE$1,"<="&Summary!$K$19,'Monthly CF'!C59:EE59) -> 300000 | B59: Working Capital Distributed | D59: =IF(D1=Summary!$K$19,'Monthly CF'!D69,IF('Monthly CF'!D55<0,MIN(-'Monthly CF'!D55,'Monthly CF'!D69),0)) -> 0 | E59: =IF(E1=Summary!$K$19,'Monthly CF'!E69,IF('Monthly CF'!E55<0,MIN(-'Monthly CF'!E55,'Monthly CF'!E69),0)) -> 102450.13 | F59: =IF(F1=Summary!$K$19,'Monthly CF'!F69,IF('Monthly CF'!F55<0,MIN(-'Monthly CF'!F55,'Monthly CF'!F69),0)) -> 156630.49 | G59: =IF(G1=Summary!$K$19,'Monthly CF'!G69,IF('Monthly CF'!G55<0,MIN(-'Monthly CF'!G55,'Monthly CF'!G69),0)) -> 40919.388 | H59: =IF(H1=Summary!$K$19,'Monthly CF'!H69,IF('Monthly CF'!H55<0,MIN(-'Monthly CF'!H55,'Monthly CF'!H69),0)) -> 0 | I59: =IF(I1=Summary!$K$19,'Monthly CF'!I69,IF('Monthly CF'!I55<0,MIN(-'Monthly CF'!I55,'Monthly CF'!I69),0)) -> 0 | J59: =IF(J1=Summary!$K$19,'Monthly CF'!J69,IF('Monthly CF'!J55<0,MIN(-'Monthly CF'!J55,'Monthly CF'!J69),0)) -> 0 | K59: =IF(K1=Summary!$K$19,'Monthly CF'!K69,IF('Monthly CF'!K55<0,MIN(-'Monthly CF'!K55,'Monthly CF'!K69),0)) -> 0 | ... EE59: =IF(EE1=Summary!$K$19,'Monthly CF'!EE69,IF('Monthly CF'!EE55<0,MIN(-'Monthly CF'!EE55,'Monthly CF'!EE69),0)) -> 0
B61: Acquisition & Sale Information
A62: =SUMIF($C$1:$EE$1,"<="&Summary!$K$19,'Monthly CF'!C62:EE62) -> -40000000 | B62: Purchase Price | C62: =-Summary!B20 -> -40000000 | EE62: 0
A63: =SUMIF($C$1:$EE$1,"<="&Summary!$K$19,'Monthly CF'!C63:EE63) -> -150000 | B63: Closing Costs | C63: =-Summary!B22 -> -150000 | EE63: 0
A64: =SUMIF($C$1:$EE$1,"<="&Summary!$K$19,'Monthly CF'!C64:EE64) -> 46643653 | B64: Sale Price | D64: =IF(D1=Summary!$K$19,SUM('Monthly CF'!E43:P43)/Summary!$K$18,0) -> 0 | E64: =IF(E1=Summary!$K$19,SUM('Monthly CF'!F43:Q43)/Summary!$K$18,0) -> 0 | F64: =IF(F1=Summary!$K$19,SUM('Monthly CF'!G43:R43)/Summary!$K$18,0) -> 0 | G64: =IF(G1=Summary!$K$19,SUM('Monthly CF'!H43:S43)/Summary!$K$18,0) -> 0 | H64: =IF(H1=Summary!$K$19,SUM('Monthly CF'!I43:T43)/Summary!$K$18,0) -> 0 | I64: =IF(I1=Summary!$K$19,SUM('Monthly CF'!J43:U43)/Summary!$K$18,0) -> 0 | J64: =IF(J1=Summary!$K$19,SUM('Monthly CF'!K43:V43)/Summary!$K$18,0) -> 0 | K64: =IF(K1=Summary!$K$19,SUM('Monthly CF'!L43:W43)/Summary!$K$18,0) -> 0 | ... EE64: =IF(EE1=Summary!$K$19,SUM('Monthly CF'!EF43:EQ43)/Summary!$K$18,0) -> 0
A65: =SUMIF($C$1:$EE$1,"<="&Summary!$K$19,'Monthly CF'!C65:EE65) -> -1399309.6 | B65: Costs of Sale | D65: =D64*-Summary!$K$17 -> 0 | E65: =E64*-Summary!$K$17 -> 0 | F65: =F64*-Summary!$K$17 -> 0 | G65: =G64*-Summary!$K$17 -> 0 | H65: =H64*-Summary!$K$17 -> 0 | I65: =I64*-Summary!$K$17 -> 0 | J65: =J64*-Summary!$K$17 -> 0 | K65: =K64*-Summary!$K$17 -> 0 | ... EE65: =EE64*-Summary!$K$17 -> 0
A67: =SUMIF($C$1:$EE$1,"<="&Summary!$K$19,'Monthly CF'!C67:EE67) -> 15050611 | B67: Net Levered Cash Flow | C67: =SUM(C47,C50:C53,C58:C59,C62:C65) -> -14710000 | D67: =SUM(D47,D50:D53,D58:D59,D62:D65) -> 61962.833 | E67: =SUM(E47,E50:E53,E58:E59,E62:E65) -> 0 | F67: =SUM(F47,F50:F53,F58:F59,F62:F65) -> 0 | G67: =SUM(G47,G50:G53,G58:G59,G62:G65) -> -114888.02 | H67: =SUM(H47,H50:H53,H58:H59,H62:H65) -> -154083.18 | I67: =SUM(I47,I50:I53,I58:I59,I62:I65) -> -124848.17 | J67: =SUM(J47,J50:J53,J58:J59,J62:J65) -> -123102.31 | ... EE67: =SUM(EE47,EE50:EE53,EE58:EE59,EE62:EE65) -> 0
B69: Beginning Working Capital Balance | C69: 0 | D69: =C70 -> 300000 | E69: =D70 -> 300000 | F69: =E70 -> 197549.87 | G69: =F70 -> 40919.388 | H69: =G70 -> 0 | I69: =H70 -> 0 | J69: =I70 -> 0 | K69: =J70 -> 0 | ... EE69: =ED70 -> 0
B70: Ending Working Capital Balance | C70: =-C58 -> 300000 | D70: =D69-D59 -> 300000 | E70: =E69-E59 -> 197549.87 | F70: =F69-F59 -> 40919.388 | G70: =G69-G59 -> 0 | H70: =H69-H59 -> 0 | I70: =I69-I59 -> 0 | J70: =J69-J59 -> 0 | K70: =K69-K59 -> 0 | ... EE70: =EE69-EE59 -> 0

Sheet Annual CF
B1: Year | C1: 0 | D1: =C1+1 -> 1 | E1: =D1+1 -> 2 | F1: =E1+1 -> 3 | G1: =F1+1 -> 4 | H1: =G1+1 -> 5 | I1: =H1+1 -> 6 | J1: =I1+1 -> 7 | K1: =J1+1 -> 8 | ... M1: =L1+1 -> 10
B2: Year Ending | C2: =Summary!B25 -> 44227 | D2: =EOMONTH(C2,12) -> 44592 | E2: =EOMONTH(D2,12) -> 44957 | F2: =EOMONTH(E2,12) -> 45322 | G2: =EOMONTH(F2,12) -> 45688 | H2: =EOMONTH(G2,12) -> 46053 | I2: =EOMONTH(H2,12) -> 46418 | J2: =EOMONTH(I2,12) -> 46783 | K2: =EOMONTH(J2,12) -> 47149 | ... M2: =EOMONTH(L2,12) -> 47879
B4: Revenue
A5: =SUM(C5:M5) -> 36563661 | B5: Gross Potential Rental Revenue | D5: =SUMIFS('Monthly CF'!6:6,'Monthly CF'!$2:$2,'Annual CF'!D$1,'Monthly CF'!$1:$1,"<="&Summary!$K$19) -> 3044073.9 | E5: =SUMIFS('Monthly CF'!6:6,'Monthly CF'!$2:$2,'Annual CF'!E$1,'Monthly CF'!$1:$1,"<="&Summary!$K$19) -> 3281163.8 | F5: =SUMIFS('Monthly CF'!6:6,'Monthly CF'!$2:$2,'Annual CF'!F$1,'Monthly CF'!$1:$1,"<="&Summary!$K$19) -> 3400503.9 | G5: =SUMIFS('Monthly CF'!6:6,'Monthly CF'!$2:$2,'Annual CF'!G$1,'Monthly CF'!$1:$1,"<="&Summary!$K$19) -> 3502519 | H5: =SUMIFS('Monthly CF'!6:6,'Monthly CF'!$2:$2,'Annual CF'!H$1,'Monthly CF'!$1:$1,"<="&Summary!$K$19) -> 3607594.6 | I5: =SUMIFS('Monthly CF'!6:6,'Monthly CF'!$2:$2,'Annual CF'!I$1,'Monthly CF'!$1:$1,"<="&Summary!$K$19) -> 3715822.4 | J5: =SUMIFS('Monthly CF'!6:6,'Monthly CF'!$2:$2,'Annual CF'!J$1,'Monthly CF'!$1:$1,"<="&Summary!$K$19) -> 3827297.1 | K5: =SUMIFS('Monthly CF'!6:6,'Monthly CF'!$2:$2,'Annual CF'!K$1,'Monthly CF'!$1:$1,"<="&Summary!$K$19) -> 3942116 | ... M5: =SUMIFS('Monthly CF'!6:6,'Monthly CF'!$2:$2,'Annual CF'!M$1,'Monthly CF'!$1:$1,"<="&Summary!$K$19) -> 4182190.9
A6: =SUM(C6:M6) -> -1875029.6 | B6: Physical Vacancy | D6: =SUMIFS('Monthly CF'!7:7,'Monthly CF'!$2:$2,'Annual CF'!D$1,'Monthly CF'!$1:$1,"<="&Summary!$K$19) -> -182644.43 | E6: =SUMIFS('Monthly CF'!7:7,'Monthly CF'!$2:$2,'Annual CF'!E$1,'Monthly CF'!$1:$1,"<="&Summary!$K$19) -> -180464.01 | F6: =SUMIFS('Monthly CF'!7:7,'Monthly CF'!$2:$2,'Annual CF'!F$1,'Monthly CF'!$1:$1,"<="&Summary!$K$19) -> -170025.2 | G6: =SUMIFS('Monthly CF'!7:7,'Monthly CF'!$2:$2,'Annual CF'!G$1,'Monthly CF'!$1:$1,"<="&Summary!$K$19) -> -175125.95 | H6: =SUMIFS('Monthly CF'!7:7,'Monthly CF'!$2:$2,'Annual CF'!H$1,'Monthly CF'!$1:$1,"<="&Summary!$K$19) -> -180379.73 | I6: =SUMIFS('Monthly CF'!7:7,'Monthly CF'!$2:$2,'Annual CF'!I$1,'Monthly CF'!$1:$1,"<="&Summary!$K$19) -> -185791.12 | J6: =SUMIFS('Monthly CF'!7:7,'Monthly CF'!$2:$2,'Annual CF'!J$1,'Monthly CF'!$1:$1,"<="&Summary!$K$19) -> -191364.86 | K6: =SUMIFS('Monthly CF'!7:7,'Monthly CF'!$2:$2,'Annual CF'!K$1,'Monthly CF'!$1:$1,"<="&Summary!$K$19) -> -197105.8 | ... M6: =SUMIFS('Monthly CF'!7:7,'Monthly CF'!$2:$2,'Annual CF'!M$1,'Monthly CF'!$1:$1,"<="&Summary!$K$19) -> -209109.54
A7: =SUM(C7:M7) -> -206241.58 | B7: Bad Debt | D7: =SUMIFS('Monthly CF'!8:8,'Monthly CF'!$2:$2,'Annual CF'!D$1,'Monthly CF'!$1:$1,"<="&Summary!$K$19) -> -30440.739 | E7: =SUMIFS('Monthly CF'!8:8,'Monthly CF'!$2:$2,'Annual CF'!E$1,'Monthly CF'!$1:$1,"<="&Summary!$K$19) -> -24608.729 | F7: =SUMIFS('Monthly CF'!8:8,'Monthly CF'!$2:$2,'Annual CF'!F$1,'Monthly CF'!$1:$1,"<="&Summary!$K$19) -> -17002.52 | G7: =SUMIFS('Monthly CF'!8:8,'Monthly CF'!$2:$2,'Annual CF'!G$1,'Monthly CF'!$1:$1,"<="&Summary!$K$19) -> -17512.595 | H7: =SUMIFS('Monthly CF'!8:8,'Monthly CF'!$2:$2,'Annual CF'!H$1,'Monthly CF'!$1:$1,"<="&Summary!$K$19) -> -18037.973 | I7: =SUMIFS('Monthly CF'!8:8,'Monthly CF'!$2:$2,'Annual CF'!I$1,'Monthly CF'!$1:$1,"<="&Summary!$K$19) -> -18579.112 | J7: =SUMIFS('Monthly CF'!8:8,'Monthly CF'!$2:$2,'Annual CF'!J$1,'Monthly CF'!$1:$1,"<="&Summary!$K$19) -> -19136.486 | K7: =SUMIFS('Monthly CF'!8:8,'Monthly CF'!$2:$2,'Annual CF'!K$1,'Monthly CF'!$1:$1,"<="&Summary!$K$19) -> -19710.58 | ... M7: =SUMIFS('Monthly CF'!8:8,'Monthly CF'!$2:$2,'Annual CF'!M$1,'Monthly CF'!$1:$1,"<="&Summary!$K$19) -> -20910.954
A8: =SUM(C8:M8) -> -46846.558 | B8: Concessions | D8: =SUMIFS('Monthly CF'!9:9,'Monthly CF'!$2:$2,'Annual CF'!D$1,'Monthly CF'!$1:$1,"<="&Summary!$K$19) -> -30440.739 | E8: =SUMIFS('Monthly CF'!9:9,'Monthly CF'!$2:$2,'Annual CF'!E$1,'Monthly CF'!$1:$1,"<="&Summary!$K$19) -> -16405.819 | F8: =SUMIFS('Monthly CF'!9:9,'Monthly CF'!$2:$2,'Annual CF'!F$1,'Monthly CF'!$1:$1,"<="&Summary!$K$19) -> 0 | G8: =SUMIFS('Monthly CF'!9:9,'Monthly CF'!$2:$2,'Annual CF'!G$1,'Monthly CF'!$1:$1,"<="&Summary!$K$19) -> 0 | H8: =SUMIFS('Monthly CF'!9:9,'Monthly CF'!$2:$2,'Annual CF'!H$1,'Monthly CF'!$1:$1,"<="&Summary!$K$19) -> 0 | I8: =SUMIFS('Monthly CF'!9:9,'Monthly CF'!$2:$2,'Annual CF'!I$1,'Monthly CF'!$1:$1,"<="&Summary!$K$19) -> 0 | J8: =SUMIFS('Monthly CF'!9:9,'Monthly CF'!$2:$2,'Annual CF'!J$1,'Monthly CF'!$1:$1,"<="&Summary!$K$19) -> 0 | K8: =SUMIFS('Monthly CF'!9:9,'Monthly CF'!$2:$2,'Annual CF'!K$1,'Monthly CF'!$1:$1,"<="&Summary!$K$19) -> 0 | ... M8: =SUMIFS('Monthly CF'!9:9,'Monthly CF'!$2:$2,'Annual CF'!M$1,'Monthly CF'!$1:$1,"<="&Summary!$K$19) -> 0
A9: =SUM(C9:M9) -> 0 | B9: Other Loss | D9: =SUMIFS('Monthly CF'!10:10,'Monthly CF'!$2:$2,'Annual CF'!D$1,'Monthly CF'!$1:$1,"<="&Summary!$K$19) -> 0 | E9: =SUMIFS('Monthly CF'!10:10,'Monthly CF'!$2:$2,'Annual CF'!E$1,'Monthly CF'!$1:$1,"<="&Summary!$K$19) -> 0 | F9: =SUMIFS('Monthly CF'!10:10,'Monthly CF'!$2:$2,'Annual CF'!F$1,'Monthly CF'!$1:$1,"<="&Summary!$K$19) -> 0 | G9: =SUMIFS('Monthly CF'!10:10,'Monthly CF'!$2:$2,'Annual CF'!G$1,'Monthly CF'!$1:$1,"<="&Summary!$K$19) -> 0 | H9: =SUMIFS('Monthly CF'!10:10,'Monthly CF'!$2:$2,'Annual CF'!H$1,'Monthly CF'!$1:$1,"<="&Summary!$K$19) -> 0 | I9: =SUMIFS('Monthly CF'!10:10,'Monthly CF'!$2:$2,'Annual CF'!I$1,'Monthly CF'!$1:$1,"<="&Summary!$K$19) -> 0 | J9: =SUMIFS('Monthly CF'!10:10,'Monthly CF'!$2:$2,'Annual CF'!J$1,'Monthly CF'!$1:$1,"<="&Summary!$K$19) -> 0 | K9: =SUMIFS('Monthly CF'!10:10,'Monthly CF'!$2:$2,'Annual CF'!K$1,'Monthly CF'!$1:$1,"<="&Summary!$K$19) -> 0 | ... M9: =SUMIFS('Monthly CF'!10:10,'Monthly CF'!$2:$2,'Annual CF'!M$1,'Monthly CF'!$1:$1,"<="&Summary!$K$19) -> 0
A10: =SUM(C10:M10) -> 34435543 | B10: Net Rental Income | D10: =SUMIFS('Monthly CF'!11:11,'Monthly CF'!$2:$2,'Annual CF'!D$1,'Monthly CF'!$1:$1,"<="&Summary!$K$19) -> 2800547.9 | E10: =SUMIFS('Monthly CF'!11:11,'Monthly CF'!$2:$2,'Annual CF'!E$1,'Monthly CF'!$1:$1,"<="&Summary!$K$19) -> 3059685.2 | F10: =SUMIFS('Monthly CF'!11:11,'Monthly CF'!$2:$2,'Annual CF'!F$1,'Monthly CF'!$1:$1,"<="&Summary!$K$19) -> 3213476.2 | G10: =SUMIFS('Monthly CF'!11:11,'Monthly CF'!$2:$2,'Annual CF'!G$1,'Monthly CF'!$1:$1,"<="&Summary!$K$19) -> 3309880.5 | H10: =SUMIFS('Monthly CF'!11:11,'Monthly CF'!$2:$2,'Annual CF'!H$1,'Monthly CF'!$1:$1,"<="&Summary!$K$19) -> 3409176.9 | I10: =SUMIFS('Monthly CF'!11:11,'Monthly CF'!$2:$2,'Annual CF'!I$1,'Monthly CF'!$1:$1,"<="&Summary!$K$19) -> 3511452.2 | J10: =SUMIFS('Monthly CF'!11:11,'Monthly CF'!$2:$2,'Annual CF'!J$1,'Monthly CF'!$1:$1,"<="&Summary!$K$19) -> 3616795.8 | K10: =SUMIFS('Monthly CF'!11:11,'Monthly CF'!$2:$2,'Annual CF'!K$1,'Monthly CF'!$1:$1,"<="&Summary!$K$19) -> 3725299.6 | ... M10: =SUMIFS('Monthly CF'!11:11,'Monthly CF'!$2:$2,'Annual CF'!M$1,'Monthly CF'!$1:$1,"<="&Summary!$K$19) -> 3952170.4
B12: Other Income
A13: =SUM(C13:M13) -> 153392.8 | B13: =Revenue!O2 -> Laundry Income | D13: =SUMIFS('Monthly CF'!14:14,'Monthly CF'!$2:$2,'Annual CF'!D$1,'Monthly CF'!$1:$1,"<="&Summary!$K$19) -> 13380.531 | E13: =SUMIFS('Monthly CF'!14:14,'Monthly CF'!$2:$2,'Annual CF'!E$1,'Monthly CF'!$1:$1,"<="&Summary!$K$19) -> 13781.947 | F13: =SUMIFS('Monthly CF'!14:14,'Monthly CF'!$2:$2,'Annual CF'!F$1,'Monthly CF'!$1:$1,"<="&Summary!$K$19) -> 14195.406 | G13: =SUMIFS('Monthly CF'!14:14,'Monthly CF'!$2:$2,'Annual CF'!G$1,'Monthly CF'!$1:$1,"<="&Summary!$K$19) -> 14621.268 | H13: =SUMIFS('Monthly CF'!14:14,'Monthly CF'!$2:$2,'Annual CF'!H$1,'Monthly CF'!$1:$1,"<="&Summary!$K$19) -> 15059.906 | I13: =SUMIFS('Monthly CF'!14:14,'Monthly CF'!$2:$2,'Annual CF'!I$1,'Monthly CF'!$1:$1,"<="&Summary!$K$19) -> 15511.703 | J13: =SUMIFS('Monthly CF'!14:14,'Monthly CF'!$2:$2,'Annual CF'!J$1,'Monthly CF'!$1:$1,"<="&Summary!$K$19) -> 15977.054 | K13: =SUMIFS('Monthly CF'!14:14,'Monthly CF'!$2:$2,'Annual CF'!K$1,'Monthly CF'!$1:$1,"<="&Summary!$K$19) -> 16456.366 | ... M13: =SUMIFS('Monthly CF'!14:14,'Monthly CF'!$2:$2,'Annual CF'!M$1,'Monthly CF'!$1:$1,"<="&Summary!$K$19) -> 17458.558
A14: =SUM(C14:M14) -> 153392.8 | B14: =Revenue!O3 -> Late Fees | D14: =SUMIFS('Monthly CF'!15:15,'Monthly CF'!$2:$2,'Annual CF'!D$1,'Monthly CF'!$1:$1,"<="&Summary!$K$19) -> 13380.531 | E14: =SUMIFS('Monthly CF'!15:15,'Monthly CF'!$2:$2,'Annual CF'!E$1,'Monthly CF'!$1:$1,"<="&Summary!$K$19) -> 13781.947 | F14: =SUMIFS('Monthly CF'!15:15,'Monthly CF'!$2:$2,'Annual CF'!F$1,'Monthly CF'!$1:$1,"<="&Summary!$K$19) -> 14195.406 | G14: =SUMIFS('Monthly CF'!15:15,'Monthly CF'!$2:$2,'Annual CF'!G$1,'Monthly CF'!$1:$1,"<="&Summary!$K$19) -> 14621.268 | H14: =SUMIFS('Monthly CF'!15:15,'Monthly CF'!$2:$2,'Annual CF'!H$1,'Monthly CF'!$1:$1,"<="&Summary!$K$19) -> 15059.906 | I14: =SUMIFS('Monthly CF'!15:15,'Monthly CF'!$2:$2,'Annual CF'!I$1,'Monthly CF'!$1:$1,"<="&Summary!$K$19) -> 15511.703 | J14: =SUMIFS('Monthly CF'!15:15,'Monthly CF'!$2:$2,'Annual CF'!J$1,'Monthly CF'!$1:$1,"<="&Summary!$K$19) -> 15977.054 | K14: =SUMIFS('Monthly CF'!15:15,'Monthly CF'!$2:$2,'Annual CF'!K$1,'Monthly CF'!$1:$1,"<="&Summary!$K$19) -> 16456.366 | ... M14: =SUMIFS('Monthly CF'!15:15,'Monthly CF'!$2:$2,'Annual CF'!M$1,'Monthly CF'!$1:$1,"<="&Summary!$K$19) -> 17458.558
A15: =SUM(C15:M15) -> 383481.99 | B15: =Revenue!O4 -> Pet Rent | D15: =SUMIFS('Monthly CF'!16:16,'Monthly CF'!$2:$2,'Annual CF'!D$1,'Monthly CF'!$1:$1,"<="&Summary!$K$19) -> 33451.328 | E15: =SUMIFS('Monthly CF'!16:16,'Monthly CF'!$2:$2,'Annual CF'!E$1,'Monthly CF'!$1:$1,"<="&Summary!$K$19) -> 34454.868 | F15: =SUMIFS('Monthly CF'!16:16,'Monthly CF'!$2:$2,'Annual CF'!F$1,'Monthly CF'!$1:$1,"<="&Summary!$K$19) -> 35488.514 | G15: =SUMIFS('Monthly CF'!16:16,'Monthly CF'!$2:$2,'Annual CF'!G$1,'Monthly CF'!$1:$1,"<="&Summary!$K$19) -> 36553.17 | H15: =SUMIFS('Monthly CF'!16:16,'Monthly CF'!$2:$2,'Annual CF'!H$1,'Monthly CF'!$1:$1,"<="&Summary!$K$19) -> 37649.765 | I15: =SUMIFS('Monthly CF'!16:16,'Monthly CF'!$2:$2,'Annual CF'!I$1,'Monthly CF'!$1:$1,"<="&Summary!$K$19) -> 38779.258 | J15: =SUMIFS('Monthly CF'!16:16,'Monthly CF'!$2:$2,'Annual CF'!J$1,'Monthly CF'!$1:$1,"<="&Summary!$K$19) -> 39942.635 | K15: =SUMIFS('Monthly CF'!16:16,'Monthly CF'!$2:$2,'Annual CF'!K$1,'Monthly CF'!$1:$1,"<="&Summary!$K$19) -> 41140.915 | ... M15: =SUMIFS('Monthly CF'!16:16,'Monthly CF'!$2:$2,'Annual CF'!M$1,'Monthly CF'!$1:$1,"<="&Summary!$K$19) -> 43646.396
A16: =SUM(C16:M16) -> 76696.398 | B16: =Revenue!O5 -> Pet Fees | D16: =SUMIFS('Monthly CF'!17:17,'Monthly CF'!$2:$2,'Annual CF'!D$1,'Monthly CF'!$1:$1,"<="&Summary!$K$19) -> 6690.2657 | E16: =SUMIFS('Monthly CF'!17:17,'Monthly CF'!$2:$2,'Annual CF'!E$1,'Monthly CF'!$1:$1,"<="&Summary!$K$19) -> 6890.9736 | F16: =SUMIFS('Monthly CF'!17:17,'Monthly CF'!$2:$2,'Annual CF'!F$1,'Monthly CF'!$1:$1,"<="&Summary!$K$19) -> 7097.7029 | G16: =SUMIFS('Monthly CF'!17:17,'Monthly CF'!$2:$2,'Annual CF'!G$1,'Monthly CF'!$1:$1,"<="&Summary!$K$19) -> 7310.6339 | H16: =SUMIFS('Monthly CF'!17:17,'Monthly CF'!$2:$2,'Annual CF'!H$1,'Monthly CF'!$1:$1,"<="&Summary!$K$19) -> 7529.953 | I16: =SUMIFS('Monthly CF'!17:17,'Monthly CF'!$2:$2,'Annual CF'!I$1,'Monthly CF'!$1:$1,"<="&Summary!$K$19) -> 7755.8515 | J16: =SUMIFS('Monthly CF'!17:17,'Monthly CF'!$2:$2,'Annual CF'!J$1,'Monthly CF'!$1:$1,"<="&Summary!$K$19) -> 7988.5271 | K16: =SUMIFS('Monthly CF'!17:17,'Monthly CF'!$2:$2,'Annual CF'!K$1,'Monthly CF'!$1:$1,"<="&Summary!$K$19) -> 8228.1829 | ... M16: =SUMIFS('Monthly CF'!17:17,'Monthly CF'!$2:$2,'Annual CF'!M$1,'Monthly CF'!$1:$1,"<="&Summary!$K$19) -> 8729.2792
A17: =SUM(C17:M17) -> 0 | B17: =Revenue!O6 -> Garage Income | D17: =SUMIFS('Monthly CF'!18:18,'Monthly CF'!$2:$2,'Annual CF'!D$1,'Monthly CF'!$1:$1,"<="&Summary!$K$19) -> 0 | E17: =SUMIFS('Monthly CF'!18:18,'Monthly CF'!$2:$2,'Annual CF'!E$1,'Monthly CF'!$1:$1,"<="&Summary!$K$19) -> 0 | F17: =SUMIFS('Monthly CF'!18:18,'Monthly CF'!$2:$2,'Annual CF'!F$1,'Monthly CF'!$1:$1,"<="&Summary!$K$19) -> 0 | G17: =SUMIFS('Monthly CF'!18:18,'Monthly CF'!$2:$2,'Annual CF'!G$1,'Monthly CF'!$1:$1,"<="&Summary!$K$19) -> 0 | H17: =SUMIFS('Monthly CF'!18:18,'Monthly CF'!$2:$2,'Annual CF'!H$1,'Monthly CF'!$1:$1,"<="&Summary!$K$19) -> 0 | I17: =SUMIFS('Monthly CF'!18:18,'Monthly CF'!$2:$2,'Annual CF'!I$1,'Monthly CF'!$1:$1,"<="&Summary!$K$19) -> 0 | J17: =SUMIFS('Monthly CF'!18:18,'Monthly CF'!$2:$2,'Annual CF'!J$1,'Monthly CF'!$1:$1,"<="&Summary!$K$19) -> 0 | K17: =SUMIFS('Monthly CF'!18:18,'Monthly CF'!$2:$2,'Annual CF'!K$1,'Monthly CF'!$1:$1,"<="&Summary!$K$19) -> 0 | ... M17: =SUMIFS('Monthly CF'!18:18,'Monthly CF'!$2:$2,'Annual CF'!M$1,'Monthly CF'!$1:$1,"<="&Summary!$K$19) -> 0
A18: =SUM(C18:M18) -> 0 | B18: =Revenue!O7 -> Storage Income | D18: =SUMIFS('Monthly CF'!19:19,'Monthly CF'!$2:$2,'Annual CF'!D$1,'Monthly CF'!$1:$1,"<="&Summary!$K$19) -> 0 | E18: =SUMIFS('Monthly CF'!19:19,'Monthly CF'!$2:$2,'Annual CF'!E$1,'Monthly CF'!$1:$1,"<="&Summary!$K$19) -> 0 | F18: =SUMIFS('Monthly CF'!19:19,'Monthly CF'!$2:$2,'Annual CF'!F$1,'Monthly CF'!$1:$1,"<="&Summary!$K$19) -> 0 | G18: =SUMIFS('Monthly CF'!19:19,'Monthly CF'!$2:$2,'Annual CF'!G$1,'Monthly CF'!$1:$1,"<="&Summary!$K$19) -> 0 | H18: =SUMIFS('Monthly CF'!19:19,'Monthly CF'!$2:$2,'Annual CF'!H$1,'Monthly CF'!$1:$1,"<="&Summary!$K$19) -> 0 | I18: =SUMIFS('Monthly CF'!19:19,'Monthly CF'!$2:$2,'Annual CF'!I$1,'Monthly CF'!$1:$1,"<="&Summary!$K$19) -> 0 | J18: =SUMIFS('Monthly CF'!19:19,'Monthly CF'!$2:$2,'Annual CF'!J$1,'Monthly CF'!$1:$1,"<="&Summary!$K$19) -> 0 | K18: =SUMIFS('Monthly CF'!19:19,'Monthly CF'!$2:$2,'Annual CF'!K$1,'Monthly CF'!$1:$1,"<="&Summary!$K$19) -> 0 | ... M18: =SUMIFS('Monthly CF'!19:19,'Monthly CF'!$2:$2,'Annual CF'!M$1,'Monthly CF'!$1:$1,"<="&Summary!$K$19) -> 0
A19: =SUM(C19:M19) -> 76696.398 | B19: =Revenue!O8 -> Forfeited Deposits | D19: =SUMIFS('Monthly CF'!20:20,'Monthly CF'!$2:$2,'Annual CF'!D$1,'Monthly CF'!$1:$1,"<="&Summary!$K$19) -> 6690.2657 | E19: =SUMIFS('Monthly CF'!20:20,'Monthly CF'!$2:$2,'Annual CF'!E$1,'Monthly CF'!$1:$1,"<="&Summary!$K$19) -> 6890.9736 | F19: =SUMIFS('Monthly CF'!20:20,'Monthly CF'!$2:$2,'Annual CF'!F$1,'Monthly CF'!$1:$1,"<="&Summary!$K$19) -> 7097.7029 | G19: =SUMIFS('Monthly CF'!20:20,'Monthly CF'!$2:$2,'Annual CF'!G$1,'Monthly CF'!$1:$1,"<="&Summary!$K$19) -> 7310.6339 | H19: =SUMIFS('Monthly CF'!20:20,'Monthly CF'!$2:$2,'Annual CF'!H$1,'Monthly CF'!$1:$1,"<="&Summary!$K$19) -> 7529.953 | I19: =SUMIFS('Monthly CF'!20:20,'Monthly CF'!$2:$2,'Annual CF'!I$1,'Monthly CF'!$1:$1,"<="&Summary!$K$19) -> 7755.8515 | J19: =SUMIFS('Monthly CF'!20:20,'Monthly CF'!$2:$2,'Annual CF'!J$1,'Monthly CF'!$1:$1,"<="&Summary!$K$19) -> 7988.5271 | K19: =SUMIFS('Monthly CF'!20:20,'Monthly CF'!$2:$2,'Annual CF'!K$1,'Monthly CF'!$1:$1,"<="&Summary!$K$19) -> 8228.1829 | ... M19: =SUMIFS('Monthly CF'!20:20,'Monthly CF'!$2:$2,'Annual CF'!M$1,'Monthly CF'!$1:$1,"<="&Summary!$K$19) -> 8729.2792
A20: =SUM(C20:M20) -> 0 | B20: =Revenue!O9 -> Other Charges | D20: =SUMIFS('Monthly CF'!21:21,'Monthly CF'!$2:$2,'Annual CF'!D$1,'Monthly CF'!$1:$1,"<="&Summary!$K$19) -> 0 | E20: =SUMIFS('Monthly CF'!21:21,'Monthly CF'!$2:$2,'Annual CF'!E$1,'Monthly CF'!$1:$1,"<="&Summary!$K$19) -> 0 | F20: =SUMIFS('Monthly CF'!21:21,'Monthly CF'!$2:$2,'Annual CF'!F$1,'Monthly CF'!$1:$1,"<="&Summary!$K$19) -> 0 | G20: =SUMIFS('Monthly CF'!21:21,'Monthly CF'!$2:$2,'Annual CF'!G$1,'Monthly CF'!$1:$1,"<="&Summary!$K$19) -> 0 | H20: =SUMIFS('Monthly CF'!21:21,'Monthly CF'!$2:$2,'Annual CF'!H$1,'Monthly CF'!$1:$1,"<="&Summary!$K$19) -> 0 | I20: =SUMIFS('Monthly CF'!21:21,'Monthly CF'!$2:$2,'Annual CF'!I$1,'Monthly CF'!$1:$1,"<="&Summary!$K$19) -> 0 | J20: =SUMIFS('Monthly CF'!21:21,'Monthly CF'!$2:$2,'Annual CF'!J$1,'Monthly CF'!$1:$1,"<="&Summary!$K$19) -> 0 | K20: =SUMIFS('Monthly CF'!21:21,'Monthly CF'!$2:$2,'Annual CF'!K$1,'Monthly CF'!$1:$1,"<="&Summary!$K$19) -> 0 | ... M20: =SUMIFS('Monthly CF'!21:21,'Monthly CF'!$2:$2,'Annual CF'!M$1,'Monthly CF'!$1:$1,"<="&Summary!$K$19) -> 0
A21: =SUM(C21:M21) -> 0 | B21: =Revenue!O10 -> Other Charges | D21: =SUMIFS('Monthly CF'!22:22,'Monthly CF'!$2:$2,'Annual CF'!D$1,'Monthly CF'!$1:$1,"<="&Summary!$K$19) -> 0 | E21: =SUMIFS('Monthly CF'!22:22,'Monthly CF'!$2:$2,'Annual CF'!E$1,'Monthly CF'!$1:$1,"<="&Summary!$K$19) -> 0 | F21: =SUMIFS('Monthly CF'!22:22,'Monthly CF'!$2:$2,'Annual CF'!F$1,'Monthly CF'!$1:$1,"<="&Summary!$K$19) -> 0 | G21: =SUMIFS('Monthly CF'!22:22,'Monthly CF'!$2:$2,'Annual CF'!G$1,'Monthly CF'!$1:$1,"<="&Summary!$K$19) -> 0 | H21: =SUMIFS('Monthly CF'!22:22,'Monthly CF'!$2:$2,'Annual CF'!H$1,'Monthly CF'!$1:$1,"<="&Summary!$K$19) -> 0 | I21: =SUMIFS('Monthly CF'!22:22,'Monthly CF'!$2:$2,'Annual CF'!I$1,'Monthly CF'!$1:$1,"<="&Summary!$K$19) -> 0 | J21: =SUMIFS('Monthly CF'!22:22,'Monthly CF'!$2:$2,'Annual CF'!J$1,'Monthly CF'!$1:$1,"<="&Summary!$K$19) -> 0 | K21: =SUMIFS('Monthly CF'!22:22,'Monthly CF'!$2:$2,'Annual CF'!K$1,'Monthly CF'!$1:$1,"<="&Summary!$K$19) -> 0 | ... M21: =SUMIFS('Monthly CF'!22:22,'Monthly CF'!$2:$2,'Annual CF'!M$1,'Monthly CF'!$1:$1,"<="&Summary!$K$19) -> 0
A22: =SUM(C22:M22) -> 0 | B22: =Revenue!O11 -> Other Charges | D22: =SUMIFS('Monthly CF'!23:23,'Monthly CF'!$2:$2,'Annual CF'!D$1,'Monthly CF'!$1:$1,"<="&Summary!$K$19) -> 0 | E22: =SUMIFS('Monthly CF'!23:23,'Monthly CF'!$2:$2,'Annual CF'!E$1,'Monthly CF'!$1:$1,"<="&Summary!$K$19) -> 0 | F22: =SUMIFS('Monthly CF'!23:23,'Monthly CF'!$2:$2,'Annual CF'!F$1,'Monthly CF'!$1:$1,"<="&Summary!$K$19) -> 0 | G22: =SUMIFS('Monthly CF'!23:23,'Monthly CF'!$2:$2,'Annual CF'!G$1,'Monthly CF'!$1:$1,"<="&Summary!$K$19) -> 0 | H22: =SUMIFS('Monthly CF'!23:23,'Monthly CF'!$2:$2,'Annual CF'!H$1,'Monthly CF'!$1:$1,"<="&Summary!$K$19) -> 0 | I22: =SUMIFS('Monthly CF'!23:23,'Monthly CF'!$2:$2,'Annual CF'!I$1,'Monthly CF'!$1:$1,"<="&Summary!$K$19) -> 0 | J22: =SUMIFS('Monthly CF'!23:23,'Monthly CF'!$2:$2,'Annual CF'!J$1,'Monthly CF'!$1:$1,"<="&Summary!$K$19) -> 0 | K22: =SUMIFS('Monthly CF'!23:23,'Monthly CF'!$2:$2,'Annual CF'!K$1,'Monthly CF'!$1:$1,"<="&Summary!$K$19) -> 0 | ... M22: =SUMIFS('Monthly CF'!23:23,'Monthly CF'!$2:$2,'Annual CF'!M$1,'Monthly CF'!$1:$1,"<="&Summary!$K$19) -> 0
A23: =SUM(C23:M23) -> 843660.38 | B23: Total Other Income | D23: =SUMIFS('Monthly CF'!24:24,'Monthly CF'!$2:$2,'Annual CF'!D$1,'Monthly CF'!$1:$1,"<="&Summary!$K$19) -> 73592.922 | E23: =SUMIFS('Monthly CF'!24:24,'Monthly CF'!$2:$2,'Annual CF'!E$1,'Monthly CF'!$1:$1,"<="&Summary!$K$19) -> 75800.71 | F23: =SUMIFS('Monthly CF'!24:24,'Monthly CF'!$2:$2,'Annual CF'!F$1,'Monthly CF'!$1:$1,"<="&Summary!$K$19) -> 78074.731 | G23: =SUMIFS('Monthly CF'!24:24,'Monthly CF'!$2:$2,'Annual CF'!G$1,'Monthly CF'!$1:$1,"<="&Summary!$K$19) -> 80416.973 | H23: =SUMIFS('Monthly CF'!24:24,'Monthly CF'!$2:$2,'Annual CF'!H$1,'Monthly CF'!$1:$1,"<="&Summary!$K$19) -> 82829.483 | I23: =SUMIFS('Monthly CF'!24:24,'Monthly CF'!$2:$2,'Annual CF'!I$1,'Monthly CF'!$1:$1,"<="&Summary!$K$19) -> 85314.367 | J23: =SUMIFS('Monthly CF'!24:24,'Monthly CF'!$2:$2,'Annual CF'!J$1,'Monthly CF'!$1:$1,"<="&Summary!$K$19) -> 87873.798 | K23: =SUMIFS('Monthly CF'!24:24,'Monthly CF'!$2:$2,'Annual CF'!K$1,'Monthly CF'!$1:$1,"<="&Summary!$K$19) -> 90510.012 | ... M23: =SUMIFS('Monthly CF'!24:24,'Monthly CF'!$2:$2,'Annual CF'!M$1,'Monthly CF'!$1:$1,"<="&Summary!$K$19) -> 96022.072
A25: =SUM(C25:M25) -> 35279204 | B25: Effective Gross Revenue | D25: =SUMIFS('Monthly CF'!26:26,'Monthly CF'!$2:$2,'Annual CF'!D$1,'Monthly CF'!$1:$1,"<="&Summary!$K$19) -> 2874140.9 | E25: =SUMIFS('Monthly CF'!26:26,'Monthly CF'!$2:$2,'Annual CF'!E$1,'Monthly CF'!$1:$1,"<="&Summary!$K$19) -> 3135486 | F25: =SUMIFS('Monthly CF'!26:26,'Monthly CF'!$2:$2,'Annual CF'!F$1,'Monthly CF'!$1:$1,"<="&Summary!$K$19) -> 3291550.9 | G25: =SUMIFS('Monthly CF'!26:26,'Monthly CF'!$2:$2,'Annual CF'!G$1,'Monthly CF'!$1:$1,"<="&Summary!$K$19) -> 3390297.5 | H25: =SUMIFS('Monthly CF'!26:26,'Monthly CF'!$2:$2,'Annual CF'!H$1,'Monthly CF'!$1:$1,"<="&Summary!$K$19) -> 3492006.4 | I25: =SUMIFS('Monthly CF'!26:26,'Monthly CF'!$2:$2,'Annual CF'!I$1,'Monthly CF'!$1:$1,"<="&Summary!$K$19) -> 3596766.6 | J25: =SUMIFS('Monthly CF'!26:26,'Monthly CF'!$2:$2,'Annual CF'!J$1,'Monthly CF'!$1:$1,"<="&Summary!$K$19) -> 3704669.6 | K25: =SUMIFS('Monthly CF'!26:26,'Monthly CF'!$2:$2,'Annual CF'!K$1,'Monthly CF'!$1:$1,"<="&Summary!$K$19) -> 3815809.7 | ... M25: =SUMIFS('Monthly CF'!26:26,'Monthly CF'!$2:$2,'Annual CF'!M$1,'Monthly CF'!$1:$1,"<="&Summary!$K$19) -> 4048192.5
B27: Expenses
A28: =SUM(C28:M28) -> -2300891.9 | B28: =Expenses!E3 -> Payroll | D28: =SUMIFS('Monthly CF'!29:29,'Monthly CF'!$2:$2,'Annual CF'!D$1,'Monthly CF'!$1:$1,"<="&Summary!$K$19) -> -200707.97 | E28: =SUMIFS('Monthly CF'!29:29,'Monthly CF'!$2:$2,'Annual CF'!E$1,'Monthly CF'!$1:$1,"<="&Summary!$K$19) -> -206729.21 | F28: =SUMIFS('Monthly CF'!29:29,'Monthly CF'!$2:$2,'Annual CF'!F$1,'Monthly CF'!$1:$1,"<="&Summary!$K$19) -> -212931.09 | G28: =SUMIFS('Monthly CF'!29:29,'Monthly CF'!$2:$2,'Annual CF'!G$1,'Monthly CF'!$1:$1,"<="&Summary!$K$19) -> -219319.02 | H28: =SUMIFS('Monthly CF'!29:29,'Monthly CF'!$2:$2,'Annual CF'!H$1,'Monthly CF'!$1:$1,"<="&Summary!$K$19) -> -225898.59 | I28: =SUMIFS('Monthly CF'!29:29,'Monthly CF'!$2:$2,'Annual CF'!I$1,'Monthly CF'!$1:$1,"<="&Summary!$K$19) -> -232675.55 | J28: =SUMIFS('Monthly CF'!29:29,'Monthly CF'!$2:$2,'Annual CF'!J$1,'Monthly CF'!$1:$1,"<="&Summary!$K$19) -> -239655.81 | K28: =SUMIFS('Monthly CF'!29:29,'Monthly CF'!$2:$2,'Annual CF'!K$1,'Monthly CF'!$1:$1,"<="&Summary!$K$19) -> -246845.49 | ... M28: =SUMIFS('Monthly CF'!29:29,'Monthly CF'!$2:$2,'Annual CF'!M$1,'Monthly CF'!$1:$1,"<="&Summary!$K$19) -> -261878.38
A29: =SUM(C29:M29) -> -351525.16 | B29: =Expenses!E4 -> General & Administrative | D29: =SUMIFS('Monthly CF'!30:30,'Monthly CF'!$2:$2,'Annual CF'!D$1,'Monthly CF'!$1:$1,"<="&Summary!$K$19) -> -30663.718 | E29: =SUMIFS('Monthly CF'!30:30,'Monthly CF'!$2:$2,'Annual CF'!E$1,'Monthly CF'!$1:$1,"<="&Summary!$K$19) -> -31583.629 | F29: =SUMIFS('Monthly CF'!30:30,'Monthly CF'!$2:$2,'Annual CF'!F$1,'Monthly CF'!$1:$1,"<="&Summary!$K$19) -> -32531.138 | G29: =SUMIFS('Monthly CF'!30:30,'Monthly CF'!$2:$2,'Annual CF'!G$1,'Monthly CF'!$1:$1,"<="&Summary!$K$19) -> -33507.072 | H29: =SUMIFS('Monthly CF'!30:30,'Monthly CF'!$2:$2,'Annual CF'!H$1,'Monthly CF'!$1:$1,"<="&Summary!$K$19) -> -34512.284 | I29: =SUMIFS('Monthly CF'!30:30,'Monthly CF'!$2:$2,'Annual CF'!I$1,'Monthly CF'!$1:$1,"<="&Summary!$K$19) -> -35547.653 | J29: =SUMIFS('Monthly CF'!30:30,'Monthly CF'!$2:$2,'Annual CF'!J$1,'Monthly CF'!$1:$1,"<="&Summary!$K$19) -> -36614.083 | K29: =SUMIFS('Monthly CF'!30:30,'Monthly CF'!$2:$2,'Annual CF'!K$1,'Monthly CF'!$1:$1,"<="&Summary!$K$19) -> -37712.505 | ... M29: =SUMIFS('Monthly CF'!30:30,'Monthly CF'!$2:$2,'Annual CF'!M$1,'Monthly CF'!$1:$1,"<="&Summary!$K$19) -> -40009.197
A30: =SUM(C30:M30) -> -287611.49 | B30: =Expenses!E5 -> Marketing | D30: =SUMIFS('Monthly CF'!31:31,'Monthly CF'!$2:$2,'Annual CF'!D$1,'Monthly CF'!$1:$1,"<="&Summary!$K$19) -> -25088.496 | E30: =SUMIFS('Monthly CF'!31:31,'Monthly CF'!$2:$2,'Annual CF'!E$1,'Monthly CF'!$1:$1,"<="&Summary!$K$19) -> -25841.151 | F30: =SUMIFS('Monthly CF'!31:31,'Monthly CF'!$2:$2,'Annual CF'!F$1,'Monthly CF'!$1:$1,"<="&Summary!$K$19) -> -26616.386 | G30: =SUMIFS('Monthly CF'!31:31,'Monthly CF'!$2:$2,'Annual CF'!G$1,'Monthly CF'!$1:$1,"<="&Summary!$K$19) -> -27414.877 | H30: =SUMIFS('Monthly CF'!31:31,'Monthly CF'!$2:$2,'Annual CF'!H$1,'Monthly CF'!$1:$1,"<="&Summary!$K$19) -> -28237.324 | I30: =SUMIFS('Monthly CF'!31:31,'Monthly CF'!$2:$2,'Annual CF'!I$1,'Monthly CF'!$1:$1,"<="&Summary!$K$19) -> -29084.443 | J30: =SUMIFS('Monthly CF'!31:31,'Monthly CF'!$2:$2,'Annual CF'!J$1,'Monthly CF'!$1:$1,"<="&Summary!$K$19) -> -29956.977 | K30: =SUMIFS('Monthly CF'!31:31,'Monthly CF'!$2:$2,'Annual CF'!K$1,'Monthly CF'!$1:$1,"<="&Summary!$K$19) -> -30855.686 | ... M30: =SUMIFS('Monthly CF'!31:31,'Monthly CF'!$2:$2,'Annual CF'!M$1,'Monthly CF'!$1:$1,"<="&Summary!$K$19) -> -32734.797
A31: =SUM(C31:M31) -> -703050.32 | B31: =Expenses!E6 -> Repairs & Maintenance | D31: =SUMIFS('Monthly CF'!32:32,'Monthly CF'!$2:$2,'Annual CF'!D$1,'Monthly CF'!$1:$1,"<="&Summary!$K$19) -> -61327.435 | E31: =SUMIFS('Monthly CF'!32:32,'Monthly CF'!$2:$2,'Annual CF'!E$1,'Monthly CF'!$1:$1,"<="&Summary!$K$19) -> -63167.258 | F31: =SUMIFS('Monthly CF'!32:32,'Monthly CF'!$2:$2,'Annual CF'!F$1,'Monthly CF'!$1:$1,"<="&Summary!$K$19) -> -65062.276 | G31: =SUMIFS('Monthly CF'!32:32,'Monthly CF'!$2:$2,'Annual CF'!G$1,'Monthly CF'!$1:$1,"<="&Summary!$K$19) -> -67014.144 | H31: =SUMIFS('Monthly CF'!32:32,'Monthly CF'!$2:$2,'Annual CF'!H$1,'Monthly CF'!$1:$1,"<="&Summary!$K$19) -> -69024.569 | I31: =SUMIFS('Monthly CF'!32:32,'Monthly CF'!$2:$2,'Annual CF'!I$1,'Monthly CF'!$1:$1,"<="&Summary!$K$19) -> -71095.306 | J31: =SUMIFS('Monthly CF'!32:32,'Monthly CF'!$2:$2,'Annual CF'!J$1,'Monthly CF'!$1:$1,"<="&Summary!$K$19) -> -73228.165 | K31: =SUMIFS('Monthly CF'!32:32,'Monthly CF'!$2:$2,'Annual CF'!K$1,'Monthly CF'!$1:$1,"<="&Summary!$K$19) -> -75425.01 | ... M31: =SUMIFS('Monthly CF'!32:32,'Monthly CF'!$2:$2,'Annual CF'!M$1,'Monthly CF'!$1:$1,"<="&Summary!$K$19) -> -80018.393
A32: =SUM(C32:M32) -> -479352.49 | B32: =Expenses!E7 -> Turnover Costs | D32: =SUMIFS('Monthly CF'!33:33,'Monthly CF'!$2:$2,'Annual CF'!D$1,'Monthly CF'!$1:$1,"<="&Summary!$K$19) -> -41814.16 | E32: =SUMIFS('Monthly CF'!33:33,'Monthly CF'!$2:$2,'Annual CF'!E$1,'Monthly CF'!$1:$1,"<="&Summary!$K$19) -> -43068.585 | F32: =SUMIFS('Monthly CF'!33:33,'Monthly CF'!$2:$2,'Annual CF'!F$1,'Monthly CF'!$1:$1,"<="&Summary!$K$19) -> -44360.643 | G32: =SUMIFS('Monthly CF'!33:33,'Monthly CF'!$2:$2,'Annual CF'!G$1,'Monthly CF'!$1:$1,"<="&Summary!$K$19) -> -45691.462 | H32: =SUMIFS('Monthly CF'!33:33,'Monthly CF'!$2:$2,'Annual CF'!H$1,'Monthly CF'!$1:$1,"<="&Summary!$K$19) -> -47062.206 | I32: =SUMIFS('Monthly CF'!33:33,'Monthly CF'!$2:$2,'Annual CF'!I$1,'Monthly CF'!$1:$1,"<="&Summary!$K$19) -> -48474.072 | J32: =SUMIFS('Monthly CF'!33:33,'Monthly CF'!$2:$2,'Annual CF'!J$1,'Monthly CF'!$1:$1,"<="&Summary!$K$19) -> -49928.294 | K32: =SUMIFS('Monthly CF'!33:33,'Monthly CF'!$2:$2,'Annual CF'!K$1,'Monthly CF'!$1:$1,"<="&Summary!$K$19) -> -51426.143 | ... M32: =SUMIFS('Monthly CF'!33:33,'Monthly CF'!$2:$2,'Annual CF'!M$1,'Monthly CF'!$1:$1,"<="&Summary!$K$19) -> -54557.995
A33: =SUM(C33:M33) -> -287611.49 | B33: =Expenses!E8 -> Contract Services | D33: =SUMIFS('Monthly CF'!34:34,'Monthly CF'!$2:$2,'Annual CF'!D$1,'Monthly CF'!$1:$1,"<="&Summary!$K$19) -> -25088.496 | E33: =SUMIFS('Monthly CF'!34:34,'Monthly CF'!$2:$2,'Annual CF'!E$1,'Monthly CF'!$1:$1,"<="&Summary!$K$19) -> -25841.151 | F33: =SUMIFS('Monthly CF'!34:34,'Monthly CF'!$2:$2,'Annual CF'!F$1,'Monthly CF'!$1:$1,"<="&Summary!$K$19) -> -26616.386 | G33: =SUMIFS('Monthly CF'!34:34,'Monthly CF'!$2:$2,'Annual CF'!G$1,'Monthly CF'!$1:$1,"<="&Summary!$K$19) -> -27414.877 | H33: =SUMIFS('Monthly CF'!34:34,'Monthly CF'!$2:$2,'Annual CF'!H$1,'Monthly CF'!$1:$1,"<="&Summary!$K$19) -> -28237.324 | I33: =SUMIFS('Monthly CF'!34:34,'Monthly CF'!$2:$2,'Annual CF'!I$1,'Monthly CF'!$1:$1,"<="&Summary!$K$19) -> -29084.443 | J33: =SUMIFS('Monthly CF'!34:34,'Monthly CF'!$2:$2,'Annual CF'!J$1,'Monthly CF'!$1:$1,"<="&Summary!$K$19) -> -29956.977 | K33: =SUMIFS('Monthly CF'!34:34,'Monthly CF'!$2:$2,'Annual CF'!K$1,'Monthly CF'!$1:$1,"<="&Summary!$K$19) -> -30855.686 | ... M33: =SUMIFS('Monthly CF'!34:34,'Monthly CF'!$2:$2,'Annual CF'!M$1,'Monthly CF'!$1:$1,"<="&Summary!$K$19) -> -32734.797
A34: =SUM(C34:M34) -> -703050.32 | B34: =Expenses!E9 -> Utilities | D34: =SUMIFS('Monthly CF'!35:35,'Monthly CF'!$2:$2,'Annual CF'!D$1,'Monthly CF'!$1:$1,"<="&Summary!$K$19) -> -61327.435 | E34: =SUMIFS('Monthly CF'!35:35,'Monthly CF'!$2:$2,'Annual CF'!E$1,'Monthly CF'!$1:$1,"<="&Summary!$K$19) -> -63167.258 | F34: =SUMIFS('Monthly CF'!35:35,'Monthly CF'!$2:$2,'Annual CF'!F$1,'Monthly CF'!$1:$1,"<="&Summary!$K$19) -> -65062.276 | G34: =SUMIFS('Monthly CF'!35:35,'Monthly CF'!$2:$2,'Annual CF'!G$1,'Monthly CF'!$1:$1,"<="&Summary!$K$19) -> -67014.144 | H34: =SUMIFS('Monthly CF'!35:35,'Monthly CF'!$2:$2,'Annual CF'!H$1,'Monthly CF'!$1:$1,"<="&Summary!$K$19) -> -69024.569 | I34: =SUMIFS('Monthly CF'!35:35,'Monthly CF'!$2:$2,'Annual CF'!I$1,'Monthly CF'!$1:$1,"<="&Summary!$K$19) -> -71095.306 | J34: =SUMIFS('Monthly CF'!35:35,'Monthly CF'!$2:$2,'Annual CF'!J$1,'Monthly CF'!$1:$1,"<="&Summary!$K$19) -> -73228.165 | K34: =SUMIFS('Monthly CF'!35:35,'Monthly CF'!$2:$2,'Annual CF'!K$1,'Monthly CF'!$1:$1,"<="&Summary!$K$19) -> -75425.01 | ... M34: =SUMIFS('Monthly CF'!35:35,'Monthly CF'!$2:$2,'Annual CF'!M$1,'Monthly CF'!$1:$1,"<="&Summary!$K$19) -> -80018.393
A35: =SUM(C35:M35) -> 607179.82 | B35: =Expenses!E10 -> Utility Bill-Back | D35: =SUMIFS('Monthly CF'!36:36,'Monthly CF'!$2:$2,'Annual CF'!D$1,'Monthly CF'!$1:$1,"<="&Summary!$K$19) -> 52964.603 | E35: =SUMIFS('Monthly CF'!36:36,'Monthly CF'!$2:$2,'Annual CF'!E$1,'Monthly CF'!$1:$1,"<="&Summary!$K$19) -> 54553.541 | F35: =SUMIFS('Monthly CF'!36:36,'Monthly CF'!$2:$2,'Annual CF'!F$1,'Monthly CF'!$1:$1,"<="&Summary!$K$19) -> 56190.148 | G35: =SUMIFS('Monthly CF'!36:36,'Monthly CF'!$2:$2,'Annual CF'!G$1,'Monthly CF'!$1:$1,"<="&Summary!$K$19) -> 57875.852 | H35: =SUMIFS('Monthly CF'!36:36,'Monthly CF'!$2:$2,'Annual CF'!H$1,'Monthly CF'!$1:$1,"<="&Summary!$K$19) -> 59612.128 | I35: =SUMIFS('Monthly CF'!36:36,'Monthly CF'!$2:$2,'Annual CF'!I$1,'Monthly CF'!$1:$1,"<="&Summary!$K$19) -> 61400.491 | J35: =SUMIFS('Monthly CF'!36:36,'Monthly CF'!$2:$2,'Annual CF'!J$1,'Monthly CF'!$1:$1,"<="&Summary!$K$19) -> 63242.506 | K35: =SUMIFS('Monthly CF'!36:36,'Monthly CF'!$2:$2,'Annual CF'!K$1,'Monthly CF'!$1:$1,"<="&Summary!$K$19) -> 65139.781 | ... M35: =SUMIFS('Monthly CF'!36:36,'Monthly CF'!$2:$2,'Annual CF'!M$1,'Monthly CF'!$1:$1,"<="&Summary!$K$19) -> 69106.794
A36: =SUM(C36:M36) -> -1411168.2 | B36: =Expenses!E11 -> Property Management Fee | D36: =SUMIFS('Monthly CF'!37:37,'Monthly CF'!$2:$2,'Annual CF'!D$1,'Monthly CF'!$1:$1,"<="&Summary!$K$19) -> -114965.63 | E36: =SUMIFS('Monthly CF'!37:37,'Monthly CF'!$2:$2,'Annual CF'!E$1,'Monthly CF'!$1:$1,"<="&Summary!$K$19) -> -125419.44 | F36: =SUMIFS('Monthly CF'!37:37,'Monthly CF'!$2:$2,'Annual CF'!F$1,'Monthly CF'!$1:$1,"<="&Summary!$K$19) -> -131662.04 | G36: =SUMIFS('Monthly CF'!37:37,'Monthly CF'!$2:$2,'Annual CF'!G$1,'Monthly CF'!$1:$1,"<="&Summary!$K$19) -> -135611.9 | H36: =SUMIFS('Monthly CF'!37:37,'Monthly CF'!$2:$2,'Annual CF'!H$1,'Monthly CF'!$1:$1,"<="&Summary!$K$19) -> -139680.26 | I36: =SUMIFS('Monthly CF'!37:37,'Monthly CF'!$2:$2,'Annual CF'!I$1,'Monthly CF'!$1:$1,"<="&Summary!$K$19) -> -143870.66 | J36: =SUMIFS('Monthly CF'!37:37,'Monthly CF'!$2:$2,'Annual CF'!J$1,'Monthly CF'!$1:$1,"<="&Summary!$K$19) -> -148186.78 | K36: =SUMIFS('Monthly CF'!37:37,'Monthly CF'!$2:$2,'Annual CF'!K$1,'Monthly CF'!$1:$1,"<="&Summary!$K$19) -> -152632.39 | ... M36: =SUMIFS('Monthly CF'!37:37,'Monthly CF'!$2:$2,'Annual CF'!M$1,'Monthly CF'!$1:$1,"<="&Summary!$K$19) -> -161927.7
A37: =SUM(C37:M37) -> -4812662.8 | B37: =Expenses!E12 -> Property Taxes | D37: =SUMIFS('Monthly CF'!38:38,'Monthly CF'!$2:$2,'Annual CF'!D$1,'Monthly CF'!$1:$1,"<="&Summary!$K$19) -> -412500 | E37: =SUMIFS('Monthly CF'!38:38,'Monthly CF'!$2:$2,'Annual CF'!E$1,'Monthly CF'!$1:$1,"<="&Summary!$K$19) -> -433125 | F37: =SUMIFS('Monthly CF'!38:38,'Monthly CF'!$2:$2,'Annual CF'!F$1,'Monthly CF'!$1:$1,"<="&Summary!$K$19) -> -446118.75 | G37: =SUMIFS('Monthly CF'!38:38,'Monthly CF'!$2:$2,'Annual CF'!G$1,'Monthly CF'!$1:$1,"<="&Summary!$K$19) -> -459502.31 | H37: =SUMIFS('Monthly CF'!38:38,'Monthly CF'!$2:$2,'Annual CF'!H$1,'Monthly CF'!$1:$1,"<="&Summary!$K$19) -> -473287.38 | I37: =SUMIFS('Monthly CF'!38:38,'Monthly CF'!$2:$2,'Annual CF'!I$1,'Monthly CF'!$1:$1,"<="&Summary!$K$19) -> -487486 | J37: =SUMIFS('Monthly CF'!38:38,'Monthly CF'!$2:$2,'Annual CF'!J$1,'Monthly CF'!$1:$1,"<="&Summary!$K$19) -> -502110.58 | K37: =SUMIFS('Monthly CF'!38:38,'Monthly CF'!$2:$2,'Annual CF'!K$1,'Monthly CF'!$1:$1,"<="&Summary!$K$19) -> -517173.9 | ... M37: =SUMIFS('Monthly CF'!38:38,'Monthly CF'!$2:$2,'Annual CF'!M$1,'Monthly CF'!$1:$1,"<="&Summary!$K$19) -> -548669.79
A38: =SUM(C38:M38) -> -567462.03 | B38: =Expenses!E13 -> Insurance | D38: =SUMIFS('Monthly CF'!39:39,'Monthly CF'!$2:$2,'Annual CF'!D$1,'Monthly CF'!$1:$1,"<="&Summary!$K$19) -> -49500 | E38: =SUMIFS('Monthly CF'!39:39,'Monthly CF'!$2:$2,'Annual CF'!E$1,'Monthly CF'!$1:$1,"<="&Summary!$K$19) -> -50985 | F38: =SUMIFS('Monthly CF'!39:39,'Monthly CF'!$2:$2,'Annual CF'!F$1,'Monthly CF'!$1:$1,"<="&Summary!$K$19) -> -52514.55 | G38: =SUMIFS('Monthly CF'!39:39,'Monthly CF'!$2:$2,'Annual CF'!G$1,'Monthly CF'!$1:$1,"<="&Summary!$K$19) -> -54089.986 | H38: =SUMIFS('Monthly CF'!39:39,'Monthly CF'!$2:$2,'Annual CF'!H$1,'Monthly CF'!$1:$1,"<="&Summary!$K$19) -> -55712.686 | I38: =SUMIFS('Monthly CF'!39:39,'Monthly CF'!$2:$2,'Annual CF'!I$1,'Monthly CF'!$1:$1,"<="&Summary!$K$19) -> -57384.067 | J38: =SUMIFS('Monthly CF'!39:39,'Monthly CF'!$2:$2,'Annual CF'!J$1,'Monthly CF'!$1:$1,"<="&Summary!$K$19) -> -59105.589 | K38: =SUMIFS('Monthly CF'!39:39,'Monthly CF'!$2:$2,'Annual CF'!K$1,'Monthly CF'!$1:$1,"<="&Summary!$K$19) -> -60878.756 | ... M38: =SUMIFS('Monthly CF'!39:39,'Monthly CF'!$2:$2,'Annual CF'!M$1,'Monthly CF'!$1:$1,"<="&Summary!$K$19) -> -64586.273
A39: =SUM(C39:M39) -> -378308.02 | B39: Capital Expense Reserves | D39: =SUMIFS('Monthly CF'!40:40,'Monthly CF'!$2:$2,'Annual CF'!D$1,'Monthly CF'!$1:$1,"<="&Summary!$K$19) -> -33000 | E39: =SUMIFS('Monthly CF'!40:40,'Monthly CF'!$2:$2,'Annual CF'!E$1,'Monthly CF'!$1:$1,"<="&Summary!$K$19) -> -33990 | F39: =SUMIFS('Monthly CF'!40:40,'Monthly CF'!$2:$2,'Annual CF'!F$1,'Monthly CF'!$1:$1,"<="&Summary!$K$19) -> -35009.7 | G39: =SUMIFS('Monthly CF'!40:40,'Monthly CF'!$2:$2,'Annual CF'!G$1,'Monthly CF'!$1:$1,"<="&Summary!$K$19) -> -36059.991 | H39: =SUMIFS('Monthly CF'!40:40,'Monthly CF'!$2:$2,'Annual CF'!H$1,'Monthly CF'!$1:$1,"<="&Summary!$K$19) -> -37141.791 | I39: =SUMIFS('Monthly CF'!40:40,'Monthly CF'!$2:$2,'Annual CF'!I$1,'Monthly CF'!$1:$1,"<="&Summary!$K$19) -> -38256.044 | J39: =SUMIFS('Monthly CF'!40:40,'Monthly CF'!$2:$2,'Annual CF'!J$1,'Monthly CF'!$1:$1,"<="&Summary!$K$19) -> -39403.726 | K39: =SUMIFS('Monthly CF'!40:40,'Monthly CF'!$2:$2,'Annual CF'!K$1,'Monthly CF'!$1:$1,"<="&Summary!$K$19) -> -40585.838 | ... M39: =SUMIFS('Monthly CF'!40:40,'Monthly CF'!$2:$2,'Annual CF'!M$1,'Monthly CF'!$1:$1,"<="&Summary!$K$19) -> -43057.515
A40: =SUM(C40:M40) -> -11675514 | B40: Total Operating Expenses | D40: =SUMIFS('Monthly CF'!41:41,'Monthly CF'!$2:$2,'Annual CF'!D$1,'Monthly CF'!$1:$1,"<="&Summary!$K$19) -> -1003018.7 | E40: =SUMIFS('Monthly CF'!41:41,'Monthly CF'!$2:$2,'Annual CF'!E$1,'Monthly CF'!$1:$1,"<="&Summary!$K$19) -> -1048364.1 | F40: =SUMIFS('Monthly CF'!41:41,'Monthly CF'!$2:$2,'Annual CF'!F$1,'Monthly CF'!$1:$1,"<="&Summary!$K$19) -> -1082295.1 | G40: =SUMIFS('Monthly CF'!41:41,'Monthly CF'!$2:$2,'Annual CF'!G$1,'Monthly CF'!$1:$1,"<="&Summary!$K$19) -> -1114763.9 | H40: =SUMIFS('Monthly CF'!41:41,'Monthly CF'!$2:$2,'Annual CF'!H$1,'Monthly CF'!$1:$1,"<="&Summary!$K$19) -> -1148206.8 | I40: =SUMIFS('Monthly CF'!41:41,'Monthly CF'!$2:$2,'Annual CF'!I$1,'Monthly CF'!$1:$1,"<="&Summary!$K$19) -> -1182653.1 | J40: =SUMIFS('Monthly CF'!41:41,'Monthly CF'!$2:$2,'Annual CF'!J$1,'Monthly CF'!$1:$1,"<="&Summary!$K$19) -> -1218132.6 | K40: =SUMIFS('Monthly CF'!41:41,'Monthly CF'!$2:$2,'Annual CF'!K$1,'Monthly CF'!$1:$1,"<="&Summary!$K$19) -> -1254676.6 | ... M40: =SUMIFS('Monthly CF'!41:41,'Monthly CF'!$2:$2,'Annual CF'!M$1,'Monthly CF'!$1:$1,"<="&Summary!$K$19) -> -1331086.4
A42: =SUM(C42:M42) -> 23603689 | B42: Net Operating Income | D42: =SUMIFS('Monthly CF'!43:43,'Monthly CF'!$2:$2,'Annual CF'!D$1,'Monthly CF'!$1:$1,"<="&Summary!$K$19) -> 1871122.1 | E42: =SUMIFS('Monthly CF'!43:43,'Monthly CF'!$2:$2,'Annual CF'!E$1,'Monthly CF'!$1:$1,"<="&Summary!$K$19) -> 2087121.8 | F42: =SUMIFS('Monthly CF'!43:43,'Monthly CF'!$2:$2,'Annual CF'!F$1,'Monthly CF'!$1:$1,"<="&Summary!$K$19) -> 2209255.8 | G42: =SUMIFS('Monthly CF'!43:43,'Monthly CF'!$2:$2,'Annual CF'!G$1,'Monthly CF'!$1:$1,"<="&Summary!$K$19) -> 2275533.5 | H42: =SUMIFS('Monthly CF'!43:43,'Monthly CF'!$2:$2,'Annual CF'!H$1,'Monthly CF'!$1:$1,"<="&Summary!$K$19) -> 2343799.5 | I42: =SUMIFS('Monthly CF'!43:43,'Monthly CF'!$2:$2,'Annual CF'!I$1,'Monthly CF'!$1:$1,"<="&Summary!$K$19) -> 2414113.5 | J42: =SUMIFS('Monthly CF'!43:43,'Monthly CF'!$2:$2,'Annual CF'!J$1,'Monthly CF'!$1:$1,"<="&Summary!$K$19) -> 2486536.9 | K42: =SUMIFS('Monthly CF'!43:43,'Monthly CF'!$2:$2,'Annual CF'!K$1,'Monthly CF'!$1:$1,"<="&Summary!$K$19) -> 2561133 | ... M42: =SUMIFS('Monthly CF'!43:43,'Monthly CF'!$2:$2,'Annual CF'!M$1,'Monthly CF'!$1:$1,"<="&Summary!$K$19) -> 2717106
A44: =SUM(C44:M44) -> -1963500 | B44: Construction Expenses | D44: =SUMIFS('Monthly CF'!45:45,'Monthly CF'!$2:$2,'Annual CF'!D$1,'Monthly CF'!$1:$1,"<="&Summary!$K$19) -> -1603020.8 | E44: =SUMIFS('Monthly CF'!45:45,'Monthly CF'!$2:$2,'Annual CF'!E$1,'Monthly CF'!$1:$1,"<="&Summary!$K$19) -> -332750 | F44: =SUMIFS('Monthly CF'!45:45,'Monthly CF'!$2:$2,'Annual CF'!F$1,'Monthly CF'!$1:$1,"<="&Summary!$K$19) -> -27729.167 | G44: =SUMIFS('Monthly CF'!45:45,'Monthly CF'!$2:$2,'Annual CF'!G$1,'Monthly CF'!$1:$1,"<="&Summary!$K$19) -> 0 | H44: =SUMIFS('Monthly CF'!45:45,'Monthly CF'!$2:$2,'Annual CF'!H$1,'Monthly CF'!$1:$1,"<="&Summary!$K$19) -> 0 | I44: =SUMIFS('Monthly CF'!45:45,'Monthly CF'!$2:$2,'Annual CF'!I$1,'Monthly CF'!$1:$1,"<="&Summary!$K$19) -> 0 | J44: =SUMIFS('Monthly CF'!45:45,'Monthly CF'!$2:$2,'Annual CF'!J$1,'Monthly CF'!$1:$1,"<="&Summary!$K$19) -> 0 | K44: =SUMIFS('Monthly CF'!45:45,'Monthly CF'!$2:$2,'Annual CF'!K$1,'Monthly CF'!$1:$1,"<="&Summary!$K$19) -> 0 | ... M44: =SUMIFS('Monthly CF'!45:45,'Monthly CF'!$2:$2,'Annual CF'!M$1,'Monthly CF'!$1:$1,"<="&Summary!$K$19) -> 0
A46: =SUM(C46:M46) -> 21640189 | B46: Cash Flow Before Debt Service | D46: =SUMIFS('Monthly CF'!47:47,'Monthly CF'!$2:$2,'Annual CF'!D$1,'Monthly CF'!$1:$1,"<="&Summary!$K$19) -> 268101.29 | E46: =SUMIFS('Monthly CF'!47:47,'Monthly CF'!$2:$2,'Annual CF'!E$1,'Monthly CF'!$1:$1,"<="&Summary!$K$19) -> 1754371.8 | F46: =SUMIFS('Monthly CF'!47:47,'Monthly CF'!$2:$2,'Annual CF'!F$1,'Monthly CF'!$1:$1,"<="&Summary!$K$19) -> 2181526.7 | G46: =SUMIFS('Monthly CF'!47:47,'Monthly CF'!$2:$2,'Annual CF'!G$1,'Monthly CF'!$1:$1,"<="&Summary!$K$19) -> 2275533.5 | H46: =SUMIFS('Monthly CF'!47:47,'Monthly CF'!$2:$2,'Annual CF'!H$1,'Monthly CF'!$1:$1,"<="&Summary!$K$19) -> 2343799.5 | I46: =SUMIFS('Monthly CF'!47:47,'Monthly CF'!$2:$2,'Annual CF'!I$1,'Monthly CF'!$1:$1,"<="&Summary!$K$19) -> 2414113.5 | J46: =SUMIFS('Monthly CF'!47:47,'Monthly CF'!$2:$2,'Annual CF'!J$1,'Monthly CF'!$1:$1,"<="&Summary!$K$19) -> 2486536.9 | K46: =SUMIFS('Monthly CF'!47:47,'Monthly CF'!$2:$2,'Annual CF'!K$1,'Monthly CF'!$1:$1,"<="&Summary!$K$19) -> 2561133 | ... M46: =SUMIFS('Monthly CF'!47:47,'Monthly CF'!$2:$2,'Annual CF'!M$1,'Monthly CF'!$1:$1,"<="&Summary!$K$19) -> 2717106
B48: Loan Information
A49: =SUM(C49:M49) -> 56000000 | B49: Loan Funding | C49: =Summary!E2 -> 26000000 | D49: =SUMIFS('Monthly CF'!50:50,'Monthly CF'!$2:$2,'Annual CF'!D$1,'Monthly CF'!$1:$1,"<="&Summary!$K$19) -> 0 | E49: =SUMIFS('Monthly CF'!50:50,'Monthly CF'!$2:$2,'Annual CF'!E$1,'Monthly CF'!$1:$1,"<="&Summary!$K$19) -> 0 | F49: =SUMIFS('Monthly CF'!50:50,'Monthly CF'!$2:$2,'Annual CF'!F$1,'Monthly CF'!$1:$1,"<="&Summary!$K$19) -> 0 | G49: =SUMIFS('Monthly CF'!50:50,'Monthly CF'!$2:$2,'Annual CF'!G$1,'Monthly CF'!$1:$1,"<="&Summary!$K$19) -> 0 | H49: =SUMIFS('Monthly CF'!50:50,'Monthly CF'!$2:$2,'Annual CF'!H$1,'Monthly CF'!$1:$1,"<="&Summary!$K$19) -> 30000000 | I49: =SUMIFS('Monthly CF'!50:50,'Monthly CF'!$2:$2,'Annual CF'!I$1,'Monthly CF'!$1:$1,"<="&Summary!$K$19) -> 0 | J49: =SUMIFS('Monthly CF'!50:50,'Monthly CF'!$2:$2,'Annual CF'!J$1,'Monthly CF'!$1:$1,"<="&Summary!$K$19) -> 0 | K49: =SUMIFS('Monthly CF'!50:50,'Monthly CF'!$2:$2,'Annual CF'!K$1,'Monthly CF'!$1:$1,"<="&Summary!$K$19) -> 0 | ... M49: =SUMIFS('Monthly CF'!50:50,'Monthly CF'!$2:$2,'Annual CF'!M$1,'Monthly CF'!$1:$1,"<="&Summary!$K$19) -> 0
A50: =SUM(C50:M50) -> -13136462 | B50: Total Payment | D50: =SUMIFS('Monthly CF'!51:51,'Monthly CF'!$2:$2,'Annual CF'!D$1,'Monthly CF'!$1:$1,"<="&Summary!$K$19) -> -1040000 | E50: =SUMIFS('Monthly CF'!51:51,'Monthly CF'!$2:$2,'Annual CF'!E$1,'Monthly CF'!$1:$1,"<="&Summary!$K$19) -> -1040000 | F50: =SUMIFS('Monthly CF'!51:51,'Monthly CF'!$2:$2,'Annual CF'!F$1,'Monthly CF'!$1:$1,"<="&Summary!$K$19) -> -1040000 | G50: =SUMIFS('Monthly CF'!51:51,'Monthly CF'!$2:$2,'Annual CF'!G$1,'Monthly CF'!$1:$1,"<="&Summary!$K$19) -> -1489535.7 | H50: =SUMIFS('Monthly CF'!51:51,'Monthly CF'!$2:$2,'Annual CF'!H$1,'Monthly CF'!$1:$1,"<="&Summary!$K$19) -> -1489535.7 | I50: =SUMIFS('Monthly CF'!51:51,'Monthly CF'!$2:$2,'Annual CF'!I$1,'Monthly CF'!$1:$1,"<="&Summary!$K$19) -> -1200000 | J50: =SUMIFS('Monthly CF'!51:51,'Monthly CF'!$2:$2,'Annual CF'!J$1,'Monthly CF'!$1:$1,"<="&Summary!$K$19) -> -1200000 | K50: =SUMIFS('Monthly CF'!51:51,'Monthly CF'!$2:$2,'Annual CF'!K$1,'Monthly CF'!$1:$1,"<="&Summary!$K$19) -> -1200000 | ... M50: =SUMIFS('Monthly CF'!51:51,'Monthly CF'!$2:$2,'Annual CF'!M$1,'Monthly CF'!$1:$1,"<="&Summary!$K$19) -> -1718695.1
A51: =SUM(C51:M51) -> -53987461 | B51: Loan Payoff | D51: =SUMIFS('Monthly CF'!52:52,'Monthly CF'!$2:$2,'Annual CF'!D$1,'Monthly CF'!$1:$1,"<="&Summary!$K$19) -> 0 | E51: =SUMIFS('Monthly CF'!52:52,'Monthly CF'!$2:$2,'Annual CF'!E$1,'Monthly CF'!$1:$1,"<="&Summary!$K$19) -> 0 | F51: =SUMIFS('Monthly CF'!52:52,'Monthly CF'!$2:$2,'Annual CF'!F$1,'Monthly CF'!$1:$1,"<="&Summary!$K$19) -> 0 | G51: =SUMIFS('Monthly CF'!52:52,'Monthly CF'!$2:$2,'Annual CF'!G$1,'Monthly CF'!$1:$1,"<="&Summary!$K$19) -> 0 | H51: =SUMIFS('Monthly CF'!52:52,'Monthly CF'!$2:$2,'Annual CF'!H$1,'Monthly CF'!$1:$1,"<="&Summary!$K$19) -> -25065607 | I51: =SUMIFS('Monthly CF'!52:52,'Monthly CF'!$2:$2,'Annual CF'!I$1,'Monthly CF'!$1:$1,"<="&Summary!$K$19) -> 0 | J51: =SUMIFS('Monthly CF'!52:52,'Monthly CF'!$2:$2,'Annual CF'!J$1,'Monthly CF'!$1:$1,"<="&Summary!$K$19) -> 0 | K51: =SUMIFS('Monthly CF'!52:52,'Monthly CF'!$2:$2,'Annual CF'!K$1,'Monthly CF'!$1:$1,"<="&Summary!$K$19) -> 0 | ... M51: =SUMIFS('Monthly CF'!52:52,'Monthly CF'!$2:$2,'Annual CF'!M$1,'Monthly CF'!$1:$1,"<="&Summary!$K$19) -> -28921854
A52: =SUM(C52:M52) -> -560000 | B52: Loan Fees | C52: =C49*-Summary!E8 -> -260000 | D52: =SUMIFS('Monthly CF'!53:53,'Monthly CF'!$2:$2,'Annual CF'!D$1,'Monthly CF'!$1:$1,"<="&Summary!$K$19) -> 0 | E52: =SUMIFS('Monthly CF'!53:53,'Monthly CF'!$2:$2,'Annual CF'!E$1,'Monthly CF'!$1:$1,"<="&Summary!$K$19) -> 0 | F52: =SUMIFS('Monthly CF'!53:53,'Monthly CF'!$2:$2,'Annual CF'!F$1,'Monthly CF'!$1:$1,"<="&Summary!$K$19) -> 0 | G52: =SUMIFS('Monthly CF'!53:53,'Monthly CF'!$2:$2,'Annual CF'!G$1,'Monthly CF'!$1:$1,"<="&Summary!$K$19) -> 0 | H52: =SUMIFS('Monthly CF'!53:53,'Monthly CF'!$2:$2,'Annual CF'!H$1,'Monthly CF'!$1:$1,"<="&Summary!$K$19) -> -300000 | I52: =SUMIFS('Monthly CF'!53:53,'Monthly CF'!$2:$2,'Annual CF'!I$1,'Monthly CF'!$1:$1,"<="&Summary!$K$19) -> 0 | J52: =SUMIFS('Monthly CF'!53:53,'Monthly CF'!$2:$2,'Annual CF'!J$1,'Monthly CF'!$1:$1,"<="&Summary!$K$19) -> 0 | K52: =SUMIFS('Monthly CF'!53:53,'Monthly CF'!$2:$2,'Annual CF'!K$1,'Monthly CF'!$1:$1,"<="&Summary!$K$19) -> 0 | ... M52: =SUMIFS('Monthly CF'!53:53,'Monthly CF'!$2:$2,'Annual CF'!M$1,'Monthly CF'!$1:$1,"<="&Summary!$K$19) -> 0
A54: =SUM(C54:M54) -> 8503727.8 | B54: Cash Flow After Debt Service | D54: =SUMIFS('Monthly CF'!55:55,'Monthly CF'!$2:$2,'Annual CF'!D$1,'Monthly CF'!$1:$1,"<="&Summary!$K$19) -> -771898.71 | E54: =SUMIFS('Monthly CF'!55:55,'Monthly CF'!$2:$2,'Annual CF'!E$1,'Monthly CF'!$1:$1,"<="&Summary!$K$19) -> 714371.81 | F54: =SUMIFS('Monthly CF'!55:55,'Monthly CF'!$2:$2,'Annual CF'!F$1,'Monthly CF'!$1:$1,"<="&Summary!$K$19) -> 1141526.7 | G54: =SUMIFS('Monthly CF'!55:55,'Monthly CF'!$2:$2,'Annual CF'!G$1,'Monthly CF'!$1:$1,"<="&Summary!$K$19) -> 785997.8 | H54: =SUMIFS('Monthly CF'!55:55,'Monthly CF'!$2:$2,'Annual CF'!H$1,'Monthly CF'!$1:$1,"<="&Summary!$K$19) -> 854263.8 | I54: =SUMIFS('Monthly CF'!55:55,'Monthly CF'!$2:$2,'Annual CF'!I$1,'Monthly CF'!$1:$1,"<="&Summary!$K$19) -> 1214113.5 | J54: =SUMIFS('Monthly CF'!55:55,'Monthly CF'!$2:$2,'Annual CF'!J$1,'Monthly CF'!$1:$1,"<="&Summary!$K$19) -> 1286536.9 | K54: =SUMIFS('Monthly CF'!55:55,'Monthly CF'!$2:$2,'Annual CF'!K$1,'Monthly CF'!$1:$1,"<="&Summary!$K$19) -> 1361133 | ... M54: =SUMIFS('Monthly CF'!55:55,'Monthly CF'!$2:$2,'Annual CF'!M$1,'Monthly CF'!$1:$1,"<="&Summary!$K$19) -> 998410.96
B56: Working Capital Funding
A57: =SUM(C57:M57) -> -300000 | B57: Working Capital Contributed | C57: =-Summary!B23 -> -300000
A58: =SUM(C58:M58) -> 300000 | B58: Working Capital Distributed | D58: =SUMIFS('Monthly CF'!59:59,'Monthly CF'!$2:$2,'Annual CF'!D$1,'Monthly CF'!$1:$1,"<="&Summary!$K$19) -> 300000 | E58: =SUMIFS('Monthly CF'!59:59,'Monthly CF'!$2:$2,'Annual CF'!E$1,'Monthly CF'!$1:$1,"<="&Summary!$K$19) -> 0 | F58: =SUMIFS('Monthly CF'!59:59,'Monthly CF'!$2:$2,'Annual CF'!F$1,'Monthly CF'!$1:$1,"<="&Summary!$K$19) -> 0 | G58: =SUMIFS('Monthly CF'!59:59,'Monthly CF'!$2:$2,'Annual CF'!G$1,'Monthly CF'!$1:$1,"<="&Summary!$K$19) -> 0 | H58: =SUMIFS('Monthly CF'!59:59,'Monthly CF'!$2:$2,'Annual CF'!H$1,'Monthly CF'!$1:$1,"<="&Summary!$K$19) -> 0 | I58: =SUMIFS('Monthly CF'!59:59,'Monthly CF'!$2:$2,'Annual CF'!I$1,'Monthly CF'!$1:$1,"<="&Summary!$K$19) -> 0 | J58: =SUMIFS('Monthly CF'!59:59,'Monthly CF'!$2:$2,'Annual CF'!J$1,'Monthly CF'!$1:$1,"<="&Summary!$K$19) -> 0 | K58: =SUMIFS('Monthly CF'!59:59,'Monthly CF'!$2:$2,'Annual CF'!K$1,'Monthly CF'!$1:$1,"<="&Summary!$K$19) -> 0 | ... M58: =SUMIFS('Monthly CF'!59:59,'Monthly CF'!$2:$2,'Annual CF'!M$1,'Monthly CF'!$1:$1,"<="&Summary!$K$19) -> 0
B60: Acquisition & Sale Information
A61: =SUM(C61:M61) -> -40000000 | B61: Purchase Price | C61: =-Summary!B20 -> -40000000
A62: =SUM(C62:M62) -> -150000 | B62: Closing Costs | C62: =-Summary!B22 -> -150000
A63: =SUM(C63:M63) -> 46643653 | B63: Sale Price | D63: =SUMIFS('Monthly CF'!64:64,'Monthly CF'!$2:$2,'Annual CF'!D$1,'Monthly CF'!$1:$1,"<="&Summary!$K$19) -> 0 | E63: =SUMIFS('Monthly CF'!64:64,'Monthly CF'!$2:$2,'Annual CF'!E$1,'Monthly CF'!$1:$1,"<="&Summary!$K$19) -> 0 | F63: =SUMIFS('Monthly CF'!64:64,'Monthly CF'!$2:$2,'Annual CF'!F$1,'Monthly CF'!$1:$1,"<="&Summary!$K$19) -> 0 | G63: =SUMIFS('Monthly CF'!64:64,'Monthly CF'!$2:$2,'Annual CF'!G$1,'Monthly CF'!$1:$1,"<="&Summary!$K$19) -> 0 | H63: =SUMIFS('Monthly CF'!64:64,'Monthly CF'!$2:$2,'Annual CF'!H$1,'Monthly CF'!$1:$1,"<="&Summary!$K$19) -> 0 | I63: =SUMIFS('Monthly CF'!64:64,'Monthly CF'!$2:$2,'Annual CF'!I$1,'Monthly CF'!$1:$1,"<="&Summary!$K$19) -> 0 | J63: =SUMIFS('Monthly CF'!64:64,'Monthly CF'!$2:$2,'Annual CF'!J$1,'Monthly CF'!$1:$1,"<="&Summary!$K$19) -> 0 | K63: =SUMIFS('Monthly CF'!64:64,'Monthly CF'!$2:$2,'Annual CF'!K$1,'Monthly CF'!$1:$1,"<="&Summary!$K$19) -> 0 | ... M63: =SUMIFS('Monthly CF'!64:64,'Monthly CF'!$2:$2,'Annual CF'!M$1,'Monthly CF'!$1:$1,"<="&Summary!$K$19) -> 46643653
A64: =SUM(C64:M64) -> -1399309.6 | B64: Costs of Sale | D64: =SUMIFS('Monthly CF'!65:65,'Monthly CF'!$2:$2,'Annual CF'!D$1,'Monthly CF'!$1:$1,"<="&Summary!$K$19) -> 0 | E64: =SUMIFS('Monthly CF'!65:65,'Monthly CF'!$2:$2,'Annual CF'!E$1,'Monthly CF'!$1:$1,"<="&Summary!$K$19) -> 0 | F64: =SUMIFS('Monthly CF'!65:65,'Monthly CF'!$2:$2,'Annual CF'!F$1,'Monthly CF'!$1:$1,"<="&Summary!$K$19) -> 0 | G64: =SUMIFS('Monthly CF'!65:65,'Monthly CF'!$2:$2,'Annual CF'!G$1,'Monthly CF'!$1:$1,"<="&Summary!$K$19) -> 0 | H64: =SUMIFS('Monthly CF'!65:65,'Monthly CF'!$2:$2,'Annual CF'!H$1,'Monthly CF'!$1:$1,"<="&Summary!$K$19) -> 0 | I64: =SUMIFS('Monthly CF'!65:65,'Monthly CF'!$2:$2,'Annual CF'!I$1,'Monthly CF'!$1:$1,"<="&Summary!$K$19) -> 0 | J64: =SUMIFS('Monthly CF'!65:65,'Monthly CF'!$2:$2,'Annual CF'!J$1,'Monthly CF'!$1:$1,"<="&Summary!$K$19) -> 0 | K64: =SUMIFS('Monthly CF'!65:65,'Monthly CF'!$2:$2,'Annual CF'!K$1,'Monthly CF'!$1:$1,"<="&Summary!$K$19) -> 0 | ... M64: =SUMIFS('Monthly CF'!65:65,'Monthly CF'!$2:$2,'Annual CF'!M$1,'Monthly CF'!$1:$1,"<="&Summary!$K$19) -> -1399309.6
A66: =SUM(C66:M66) -> 15050611 | B66: Net Levered Cash Flow | C66: =SUM(C46,C49:C52,C57:C58,C61:C64) -> -14710000 | D66: =SUMIFS('Monthly CF'!67:67,'Monthly CF'!$2:$2,'Annual CF'!D$1,'Monthly CF'!$1:$1,"<="&Summary!$K$19) -> -471898.71 | E66: =SUMIFS('Monthly CF'!67:67,'Monthly CF'!$2:$2,'Annual CF'!E$1,'Monthly CF'!$1:$1,"<="&Summary!$K$19) -> 714371.81 | F66: =SUMIFS('Monthly CF'!67:67,'Monthly CF'!$2:$2,'Annual CF'!F$1,'Monthly CF'!$1:$1,"<="&Summary!$K$19) -> 1141526.7 | G66: =SUMIFS('Monthly CF'!67:67,'Monthly CF'!$2:$2,'Annual CF'!G$1,'Monthly CF'!$1:$1,"<="&Summary!$K$19) -> 785997.8 | H66: =SUMIFS('Monthly CF'!67:67,'Monthly CF'!$2:$2,'Annual CF'!H$1,'Monthly CF'!$1:$1,"<="&Summary!$K$19) -> 5488657.1 | I66: =SUMIFS('Monthly CF'!67:67,'Monthly CF'!$2:$2,'Annual CF'!I$1,'Monthly CF'!$1:$1,"<="&Summary!$K$19) -> 1214113.5 | J66: =SUMIFS('Monthly CF'!67:67,'Monthly CF'!$2:$2,'Annual CF'!J$1,'Monthly CF'!$1:$1,"<="&Summary!$K$19) -> 1286536.9 | K66: =SUMIFS('Monthly CF'!67:67,'Monthly CF'!$2:$2,'Annual CF'!K$1,'Monthly CF'!$1:$1,"<="&Summary!$K$19) -> 1361133 | ... M66: =SUMIFS('Monthly CF'!67:67,'Monthly CF'!$2:$2,'Annual CF'!M$1,'Monthly CF'!$1:$1,"<="&Summary!$K$19) -> 17320901
B68: Cash-on-Cash Return | D68: =SUM(D54,D58)/ABS(SUMIF($C$66:C66,"<"&0,$C$66:C66)) -> -0.03208013 | E68: =SUM(E54,E58)/ABS(SUMIF($C$66:D66,"<"&0,$C$66:D66)) -> 0.047054181 | F68: =SUM(F54,F58)/ABS(SUMIF($C$66:E66,"<"&0,$C$66:E66)) -> 0.075189981 | G68: =SUM(G54,G58)/ABS(SUMIF($C$66:F66,"<"&0,$C$66:F66)) -> 0.051772035 | H68: =SUM(H54,H58)/ABS(SUMIF($C$66:G66,"<"&0,$C$66:G66)) -> 0.056268575 | I68: =SUM(I54,I58)/ABS(SUMIF($C$66:H66,"<"&0,$C$66:H66)) -> 0.079971125 | J68: =SUM(J54,J58)/ABS(SUMIF($C$66:I66,"<"&0,$C$66:I66)) -> 0.084741503 | K68: =SUM(K54,K58)/ABS(SUMIF($C$66:J66,"<"&0,$C$66:J66)) -> 0.089654993 | ... M68: =SUM(M54,M58)/ABS(SUMIF($C$66:L66,"<"&0,$C$66:L66)) -> 0.065763247
